Workbook

Sheet 29
A1: MLHUILLIER PHILIPPINES
A2: BILLS PAYMENT REPORT
A3: Report Date : AUGUST 2025
F4: MLKP7 | J4: Cancelled (web) | N4: Net Total Trxns | R4: Billed Amount | V4: Current Variance
A5: No. | B5: Partner's Name | C5: Banks | D5: CHARGING TYPE | F5: Vol | G5: Principal | H5: Charge | J5: Vol | K5: Principal | L5: Charge | N5: Vol | O5: Principal | P5: Charge | R5: Vol | S5: Amount | T5: Charge | V5: Vol | W5: Amount
A6: 1 | B6: 123 LENDING CORPORATION | C6: BDO | D6: Customer | F6: 8 | G6: 109814 | H6: 800 | J6: 0 | K6: 0 | L6: 0 | N6: 8 | O6: 109814 | P6: 800 | R6: 0 | S6: 0 | T6: 0 | V6: 8 | W6: 109814
A7: 2 | B7: A-1 MILLING CORPORATION | C7: METROBANK | D7: Customer | F7: 4 | G7: 651400 | H7: 350 | J7: 0 | K7: 0 | L7: 0 | N7: 4 | O7: 651400 | P7: 350 | R7: 0 | S7: 0 | T7: 0 | V7: 4 | W7: 651400
A8: 3 | B8: A2M GLOBAL DISTRIBUTION INC. | C8: METROBANK | D8: Partner | F8: 6 | G8: 97977.82 | H8: 300 | J8: 0 | K8: 0 | L8: 0 | N8: 6 | O8: 97977.82 | P8: 300 | R8: 0 | S8: 0 | T8: 0 | V8: 6 | W8: 97977.82
A9: 4 | B9: ABEJO WATERS CORP - CEBU | C9: BPI ONLINE | D9: Customer | F9: 0 | G9: 0 | H9: 0 | J9: 0 | K9: 0 | L9: 0 | N9: 0 | O9: 0 | P9: 0 | R9: 0 | S9: 0 | T9: 0 | V9: 0 | W9: 0
A10: 5 | B10: ABEJO WATERS CORP - TALISAY | C10: CHINABANK | D10: Customer | F10: 0 | G10: 0 | H10: 0 | J10: 0 | K10: 0 | L10: 0 | N10: 0 | O10: 0 | P10: 0 | R10: 0 | S10: 0 | T10: 0 | V10: 0 | W10: 0
A11: 6 | B11: AEON CREDIT SERVICE PHIL INC. API | C11: METROBANK | D11: Customer | F11: 7 | G11: 17562.38 | H11: 105 | J11: 0 | K11: 0 | L11: 0 | N11: 7 | O11: 17562.38 | P11: 105 | R11: 0 | S11: 0 | T11: 0 | V11: 7 | W11: 17562.38
A12: 7 | B12: AF PAYMENTS (BEEP LOADING) | C12: BPI CHECK | D12: Customer | F12: 0 | G12: 0 | H12: 0 | J12: 0 | K12: 0 | L12: 0 | N12: 0 | O12: 0 | P12: 0 | R12: 0 | S12: 0 | T12: 0 | V12: 0 | W12: 0
A13: 8 | B13: AIA PHILIPPINES | C13: BPI | D13: Customer | F13: 8 | G13: 79687 | H13: 200 | J13: 0 | K13: 0 | L13: 0 | N13: 8 | O13: 79687 | P13: 200 | R13: 0 | S13: 0 | T13: 0 | V13: 8 | W13: 79687
A14: 9 | B14: AIR ASIA/ZEST AIR | C14: BDO | D14: Partner | F14: 4 | G14: 17588.96 | H14: 80 | J14: 0 | K14: 0 | L14: 0 | N14: 4 | O14: 17588.96 | P14: 80 | R14: 0 | S14: 0 | T14: 0 | V14: 4 | W14: 17588.96
A15: 10 | B15: AIR YOU GO TRAVEL PHILS CO. | C15: BDO | D15: Customer | F15: 0 | G15: 0 | H15: 0 | J15: 0 | K15: 0 | L15: 0 | N15: 0 | O15: 0 | P15: 0 | R15: 0 | S15: 0 | T15: 0 | V15: 0 | W15: 0
A16: 11 | B16: AKLAN CABLE NETWORK, INC. - LEMERY | D16: Customer | F16: 0 | G16: 0 | H16: 0 | J16: 0 | K16: 0 | L16: 0 | N16: 0 | O16: 0 | P16: 0 | R16: 0 | S16: 0 | T16: 0 | V16: 0 | W16: 0
A17: 12 | B17: ALFA- ALL FOOD ASIA, INC. | C17: METROBANK | D17: Customer | F17: 0 | G17: 0 | H17: 0 | J17: 0 | K17: 0 | L17: 0 | N17: 0 | O17: 0 | P17: 0 | R17: 0 | S17: 0 | T17: 0 | V17: 0 | W17: 0
A18: 13 | B18: AMBROSIA PHILS INC | C18: METROBANK | D18: Partner | F18: 56 | G18: 1155780.3 | H18: 1650 | J18: 0 | K18: 0 | L18: 0 | N18: 56 | O18: 1155780.3 | P18: 1650 | R18: 0 | S18: 0 | T18: 0 | V18: 56 | W18: 1155780.3
A19: 14 | B19: ANECO | C19: BPI | D19: Customer | F19: 11 | G19: 36783.03 | H19: 55 | J19: 0 | K19: 0 | L19: 0 | N19: 11 | O19: 36783.03 | P19: 55 | R19: 0 | S19: 0 | T19: 0 | V19: 11 | W19: 36783.03
A20: 15 | B20: ANECO COLLECTIONS | C20: BPI | D20: Customer | F20: 0 | G20: 0 | H20: 0 | J20: 0 | K20: 0 | L20: 0 | N20: 0 | O20: 0 | P20: 0 | R20: 0 | S20: 0 | T20: 0 | V20: 0 | W20: 0
A21: 16 | B21: ANGELES CITY WATER DISTRICT | C21: LANBANK | D21: Customer | F21: 0 | G21: 0 | H21: 0 | J21: 0 | K21: 0 | L21: 0 | N21: 0 | O21: 0 | P21: 0 | R21: 0 | S21: 0 | T21: 0 | V21: 0 | W21: 0
A22: 17 | B22: AQUA CENTRO MWPV CORP. | C22: BPI ONLINE | D22: CusPart | F22: 0 | G22: 0 | H22: 0 | J22: 0 | K22: 0 | L22: 0 | N22: 0 | O22: 0 | P22: 0 | R22: 0 | S22: 0 | T22: 0 | V22: 0 | W22: 0
A23: 18 | B23: ASIALINK FINANCE CORPORATION | C23: BDO | D23: Partner M. | F23: 605 | G23: 12351943 | H23: 10176 | J23: 0 | K23: 0 | L23: 0 | N23: 605 | O23: 12351943 | P23: 10176 | R23: 0 | S23: 0 | T23: 0 | V23: 605 | W23: 12351943
A24: 19 | B24: ASIAN COLLEGE OF SCIENCE AND TECHNOLOGY FDN. INC. | C24: BPI ONLINE | D24: Customer | F24: 0 | G24: 0 | H24: 0 | J24: 0 | K24: 0 | L24: 0 | N24: 0 | O24: 0 | P24: 0 | R24: 0 | S24: 0 | T24: 0 | V24: 0 | W24: 0
A25: 20 | B25: ASIAN COLLEGE OF TECHNOLOGY (ACT) | D25: Customer | F25: 0 | G25: 0 | H25: 0 | J25: 0 | K25: 0 | L25: 0 | N25: 0 | O25: 0 | P25: 0 | R25: 0 | S25: 0 | T25: 0 | V25: 0 | W25: 0
A26: 21 | B26: ASIAN INTERNATIONAL SCHOOL OF AERONAUTICS AND TECHNOLOGY (AISAT) CORP. | C26: METROBANK | D26: Customer | F26: 0 | G26: 0 | H26: 0 | J26: 0 | K26: 0 | L26: 0 | N26: 0 | O26: 0 | P26: 0 | R26: 0 | S26: 0 | T26: 0 | V26: 0 | W26: 0
A27: 22 | B27: ATENEO DE DAVAO UNIVERSITY | C27: PNB | D27: Customer | F27: 0 | G27: 0 | H27: 0 | J27: 0 | K27: 0 | L27: 0 | N27: 0 | O27: 0 | P27: 0 | R27: 0 | S27: 0 | T27: 0 | V27: 0 | W27: 0
A28: 23 | B28: ATENEO DE ZAMBOANGA UNIVERSITY | C28: METROBANK | D28: Customer | F28: 0 | G28: 0 | H28: 0 | J28: 0 | K28: 0 | L28: 0 | N28: 0 | O28: 0 | P28: 0 | R28: 0 | S28: 0 | T28: 0 | V28: 0 | W28: 0
A29: 24 | B29: ATLAS CEBU CORN MILL CORP | C29: CHINABANK | D29: Customer | F29: 6 | G29: 239025 | H29: 300 | J29: 0 | K29: 0 | L29: 0 | N29: 6 | O29: 239025 | P29: 300 | R29: 0 | S29: 0 | T29: 0 | V29: 6 | W29: 239025
A30: 25 | B30: BAKERS BEST MARKETING CORPORATION | C30: BPI | D30: Customer | F30: 3 | G30: 18925 | H30: 90 | J30: 0 | K30: 0 | L30: 0 | N30: 3 | O30: 18925 | P30: 90 | R30: 0 | S30: 0 | T30: 0 | V30: 3 | W30: 18925
A31: 26 | B31: BALAMBAN ENERZONE | D31: No Billers | F31: 0 | G31: 0 | H31: 0 | J31: 0 | K31: 0 | L31: 0 | N31: 0 | O31: 0 | P31: 0 | R31: 0 | S31: 0 | T31: 0 | V31: 0 | W31: 0
A32: 27 | B32: BALAMBAN WATER DISTRICT | C32: LANBANK | D32: Customer | F32: 14 | G32: 8218.85 | H32: 140 | J32: 0 | K32: 0 | L32: 0 | N32: 14 | O32: 8218.85 | P32: 140 | R32: 0 | S32: 0 | T32: 0 | V32: 14 | W32: 8218.85
A33: 28 | B33: BASIC WATER ENTERPRISES INC. | C33: METROBANK | D33: Partner | F33: 0 | G33: 0 | H33: 0 | J33: 0 | K33: 0 | L33: 0 | N33: 0 | O33: 0 | P33: 0 | R33: 0 | S33: 0 | T33: 0 | V33: 0 | W33: 0
A34: 29 | B34: BATANGAS CATV, INC. - BATANGAS | D34: Customer | F34: 0 | G34: 0 | H34: 0 | J34: 0 | K34: 0 | L34: 0 | N34: 0 | O34: 0 | P34: 0 | R34: 0 | S34: 0 | T34: 0 | V34: 0 | W34: 0
A35: 30 | B35: BATANGAS CATV, INC. - BAUAN | D35: Customer | F35: 0 | G35: 0 | H35: 0 | J35: 0 | K35: 0 | L35: 0 | N35: 0 | O35: 0 | P35: 0 | R35: 0 | S35: 0 | T35: 0 | V35: 0 | W35: 0
A36: 31 | B36: BAYAD CENTER - NBI | D36: No Billers | F36: 0 | G36: 0 | H36: 0 | J36: 0 | K36: 0 | L36: 0 | N36: 0 | O36: 0 | P36: 0 | R36: 0 | S36: 0 | T36: 0 | V36: 0 | W36: 0
A37: 32 | B37: BAYAN TELECOMMUNICATIONS INC | C37: BDO | D37: CusPart | F37: 0 | G37: 0 | H37: 0 | J37: 0 | K37: 0 | L37: 0 | N37: 0 | O37: 0 | P37: 0 | R37: 0 | S37: 0 | T37: 0 | V37: 0 | W37: 0
A38: 33 | B38: BBBROTHERS DV GEN. MDSE INC | C38: BDO ONLINE | D38: Customer | F38: 1 | G38: 9835 | H38: 30 | J38: 0 | K38: 0 | L38: 0 | N38: 1 | O38: 9835 | P38: 30 | R38: 0 | S38: 0 | T38: 0 | V38: 1 | W38: 9835
A39: 34 | B39: BBBROTHERS LAGUNA INC 001 | C39: BDO ONLINE | D39: Customer | F39: 0 | G39: 0 | H39: 0 | J39: 0 | K39: 0 | L39: 0 | N39: 0 | O39: 0 | P39: 0 | R39: 0 | S39: 0 | T39: 0 | V39: 0 | W39: 0
A40: 35 | B40: BBBROTHERS LAGUNA INC 002 | C40: BDO ONLINE | D40: Customer | F40: 0 | G40: 0 | H40: 0 | J40: 0 | K40: 0 | L40: 0 | N40: 0 | O40: 0 | P40: 0 | R40: 0 | S40: 0 | T40: 0 | V40: 0 | W40: 0
A41: 36 | B41: BBBROTHERS MASBATE GEN. MDSE INC | C41: BDO ONLINE | D41: Customer | F41: 1 | G41: 10720 | H41: 30 | J41: 0 | K41: 0 | L41: 0 | N41: 1 | O41: 10720 | P41: 30 | R41: 0 | S41: 0 | T41: 0 | V41: 1 | W41: 10720
A42: 37 | B42: BBBROTHERS MINDANAO INC 001 | C42: BDO ONLINE | D42: Customer | F42: 0 | G42: 0 | H42: 0 | J42: 0 | K42: 0 | L42: 0 | N42: 0 | O42: 0 | P42: 0 | R42: 0 | S42: 0 | T42: 0 | V42: 0 | W42: 0
A43: 38 | B43: BBBROTHERS MINDANAO INC 002 | C43: BDO ONLINE | D43: Customer | F43: 0 | G43: 0 | H43: 0 | J43: 0 | K43: 0 | L43: 0 | N43: 0 | O43: 0 | P43: 0 | R43: 0 | S43: 0 | T43: 0 | V43: 0 | W43: 0
A44: 39 | B44: BBBROTHERS PHIL-BDO | C44: BDO | D44: Customer | F44: 0 | G44: 0 | H44: 0 | J44: 0 | K44: 0 | L44: 0 | N44: 0 | O44: 0 | P44: 0 | R44: 0 | S44: 0 | T44: 0 | V44: 0 | W44: 0
A45: 40 | B45: BBBROTHERS PHIL-BPI | C45: BPI | D45: Customer | F45: 0 | G45: 0 | H45: 0 | J45: 0 | K45: 0 | L45: 0 | N45: 0 | O45: 0 | P45: 0 | R45: 0 | S45: 0 | T45: 0 | V45: 0 | W45: 0
A46: 41 | B46: BBBROTHERS PHIL-DV/PNB | C46: PNB | D46: Customer | F46: 0 | G46: 0 | H46: 0 | J46: 0 | K46: 0 | L46: 0 | N46: 0 | O46: 0 | P46: 0 | R46: 0 | S46: 0 | T46: 0 | V46: 0 | W46: 0
A47: 42 | B47: BBBROTHERS PHILIPPINES INC 001 | C47: BDO ONLINE | D47: Customer | F47: 22 | G47: 208356 | H47: 660 | J47: 0 | K47: 0 | L47: 0 | N47: 22 | O47: 208356 | P47: 660 | R47: 0 | S47: 0 | T47: 0 | V47: 22 | W47: 208356
A48: 43 | B48: BBBROTHERS PHILLIPINES INC 002 | C48: BDO ONLINE | D48: Customer | F48: 14 | G48: 170643 | H48: 420 | J48: 0 | K48: 0 | L48: 0 | N48: 14 | O48: 170643 | P48: 420 | R48: 0 | S48: 0 | T48: 0 | V48: 14 | W48: 170643
... A54: 49 | B54: BDMPC-MAIN OFFICE | C54: BDO | D54: Customer | F54: 0 | G54: 0 | H54: 0 | J54: 0 | K54: 0 | L54: 0 | N54: 0 | O54: 0 | P54: 0 | R54: 0 | S54: 0 | T54: 0 | V54: 0 | W54: 0
A55: 50 | B55: BDMPC-PANGLAO | D55: Customer | F55: 0 | G55: 0 | H55: 0 | J55: 0 | K55: 0 | L55: 0 | N55: 0 | O55: 0 | P55: 0 | R55: 0 | S55: 0 | T55: 0 | V55: 0 | W55: 0
A56: 51 | B56: BDMPC-TUBIGON | C56: METROBANK | D56: Customer | F56: 0 | G56: 0 | H56: 0 | J56: 0 | K56: 0 | L56: 0 | N56: 0 | O56: 0 | P56: 0 | R56: 0 | S56: 0 | T56: 0 | V56: 0 | W56: 0
A57: 52 | B57: BDMPC-UBAY | C57: PNB | D57: Customer | F57: 0 | G57: 0 | H57: 0 | J57: 0 | K57: 0 | L57: 0 | N57: 0 | O57: 0 | P57: 0 | R57: 0 | S57: 0 | T57: 0 | V57: 0 | W57: 0
A58: 53 | B58: BENEDICTO COLLEGE INC | D58: Customer | F58: 0 | G58: 0 | H58: 0 | J58: 0 | K58: 0 | L58: 0 | N58: 0 | O58: 0 | P58: 0 | R58: 0 | S58: 0 | T58: 0 | V58: 0 | W58: 0
A59: 54 | B59: BICOL JL AGRI CORP | C59: METROBANK | D59: Partner | F59: 0 | G59: 0 | H59: 0 | J59: 0 | K59: 0 | L59: 0 | N59: 0 | O59: 0 | P59: 0 | R59: 0 | S59: 0 | T59: 0 | V59: 0 | W59: 0
A60: 55 | B60: BILIRAN TELE TV NETWORK CORP | C60: AUB | D60: partner daily | F60: 1 | G60: 660 | H60: 20 | J60: 0 | K60: 0 | L60: 0 | N60: 1 | O60: 660 | P60: 20 | R60: 0 | S60: 0 | T60: 0 | V60: 1 | W60: 660
A61: 56 | B61: BIYAHEKO.COM CORPORATION | C61: BPI | D61: Customer | F61: 2 | G61: 18950 | H61: 100 | J61: 0 | K61: 0 | L61: 0 | N61: 2 | O61: 18950 | P61: 100 | R61: 0 | S61: 0 | T61: 0 | V61: 2 | W61: 18950
A62: 57 | B62: BNSC/BOHOL NORTHERN STAR COLLEGE | D62: Customer | F62: 0 | G62: 0 | H62: 0 | J62: 0 | K62: 0 | L62: 0 | N62: 0 | O62: 0 | P62: 0 | R62: 0 | S62: 0 | T62: 0 | V62: 0 | W62: 0
A63: 58 | B63: BOARDWALK BUSINESS VENTURES | C63: SECURITY | D63: Customer | F63: 0 | G63: 0 | H63: 0 | J63: 0 | K63: 0 | L63: 0 | N63: 0 | O63: 0 | P63: 0 | R63: 0 | S63: 0 | T63: 0 | V63: 0 | W63: 0
A64: 59 | B64: BOHECO 1 | C64: SECURITY BANK | D64: Customer | F64: 69 | G64: 168070.44 | H64: 690 | J64: 0 | K64: 0 | L64: 0 | N64: 69 | O64: 168070.44 | P64: 690 | R64: 0 | S64: 0 | T64: 0 | V64: 69 | W64: 168070.44
A65: 60 | B65: BOHECO 2 | C65: METROBANK | D65: Customer | F65: 14 | G65: 22461.52 | H65: 70 | J65: 0 | K65: 0 | L65: 0 | N65: 14 | O65: 22461.52 | P65: 70 | R65: 0 | S65: 0 | T65: 0 | V65: 14 | W65: 22461.52
A66: 61 | B66: BOHOL LIGHTS INC | C66: SECURITY BANK | D66: Customer | F66: 215 | G66: 808215.42 | H66: 2150 | J66: -2 | K66: -7037.27 | L66: -20 | N66: 213 | O66: 801178.15 | P66: 2130 | R66: 0 | S66: 0 | T66: 0 | V66: 213 | W66: 801178.15
A67: 62 | B67: BOHOL NORTHERNEASTERN EDUCATION FOUNDATION INC. | D67: Customer | F67: 0 | G67: 0 | H67: 0 | J67: 0 | K67: 0 | L67: 0 | N67: 0 | O67: 0 | P67: 0 | R67: 0 | S67: 0 | T67: 0 | V67: 0 | W67: 0
A68: 63 | B68: BOHOL WATER UTILITIES INC. | C68: SECURITY BANK | D68: Customer | F68: 55 | G68: 43853.46 | H68: 550 | J68: 0 | K68: 0 | L68: 0 | N68: 55 | O68: 43853.46 | P68: 550 | R68: 0 | S68: 0 | T68: 0 | V68: 55 | W68: 43853.46
A69: 64 | B69: BONJOUR TRAVEL AND TOURS | C69: bpi online | D69: Partner | F69: 0 | G69: 0 | H69: 0 | J69: 0 | K69: 0 | L69: 0 | N69: 0 | O69: 0 | P69: 0 | R69: 0 | S69: 0 | T69: 0 | V69: 0 | W69: 0
A70: 65 | B70: BOSTON FINANCE INVESTMENT CORP. | C70: CHINABANK | D70: Customer | F70: 0 | G70: 0 | H70: 0 | J70: 0 | K70: 0 | L70: 0 | N70: 0 | O70: 0 | P70: 0 | R70: 0 | S70: 0 | T70: 0 | V70: 0 | W70: 0
A71: 66 | B71: BOTICARD | C71: BPI | D71: Partner | F71: 2 | G71: 17311 | H71: 60 | J71: 0 | K71: 0 | L71: 0 | N71: 2 | O71: 17311 | P71: 60 | R71: 0 | S71: 0 | T71: 0 | V71: 2 | W71: 17311
A72: 67 | B72: BOUNTY PLUS - LUZON (PROVINCIAL FRESH LUZON) | C72: BPI CHECK | D72: PARTNER DAILY | F72: 0 | G72: 0 | H72: 0 | J72: 0 | K72: 0 | L72: 0 | N72: 0 | O72: 0 | P72: 0 | R72: 0 | S72: 0 | T72: 0 | V72: 0 | W72: 0
A73: 68 | B73: BOUNTY PLUS - MINDANAO (PROVINCIAL FRESH MINDANAO) | C73: SECURITY BANK | D73: Partner | F73: 17 | G73: 1287851.8 | H73: 1400 | J73: 0 | K73: 0 | L73: 0 | N73: 17 | O73: 1287851.8 | P73: 1400 | R73: 0 | S73: 0 | T73: 0 | V73: 17 | W73: 1287851.8
A74: 69 | B74: BOUNTY PLUS - VISAYAS (PROVINCIAL FRESH VISAYAS) | C74: BDO CHECK | D74: Partner | F74: 54 | G74: 1986273.8 | H74: 3000 | J74: 0 | K74: 0 | L74: 0 | N74: 54 | O74: 1986273.8 | P74: 3000 | R74: 0 | S74: 0 | T74: 0 | V74: 54 | W74: 1986273.8
A75: 70 | B75: BP WATERWORKS | C75: BDO | D75: Partner M. | F75: 114 | G75: 83383.19 | H75: 912 | J75: 0 | K75: 0 | L75: 0 | N75: 114 | O75: 83383.19 | P75: 912 | R75: 0 | S75: 0 | T75: 0 | V75: 114 | W75: 83383.19
A76: 71 | B76: BREAD AND MORE INC. | C76: METROBANK | D76: Partner | F76: 15 | G76: 397726 | H76: 450 | J76: 0 | K76: 0 | L76: 0 | N76: 15 | O76: 397726 | P76: 450 | R76: 0 | S76: 0 | T76: 0 | V76: 15 | W76: 397726
A77: 72 | B77: BREAD AREA INC. | C77: METROBANK | D77: Partner | F77: 0 | G77: 0 | H77: 0 | J77: 0 | K77: 0 | L77: 0 | N77: 0 | O77: 0 | P77: 0 | R77: 0 | S77: 0 | T77: 0 | V77: 0 | W77: 0
A78: 73 | B78: BREAD BY PATTY CORPORATION | C78: CHINABANK | D78: Partner | F78: 22 | G78: 156205 | H78: 660 | J78: 0 | K78: 0 | L78: 0 | N78: 22 | O78: 156205 | P78: 660 | R78: 0 | S78: 0 | T78: 0 | V78: 22 | W78: 156205
A79: 74 | B79: BREADPOINT | C79: METROBANK | D79: Customer | F79: 26 | G79: 252950 | H79: 1040 | J79: 0 | K79: 0 | L79: 0 | N79: 26 | O79: 252950 | P79: 1040 | R79: 0 | S79: 0 | T79: 0 | V79: 26 | W79: 252950
... A112: 107 | B112: CHARISSA'S FOOD ENTERPRISE | C112: eastwest | D112: Customer | F112: 0 | G112: 0 | H112: 0 | J112: 0 | K112: 0 | L112: 0 | N112: 0 | O112: 0 | P112: 0 | R112: 0 | S112: 0 | T112: 0 | V112: 0 | W112: 0
A113: 108 | B113: CHARLES CATV SYSTEMS, INC. | D113: Customer | F113: 0 | G113: 0 | H113: 0 | J113: 0 | K113: 0 | L113: 0 | N113: 0 | O113: 0 | P113: 0 | R113: 0 | S113: 0 | T113: 0 | V113: 0 | W113: 0
A114: 109 | B114: CHARLES PEAK | C114: BPI | D114: Customer | F114: 7 | G114: 3823 | H114: 70 | J114: 0 | K114: 0 | L114: 0 | N114: 7 | O114: 3823 | P114: 70 | R114: 0 | S114: 0 | T114: 0 | V114: 7 | W114: 3823
A115: 110 | B115: CHICKEN ESSENTIALS, INC | C115: SECURITY BANK | D115: Partner | F115: 0 | G115: 0 | H115: 0 | J115: 0 | K115: 0 | L115: 0 | N115: 0 | O115: 0 | P115: 0 | R115: 0 | S115: 0 | T115: 0 | V115: 0 | W115: 0
A116: 111 | B116: CHICKY OINK | C116: CHINABANK | D116: Partner | F116: 63 | G116: 1075775 | H116: 1895 | J116: 0 | K116: 0 | L116: 0 | N116: 63 | O116: 1075775 | P116: 1895 | R116: 0 | S116: 0 | T116: 0 | V116: 63 | W116: 1075775
A117: 112 | B117: CHOOKS TO GO | C117: BDO | D117: Partner | F117: 0 | G117: 0 | H117: 0 | J117: 0 | K117: 0 | L117: 0 | N117: 0 | O117: 0 | P117: 0 | R117: 0 | S117: 0 | T117: 0 | V117: 0 | W117: 0
A118: 113 | B118: CHOOKS TO GO PILIPINAS | C118: CHINABANK | D118: partner daily | F118: 289 | G118: 4956347.9 | H118: 11760 | J118: 0 | K118: 0 | L118: 0 | N118: 289 | O118: 4956347.9 | P118: 11760 | R118: 0 | S118: 0 | T118: 0 | V118: 289 | W118: 4956347.9
A119: 114 | B119: CIS BAYAD CENTER INC. | C119: BDO | D119: Partner M. | F119: 2723 | G119: 5547497 | H119: 15314 | J119: 0 | K119: 0 | L119: 0 | N119: 2723 | O119: 5547497 | P119: 15314 | R119: 0 | S119: 0 | T119: 0 | V119: 2723 | W119: 5547497
A120: 115 | B120: CITY SAVINGS BANK | C120: UNION BANK | D120: Partner M. | F120: 765 | G120: 4175452.5 | H120: 38250 | J120: 0 | K120: 0 | L120: 0 | N120: 765 | O120: 4175452.5 | P120: 38250 | R120: 0 | S120: 0 | T120: 0 | V120: 765 | W120: 4175452.5
A121: 116 | B121: CLAVER TV AND INTERNET SERVICES | C121: METROBANK | D121: Customer | F121: 3 | G121: 3647 | H121: 50 | J121: 0 | K121: 0 | L121: 0 | N121: 3 | O121: 3647 | P121: 50 | R121: 0 | S121: 0 | T121: 0 | V121: 3 | W121: 3647
A122: 117 | B122: COLEGIO DE DAGUPAN | D122: Customer | F122: 0 | G122: 0 | H122: 0 | J122: 0 | K122: 0 | L122: 0 | N122: 0 | O122: 0 | P122: 0 | R122: 0 | S122: 0 | T122: 0 | V122: 0 | W122: 0
A123: 118 | B123: COLEGIO SAN AGUSTIN - BACOLOD | C123: BPI | D123: Customer | F123: 14 | G123: 263278.36 | H123: 420 | J123: 0 | K123: 0 | L123: 0 | N123: 14 | O123: 263278.36 | P123: 420 | R123: 0 | S123: 0 | T123: 0 | V123: 14 | W123: 263278.36
A124: 119 | B124: COLLEGE OF TECHNOLOGICAL SCIENCES CEBU INC. | C124: METROBANK | D124: Customer | F124: 0 | G124: 0 | H124: 0 | J124: 0 | K124: 0 | L124: 0 | N124: 0 | O124: 0 | P124: 0 | R124: 0 | S124: 0 | T124: 0 | V124: 0 | W124: 0
A125: 120 | B125: COLUMBAN MISSIONARY FOUNDATION INC. | C125: EASTWEST BANK | D125: Customer | F125: 0 | G125: 0 | H125: 0 | J125: 0 | K125: 0 | L125: 0 | N125: 0 | O125: 0 | P125: 0 | R125: 0 | S125: 0 | T125: 0 | V125: 0 | W125: 0
A126: 121 | B126: COMMUNITY ECONOMIC VENTURES INC. | C126: BPI | D126: Customer | F126: 0 | G126: 0 | H126: 0 | J126: 0 | K126: 0 | L126: 0 | N126: 0 | O126: 0 | P126: 0 | R126: 0 | S126: 0 | T126: 0 | V126: 0 | W126: 0
A127: 122 | B127: COMPASIA TECHNOLOGY PHILIPPINES INC. | C127: METROBANK | D127: Customer | F127: 0 | G127: 0 | H127: 0 | J127: 0 | K127: 0 | L127: 0 | N127: 0 | O127: 0 | P127: 0 | R127: 0 | S127: 0 | T127: 0 | V127: 0 | W127: 0
A128: 123 | B128: COOPERATIVE BANK OF CEBU (COOPBANK) | C128: BANK OF COMMERCE | D128: Customer | F128: 17 | G128: 31564.19 | H128: 680 | J128: 0 | K128: 0 | L128: 0 | N128: 17 | O128: 31564.19 | P128: 680 | R128: 0 | S128: 0 | T128: 0 | V128: 17 | W128: 31564.19
A129: 124 | B129: COR JESU COLLEGE. | C129: METROBANK | D129: Customer | F129: 0 | G129: 0 | H129: 0 | J129: 0 | K129: 0 | L129: 0 | N129: 0 | O129: 0 | P129: 0 | R129: 0 | S129: 0 | T129: 0 | V129: 0 | W129: 0
A130: 125 | B130: COTABATO ELECTRIC COOPERATIVE, INC. (COTELCO)-MATALAM | C130: METROBANK | D130: Customer | F130: 181 | G130: 262698.41 | H130: 1448 | J130: 0 | K130: 0 | L130: 0 | N130: 181 | O130: 262698.41 | P130: 1448 | R130: 0 | S130: 0 | T130: 0 | V130: 181 | W130: 262698.41
A131: 126 | B131: COTABATO LIGHTS | C131: BDO | D131: Partner M. | F131: 44 | G131: 68979.56 | H131: 396 | J131: 0 | K131: 0 | L131: 0 | N131: 44 | O131: 68979.56 | P131: 396 | R131: 0 | S131: 0 | T131: 0 | V131: 44 | W131: 68979.56
A132: 127 | B132: COTELCO-MATALAM COLLECTIONS | C132: METROBANK | D132: Customer | F132: 3 | G132: 713009.67 | H132: 375 | J132: 0 | K132: 0 | L132: 0 | N132: 3 | O132: 713009.67 | P132: 375 | R132: 0 | S132: 0 | T132: 0 | V132: 3 | W132: 713009.67
A133: 128 | B133: COVERBEST DISTRIBUTIONS CORPORATION | C133: SECURITY BANK | D133: Customer | F133: 1 | G133: 37725 | H133: 30 | J133: 0 | K133: 0 | L133: 0 | N133: 1 | O133: 37725 | P133: 30 | R133: 0 | S133: 0 | T133: 0 | V133: 1 | W133: 37725
A134: 129 | B134: CSW - ILOILO INC. | C134: LANBANK | D134: Customer | F134: 0 | G134: 0 | H134: 0 | J134: 0 | K134: 0 | L134: 0 | N134: 0 | O134: 0 | P134: 0 | R134: 0 | S134: 0 | T134: 0 | V134: 0 | W134: 0
... A142: 137 | B142: DITO TELECOMMUNITY CORPORATION | C142: unionbank | D142: Customer | F142: 1 | G142: 388.33 | H142: 10 | J142: 0 | K142: 0 | L142: 0 | N142: 1 | O142: 388.33 | P142: 10 | R142: 0 | S142: 0 | T142: 0 | V142: 1 | W142: 388.33
A143: 138 | B143: DMC COLLEGE FOUNDATION INC. | D143: Customer | F143: 5 | G143: 22000 | H143: 100 | J143: 0 | K143: 0 | L143: 0 | N143: 5 | O143: 22000 | P143: 100 | R143: 0 | S143: 0 | T143: 0 | V143: 5 | W143: 22000
A144: 139 | B144: DOKTORS GENERICS PHARMACY INC | C144: BDO CHECK | D144: Customer | F144: 15 | G144: 195450.72 | H144: 400 | J144: 0 | K144: 0 | L144: 0 | N144: 15 | O144: 195450.72 | P144: 400 | R144: 0 | S144: 0 | T144: 0 | V144: 15 | W144: 195450.72
...

Sheet 30
A1: MLHUILLIER PHILIPPINES
A2: BILLS PAYMENT REPORT
A3: Report Date : AUGUST 2025
F4: MLKP7 | J4: Cancelled (web) | N4: Net Total Trxns | R4: Billed Amount | V4: Current Variance
A5: No. | B5: Partner's Name | C5: Banks | D5: CHARGING TYPE | F5: Vol | G5: Principal | H5: Charge | J5: Vol | K5: Principal | L5: Charge | N5: Vol | O5: Principal | P5: Charge | R5: Vol | S5: Amount | T5: Charge | V5: Vol | W5: Amount
A6: 1 | B6: 123 LENDING CORPORATION | C6: BDO | D6: Customer | F6: 6 | G6: 56049.33 | H6: 600 | J6: 0 | K6: 0 | L6: 0 | N6: 6 | O6: 56049.33 | P6: 600 | R6: 0 | S6: 0 | T6: 0 | V6: 6 | W6: 56049.33
A7: 2 | B7: A-1 MILLING CORPORATION | C7: METROBANK | D7: Customer | F7: 0 | G7: 0 | H7: 0 | J7: 0 | K7: 0 | L7: 0 | N7: 0 | O7: 0 | P7: 0 | R7: 0 | S7: 0 | T7: 0 | V7: 0 | W7: 0
A8: 3 | B8: A2M GLOBAL DISTRIBUTION INC. | C8: METROBANK | D8: Partner | F8: 6 | G8: 87272.07 | H8: 300 | J8: 0 | K8: 0 | L8: 0 | N8: 6 | O8: 87272.07 | P8: 300 | R8: 0 | S8: 0 | T8: 0 | V8: 6 | W8: 87272.07
A9: 4 | B9: ABEJO WATERS CORP - CEBU | C9: BPI ONLINE | D9: Customer | F9: 0 | G9: 0 | H9: 0 | J9: 0 | K9: 0 | L9: 0 | N9: 0 | O9: 0 | P9: 0 | R9: 0 | S9: 0 | T9: 0 | V9: 0 | W9: 0
A10: 5 | B10: ABEJO WATERS CORP - TALISAY | C10: CHINABANK | D10: Customer | F10: 0 | G10: 0 | H10: 0 | J10: 0 | K10: 0 | L10: 0 | N10: 0 | O10: 0 | P10: 0 | R10: 0 | S10: 0 | T10: 0 | V10: 0 | W10: 0
A11: 6 | B11: AEON CREDIT SERVICE PHIL INC. API | C11: METROBANK | D11: Customer | F11: 14 | G11: 39135.45 | H11: 210 | J11: 0 | K11: 0 | L11: 0 | N11: 14 | O11: 39135.45 | P11: 210 | R11: 0 | S11: 0 | T11: 0 | V11: 14 | W11: 39135.45
A12: 7 | B12: AF PAYMENTS (BEEP LOADING) | C12: BPI CHECK | D12: Customer | F12: 0 | G12: 0 | H12: 0 | J12: 0 | K12: 0 | L12: 0 | N12: 0 | O12: 0 | P12: 0 | R12: 0 | S12: 0 | T12: 0 | V12: 0 | W12: 0
A13: 8 | B13: AIA PHILIPPINES | C13: BPI | D13: Customer | F13: 10 | G13: 79233.91 | H13: 250 | J13: 0 | K13: 0 | L13: 0 | N13: 10 | O13: 79233.91 | P13: 250 | R13: 0 | S13: 0 | T13: 0 | V13: 10 | W13: 79233.91
A14: 9 | B14: AIR ASIA/ZEST AIR | C14: BDO | D14: Partner | F14: 6 | G14: 93851.55 | H14: 160 | J14: 0 | K14: 0 | L14: 0 | N14: 6 | O14: 93851.55 | P14: 160 | R14: 0 | S14: 0 | T14: 0 | V14: 6 | W14: 93851.55
A15: 10 | B15: AIR YOU GO TRAVEL PHILS CO. | C15: BDO | D15: Customer | F15: 0 | G15: 0 | H15: 0 | J15: 0 | K15: 0 | L15: 0 | N15: 0 | O15: 0 | P15: 0 | R15: 0 | S15: 0 | T15: 0 | V15: 0 | W15: 0
A16: 11 | B16: AKLAN CABLE NETWORK, INC. - LEMERY | D16: Customer | F16: 0 | G16: 0 | H16: 0 | J16: 0 | K16: 0 | L16: 0 | N16: 0 | O16: 0 | P16: 0 | R16: 0 | S16: 0 | T16: 0 | V16: 0 | W16: 0
A17: 12 | B17: ALFA- ALL FOOD ASIA, INC. | C17: METROBANK | D17: Customer | F17: 0 | G17: 0 | H17: 0 | J17: 0 | K17: 0 | L17: 0 | N17: 0 | O17: 0 | P17: 0 | R17: 0 | S17: 0 | T17: 0 | V17: 0 | W17: 0
A18: 13 | B18: AMBROSIA PHILS INC | C18: METROBANK | D18: Partner | F18: 58 | G18: 1379443.8 | H18: 1825 | J18: 0 | K18: 0 | L18: 0 | N18: 58 | O18: 1379443.8 | P18: 1825 | R18: 0 | S18: 0 | T18: 0 | V18: 58 | W18: 1379443.8
A19: 14 | B19: ANECO | C19: BPI | D19: Customer | F19: 5 | G19: 20349.54 | H19: 25 | J19: 0 | K19: 0 | L19: 0 | N19: 5 | O19: 20349.54 | P19: 25 | R19: 0 | S19: 0 | T19: 0 | V19: 5 | W19: 20349.54
A20: 15 | B20: ANECO COLLECTIONS | C20: BPI | D20: Customer | F20: 0 | G20: 0 | H20: 0 | J20: 0 | K20: 0 | L20: 0 | N20: 0 | O20: 0 | P20: 0 | R20: 0 | S20: 0 | T20: 0 | V20: 0 | W20: 0
A21: 16 | B21: ANGELES CITY WATER DISTRICT | C21: LANBANK | D21: Customer | F21: 0 | G21: 0 | H21: 0 | J21: 0 | K21: 0 | L21: 0 | N21: 0 | O21: 0 | P21: 0 | R21: 0 | S21: 0 | T21: 0 | V21: 0 | W21: 0
A22: 17 | B22: AQUA CENTRO MWPV CORP. | C22: BPI ONLINE | D22: CusPart | F22: 1 | G22: 2000 | H22: 7 | J22: 0 | K22: 0 | L22: 0 | N22: 1 | O22: 2000 | P22: 7 | R22: 0 | S22: 0 | T22: 0 | V22: 1 | W22: 2000
A23: 18 | B23: ASIALINK FINANCE CORPORATION | C23: BDO | D23: Partner M. | F23: 599 | G23: 12391964 | H23: 10080 | J23: 0 | K23: 0 | L23: 0 | N23: 599 | O23: 12391964 | P23: 10080 | R23: 0 | S23: 0 | T23: 0 | V23: 599 | W23: 12391964
A24: 19 | B24: ASIAN COLLEGE OF SCIENCE AND TECHNOLOGY FDN. INC. | C24: BPI ONLINE | D24: Customer | F24: 0 | G24: 0 | H24: 0 | J24: 0 | K24: 0 | L24: 0 | N24: 0 | O24: 0 | P24: 0 | R24: 0 | S24: 0 | T24: 0 | V24: 0 | W24: 0
A25: 20 | B25: ASIAN COLLEGE OF TECHNOLOGY (ACT) | D25: Customer | F25: 0 | G25: 0 | H25: 0 | J25: 0 | K25: 0 | L25: 0 | N25: 0 | O25: 0 | P25: 0 | R25: 0 | S25: 0 | T25: 0 | V25: 0 | W25: 0
A26: 21 | B26: ASIAN INTERNATIONAL SCHOOL OF AERONAUTICS AND TECHNOLOGY (AISAT) CORP. | C26: METROBANK | D26: Customer | F26: 1 | G26: 7700 | H26: 30 | J26: 0 | K26: 0 | L26: 0 | N26: 1 | O26: 7700 | P26: 30 | R26: 0 | S26: 0 | T26: 0 | V26: 1 | W26: 7700
A27: 22 | B27: ATENEO DE DAVAO UNIVERSITY | C27: PNB | D27: Customer | F27: 0 | G27: 0 | H27: 0 | J27: 0 | K27: 0 | L27: 0 | N27: 0 | O27: 0 | P27: 0 | R27: 0 | S27: 0 | T27: 0 | V27: 0 | W27: 0
A28: 23 | B28: ATENEO DE ZAMBOANGA UNIVERSITY | C28: METROBANK | D28: Customer | F28: 0 | G28: 0 | H28: 0 | J28: 0 | K28: 0 | L28: 0 | N28: 0 | O28: 0 | P28: 0 | R28: 0 | S28: 0 | T28: 0 | V28: 0 | W28: 0
A29: 24 | B29: ATLAS CEBU CORN MILL CORP | C29: CHINABANK | D29: Customer | F29: 5 | G29: 395290 | H29: 250 | J29: 0 | K29: 0 | L29: 0 | N29: 5 | O29: 395290 | P29: 250 | R29: 0 | S29: 0 | T29: 0 | V29: 5 | W29: 395290
A30: 25 | B30: BAKERS BEST MARKETING CORPORATION | C30: BPI | D30: Customer | F30: 2 | G30: 9079 | H30: 60 | J30: 0 | K30: 0 | L30: 0 | N30: 2 | O30: 9079 | P30: 60 | R30: 0 | S30: 0 | T30: 0 | V30: 2 | W30: 9079
A31: 26 | B31: BALAMBAN ENERZONE | D31: No Billers | F31: 0 | G31: 0 | H31: 0 | J31: 0 | K31: 0 | L31: 0 | N31: 0 | O31: 0 | P31: 0 | R31: 0 | S31: 0 | T31: 0 | V31: 0 | W31: 0
A32: 27 | B32: BALAMBAN WATER DISTRICT | C32: LANBANK | D32: Customer | F32: 8 | G32: 2636.05 | H32: 80 | J32: 0 | K32: 0 | L32: 0 | N32: 8 | O32: 2636.05 | P32: 80 | R32: 0 | S32: 0 | T32: 0 | V32: 8 | W32: 2636.05
A33: 28 | B33: BASIC WATER ENTERPRISES INC. | C33: METROBANK | D33: Partner | F33: 0 | G33: 0 | H33: 0 | J33: 0 | K33: 0 | L33: 0 | N33: 0 | O33: 0 | P33: 0 | R33: 0 | S33: 0 | T33: 0 | V33: 0 | W33: 0
A34: 29 | B34: BATANGAS CATV, INC. - BATANGAS | D34: Customer | F34: 0 | G34: 0 | H34: 0 | J34: 0 | K34: 0 | L34: 0 | N34: 0 | O34: 0 | P34: 0 | R34: 0 | S34: 0 | T34: 0 | V34: 0 | W34: 0
A35: 30 | B35: BATANGAS CATV, INC. - BAUAN | D35: Customer | F35: 0 | G35: 0 | H35: 0 | J35: 0 | K35: 0 | L35: 0 | N35: 0 | O35: 0 | P35: 0 | R35: 0 | S35: 0 | T35: 0 | V35: 0 | W35: 0
A36: 31 | B36: BAYAD CENTER - NBI | D36: No Billers | F36: 0 | G36: 0 | H36: 0 | J36: 0 | K36: 0 | L36: 0 | N36: 0 | O36: 0 | P36: 0 | R36: 0 | S36: 0 | T36: 0 | V36: 0 | W36: 0
A37: 32 | B37: BAYAN TELECOMMUNICATIONS INC | C37: BDO | D37: CusPart | F37: 0 | G37: 0 | H37: 0 | J37: 0 | K37: 0 | L37: 0 | N37: 0 | O37: 0 | P37: 0 | R37: 0 | S37: 0 | T37: 0 | V37: 0 | W37: 0
A38: 33 | B38: BBBROTHERS DV GEN. MDSE INC | C38: BDO ONLINE | D38: Customer | F38: 2 | G38: 22435 | H38: 60 | J38: 0 | K38: 0 | L38: 0 | N38: 2 | O38: 22435 | P38: 60 | R38: 0 | S38: 0 | T38: 0 | V38: 2 | W38: 22435
A39: 34 | B39: BBBROTHERS LAGUNA INC 001 | C39: BDO ONLINE | D39: Customer | F39: 0 | G39: 0 | H39: 0 | J39: 0 | K39: 0 | L39: 0 | N39: 0 | O39: 0 | P39: 0 | R39: 0 | S39: 0 | T39: 0 | V39: 0 | W39: 0
A40: 35 | B40: BBBROTHERS LAGUNA INC 002 | C40: BDO ONLINE | D40: Customer | F40: 0 | G40: 0 | H40: 0 | J40: 0 | K40: 0 | L40: 0 | N40: 0 | O40: 0 | P40: 0 | R40: 0 | S40: 0 | T40: 0 | V40: 0 | W40: 0
A41: 36 | B41: BBBROTHERS MASBATE GEN. MDSE INC | C41: BDO ONLINE | D41: Customer | F41: 0 | G41: 0 | H41: 0 | J41: 0 | K41: 0 | L41: 0 | N41: 0 | O41: 0 | P41: 0 | R41: 0 | S41: 0 | T41: 0 | V41: 0 | W41: 0
A42: 37 | B42: BBBROTHERS MINDANAO INC 001 | C42: BDO ONLINE | D42: Customer | F42: 0 | G42: 0 | H42: 0 | J42: 0 | K42: 0 | L42: 0 | N42: 0 | O42: 0 | P42: 0 | R42: 0 | S42: 0 | T42: 0 | V42: 0 | W42: 0
A43: 38 | B43: BBBROTHERS MINDANAO INC 002 | C43: BDO ONLINE | D43: Customer | F43: 0 | G43: 0 | H43: 0 | J43: 0 | K43: 0 | L43: 0 | N43: 0 | O43: 0 | P43: 0 | R43: 0 | S43: 0 | T43: 0 | V43: 0 | W43: 0
A44: 39 | B44: BBBROTHERS PHIL-BDO | C44: BDO | D44: Customer | F44: 0 | G44: 0 | H44: 0 | J44: 0 | K44: 0 | L44: 0 | N44: 0 | O44: 0 | P44: 0 | R44: 0 | S44: 0 | T44: 0 | V44: 0 | W44: 0
A45: 40 | B45: BBBROTHERS PHIL-BPI | C45: BPI | D45: Customer | F45: 0 | G45: 0 | H45: 0 | J45: 0 | K45: 0 | L45: 0 | N45: 0 | O45: 0 | P45: 0 | R45: 0 | S45: 0 | T45: 0 | V45: 0 | W45: 0
A46: 41 | B46: BBBROTHERS PHIL-DV/PNB | C46: PNB | D46: Customer | F46: 0 | G46: 0 | H46: 0 | J46: 0 | K46: 0 | L46: 0 | N46: 0 | O46: 0 | P46: 0 | R46: 0 | S46: 0 | T46: 0 | V46: 0 | W46: 0
A47: 42 | B47: BBBROTHERS PHILIPPINES INC 001 | C47: BDO ONLINE | D47: Customer | F47: 19 | G47: 221322 | H47: 570 | J47: 0 | K47: 0 | L47: 0 | N47: 19 | O47: 221322 | P47: 570 | R47: 0 | S47: 0 | T47: 0 | V47: 19 | W47: 221322
A48: 43 | B48: BBBROTHERS PHILLIPINES INC 002 | C48: BDO ONLINE | D48: Customer | F48: 16 | G48: 183296 | H48: 480 | J48: 0 | K48: 0 | L48: 0 | N48: 16 | O48: 183296 | P48: 480 | R48: 0 | S48: 0 | T48: 0 | V48: 16 | W48: 183296
... A54: 49 | B54: BDMPC-MAIN OFFICE | C54: BDO | D54: Customer | F54: 1 | G54: 1000 | H54: 50 | J54: 0 | K54: 0 | L54: 0 | N54: 1 | O54: 1000 | P54: 50 | R54: 0 | S54: 0 | T54: 0 | V54: 1 | W54: 1000
A55: 50 | B55: BDMPC-PANGLAO | D55: Customer | F55: 0 | G55: 0 | H55: 0 | J55: 0 | K55: 0 | L55: 0 | N55: 0 | O55: 0 | P55: 0 | R55: 0 | S55: 0 | T55: 0 | V55: 0 | W55: 0
A56: 51 | B56: BDMPC-TUBIGON | C56: METROBANK | D56: Customer | F56: 1 | G56: 3000 | H56: 50 | J56: 0 | K56: 0 | L56: 0 | N56: 1 | O56: 3000 | P56: 50 | R56: 0 | S56: 0 | T56: 0 | V56: 1 | W56: 3000
A57: 52 | B57: BDMPC-UBAY | C57: PNB | D57: Customer | F57: 0 | G57: 0 | H57: 0 | J57: 0 | K57: 0 | L57: 0 | N57: 0 | O57: 0 | P57: 0 | R57: 0 | S57: 0 | T57: 0 | V57: 0 | W57: 0
A58: 53 | B58: BENEDICTO COLLEGE INC | D58: Customer | F58: 0 | G58: 0 | H58: 0 | J58: 0 | K58: 0 | L58: 0 | N58: 0 | O58: 0 | P58: 0 | R58: 0 | S58: 0 | T58: 0 | V58: 0 | W58: 0
A59: 54 | B59: BICOL JL AGRI CORP | C59: METROBANK | D59: Partner | F59: 3 | G59: 119314 | H59: 150 | J59: 0 | K59: 0 | L59: 0 | N59: 3 | O59: 119314 | P59: 150 | R59: 0 | S59: 0 | T59: 0 | V59: 3 | W59: 119314
A60: 55 | B60: BILIRAN TELE TV NETWORK CORP | C60: AUB | D60: partner daily | F60: 6 | G60: 27144 | H60: 120 | J60: 0 | K60: 0 | L60: 0 | N60: 6 | O60: 27144 | P60: 120 | R60: 0 | S60: 0 | T60: 0 | V60: 6 | W60: 27144
A61: 56 | B61: BIYAHEKO.COM CORPORATION | C61: BPI | D61: Customer | F61: 1 | G61: 10000 | H61: 50 | J61: 0 | K61: 0 | L61: 0 | N61: 1 | O61: 10000 | P61: 50 | R61: 0 | S61: 0 | T61: 0 | V61: 1 | W61: 10000
A62: 57 | B62: BNSC/BOHOL NORTHERN STAR COLLEGE | D62: Customer | F62: 0 | G62: 0 | H62: 0 | J62: 0 | K62: 0 | L62: 0 | N62: 0 | O62: 0 | P62: 0 | R62: 0 | S62: 0 | T62: 0 | V62: 0 | W62: 0
A63: 58 | B63: BOARDWALK BUSINESS VENTURES | C63: SECURITY | D63: Customer | F63: 0 | G63: 0 | H63: 0 | J63: 0 | K63: 0 | L63: 0 | N63: 0 | O63: 0 | P63: 0 | R63: 0 | S63: 0 | T63: 0 | V63: 0 | W63: 0
A64: 59 | B64: BOHECO 1 | C64: SECURITY BANK | D64: Customer | F64: 64 | G64: 113436.43 | H64: 640 | J64: 0 | K64: 0 | L64: 0 | N64: 64 | O64: 113436.43 | P64: 640 | R64: 0 | S64: 0 | T64: 0 | V64: 64 | W64: 113436.43
A65: 60 | B65: BOHECO 2 | C65: METROBANK | D65: Customer | F65: 18 | G65: 18467.37 | H65: 90 | J65: 0 | K65: 0 | L65: 0 | N65: 18 | O65: 18467.37 | P65: 90 | R65: 0 | S65: 0 | T65: 0 | V65: 18 | W65: 18467.37
A66: 61 | B66: BOHOL LIGHTS INC | C66: SECURITY BANK | D66: Customer | F66: 226 | G66: 735809.19 | H66: 2260 | J66: 0 | K66: 0 | L66: 0 | N66: 226 | O66: 735809.19 | P66: 2260 | R66: 0 | S66: 0 | T66: 0 | V66: 226 | W66: 735809.19
A67: 62 | B67: BOHOL NORTHERNEASTERN EDUCATION FOUNDATION INC. | D67: Customer | F67: 0 | G67: 0 | H67: 0 | J67: 0 | K67: 0 | L67: 0 | N67: 0 | O67: 0 | P67: 0 | R67: 0 | S67: 0 | T67: 0 | V67: 0 | W67: 0
A68: 63 | B68: BOHOL WATER UTILITIES INC. | C68: SECURITY BANK | D68: Customer | F68: 47 | G68: 40562.56 | H68: 470 | J68: 0 | K68: 0 | L68: 0 | N68: 47 | O68: 40562.56 | P68: 470 | R68: 0 | S68: 0 | T68: 0 | V68: 47 | W68: 40562.56
A69: 64 | B69: BONJOUR TRAVEL AND TOURS | C69: bpi online | D69: Partner | F69: 0 | G69: 0 | H69: 0 | J69: 0 | K69: 0 | L69: 0 | N69: 0 | O69: 0 | P69: 0 | R69: 0 | S69: 0 | T69: 0 | V69: 0 | W69: 0
A70: 65 | B70: BOSTON FINANCE INVESTMENT CORP. | C70: CHINABANK | D70: Customer | F70: 0 | G70: 0 | H70: 0 | J70: 0 | K70: 0 | L70: 0 | N70: 0 | O70: 0 | P70: 0 | R70: 0 | S70: 0 | T70: 0 | V70: 0 | W70: 0
A71: 66 | B71: BOTICARD | C71: BPI | D71: Partner | F71: 2 | G71: 17398 | H71: 60 | J71: 0 | K71: 0 | L71: 0 | N71: 2 | O71: 17398 | P71: 60 | R71: 0 | S71: 0 | T71: 0 | V71: 2 | W71: 17398
A72: 67 | B72: BOUNTY PLUS - LUZON (PROVINCIAL FRESH LUZON) | C72: BPI CHECK | D72: PARTNER DAILY | F72: 0 | G72: 0 | H72: 0 | J72: 0 | K72: 0 | L72: 0 | N72: 0 | O72: 0 | P72: 0 | R72: 0 | S72: 0 | T72: 0 | V72: 0 | W72: 0
A73: 68 | B73: BOUNTY PLUS - MINDANAO (PROVINCIAL FRESH MINDANAO) | C73: SECURITY BANK | D73: Partner | F73: 15 | G73: 780407.9 | H73: 960 | J73: 0 | K73: 0 | L73: 0 | N73: 15 | O73: 780407.9 | P73: 960 | R73: 0 | S73: 0 | T73: 0 | V73: 15 | W73: 780407.9
A74: 69 | B74: BOUNTY PLUS - VISAYAS (PROVINCIAL FRESH VISAYAS) | C74: BDO CHECK | D74: Partner | F74: 64 | G74: 1953740.6 | H74: 3120 | J74: 0 | K74: 0 | L74: 0 | N74: 64 | O74: 1953740.6 | P74: 3120 | R74: 0 | S74: 0 | T74: 0 | V74: 64 | W74: 1953740.6
A75: 70 | B75: BP WATERWORKS | C75: BDO | D75: Partner M. | F75: 124 | G75: 84182.91 | H75: 992 | J75: 0 | K75: 0 | L75: 0 | N75: 124 | O75: 84182.91 | P75: 992 | R75: 0 | S75: 0 | T75: 0 | V75: 124 | W75: 84182.91
A76: 71 | B76: BREAD AND MORE INC. | C76: METROBANK | D76: Partner | F76: 21 | G76: 558886.85 | H76: 630 | J76: 0 | K76: 0 | L76: 0 | N76: 21 | O76: 558886.85 | P76: 630 | R76: 0 | S76: 0 | T76: 0 | V76: 21 | W76: 558886.85
A77: 72 | B77: BREAD AREA INC. | C77: METROBANK | D77: Partner | F77: 0 | G77: 0 | H77: 0 | J77: 0 | K77: 0 | L77: 0 | N77: 0 | O77: 0 | P77: 0 | R77: 0 | S77: 0 | T77: 0 | V77: 0 | W77: 0
A78: 73 | B78: BREAD BY PATTY CORPORATION | C78: CHINABANK | D78: Partner | F78: 30 | G78: 111261 | H78: 900 | J78: 0 | K78: 0 | L78: 0 | N78: 30 | O78: 111261 | P78: 900 | R78: 0 | S78: 0 | T78: 0 | V78: 30 | W78: 111261
A79: 74 | B79: BREADPOINT | C79: METROBANK | D79: Customer | F79: 33 | G79: 351912 | H79: 1320 | J79: 0 | K79: 0 | L79: 0 | N79: 33 | O79: 351912 | P79: 1320 | R79: 0 | S79: 0 | T79: 0 | V79: 33 | W79: 351912
... A112: 107 | B112: CHARISSA'S FOOD ENTERPRISE | C112: eastwest | D112: Customer | F112: 0 | G112: 0 | H112: 0 | J112: 0 | K112: 0 | L112: 0 | N112: 0 | O112: 0 | P112: 0 | R112: 0 | S112: 0 | T112: 0 | V112: 0 | W112: 0
A113: 108 | B113: CHARLES CATV SYSTEMS, INC. | D113: Customer | F113: 0 | G113: 0 | H113: 0 | J113: 0 | K113: 0 | L113: 0 | N113: 0 | O113: 0 | P113: 0 | R113: 0 | S113: 0 | T113: 0 | V113: 0 | W113: 0
A114: 109 | B114: CHARLES PEAK | C114: BPI | D114: Customer | F114: 3 | G114: 2283 | H114: 30 | J114: 0 | K114: 0 | L114: 0 | N114: 3 | O114: 2283 | P114: 30 | R114: 0 | S114: 0 | T114: 0 | V114: 3 | W114: 2283
A115: 110 | B115: CHICKEN ESSENTIALS, INC | C115: SECURITY BANK | D115: Partner | F115: 0 | G115: 0 | H115: 0 | J115: 0 | K115: 0 | L115: 0 | N115: 0 | O115: 0 | P115: 0 | R115: 0 | S115: 0 | T115: 0 | V115: 0 | W115: 0
A116: 111 | B116: CHICKY OINK | C116: CHINABANK | D116: Partner | F116: 63 | G116: 1717273 | H116: 2520 | J116: 0 | K116: 0 | L116: 0 | N116: 63 | O116: 1717273 | P116: 2520 | R116: 0 | S116: 0 | T116: 0 | V116: 63 | W116: 1717273
A117: 112 | B117: CHOOKS TO GO | C117: BDO | D117: Partner | F117: 0 | G117: 0 | H117: 0 | J117: 0 | K117: 0 | L117: 0 | N117: 0 | O117: 0 | P117: 0 | R117: 0 | S117: 0 | T117: 0 | V117: 0 | W117: 0
A118: 113 | B118: CHOOKS TO GO PILIPINAS | C118: CHINABANK | D118: partner daily | F118: 301 | G118: 6348719.8 | H118: 12360 | J118: 0 | K118: 0 | L118: 0 | N118: 301 | O118: 6348719.8 | P118: 12360 | R118: 0 | S118: 0 | T118: 0 | V118: 301 | W118: 6348719.8
A119: 114 | B119: CIS BAYAD CENTER INC. | C119: BDO | D119: Partner M. | F119: 2507 | G119: 4850349.3 | H119: 14068.5 | J119: 0 | K119: 0 | L119: 0 | N119: 2507 | O119: 4850349.3 | P119: 14068.5 | R119: 0 | S119: 0 | T119: 0 | V119: 2507 | W119: 4850349.3
A120: 115 | B120: CITY SAVINGS BANK | C120: UNION BANK | D120: Partner M. | F120: 775 | G120: 4126207 | H120: 38750 | J120: 0 | K120: 0 | L120: 0 | N120: 775 | O120: 4126207 | P120: 38750 | R120: 0 | S120: 0 | T120: 0 | V120: 775 | W120: 4126207
A121: 116 | B121: CLAVER TV AND INTERNET SERVICES | C121: METROBANK | D121: Customer | F121: 3 | G121: 3950 | H121: 60 | J121: 0 | K121: 0 | L121: 0 | N121: 3 | O121: 3950 | P121: 60 | R121: 0 | S121: 0 | T121: 0 | V121: 3 | W121: 3950
A122: 117 | B122: COLEGIO DE DAGUPAN | D122: Customer | F122: 0 | G122: 0 | H122: 0 | J122: 0 | K122: 0 | L122: 0 | N122: 0 | O122: 0 | P122: 0 | R122: 0 | S122: 0 | T122: 0 | V122: 0 | W122: 0
A123: 118 | B123: COLEGIO SAN AGUSTIN - BACOLOD | C123: BPI | D123: Customer | F123: 8 | G123: 128391.41 | H123: 240 | J123: 0 | K123: 0 | L123: 0 | N123: 8 | O123: 128391.41 | P123: 240 | R123: 0 | S123: 0 | T123: 0 | V123: 8 | W123: 128391.41
A124: 119 | B124: COLLEGE OF TECHNOLOGICAL SCIENCES CEBU INC. | C124: METROBANK | D124: Customer | F124: 0 | G124: 0 | H124: 0 | J124: 0 | K124: 0 | L124: 0 | N124: 0 | O124: 0 | P124: 0 | R124: 0 | S124: 0 | T124: 0 | V124: 0 | W124: 0
A125: 120 | B125: COLUMBAN MISSIONARY FOUNDATION INC. | C125: EASTWEST BANK | D125: Customer | F125: 0 | G125: 0 | H125: 0 | J125: 0 | K125: 0 | L125: 0 | N125: 0 | O125: 0 | P125: 0 | R125: 0 | S125: 0 | T125: 0 | V125: 0 | W125: 0
A126: 121 | B126: COMMUNITY ECONOMIC VENTURES INC. | C126: BPI | D126: Customer | F126: 0 | G126: 0 | H126: 0 | J126: 0 | K126: 0 | L126: 0 | N126: 0 | O126: 0 | P126: 0 | R126: 0 | S126: 0 | T126: 0 | V126: 0 | W126: 0
A127: 122 | B127: COMPASIA TECHNOLOGY PHILIPPINES INC. | C127: METROBANK | D127: Customer | F127: 0 | G127: 0 | H127: 0 | J127: 0 | K127: 0 | L127: 0 | N127: 0 | O127: 0 | P127: 0 | R127: 0 | S127: 0 | T127: 0 | V127: 0 | W127: 0
A128: 123 | B128: COOPERATIVE BANK OF CEBU (COOPBANK) | C128: BANK OF COMMERCE | D128: Customer | F128: 8 | G128: 16347.55 | H128: 300 | J128: 0 | K128: 0 | L128: 0 | N128: 8 | O128: 16347.55 | P128: 300 | R128: 0 | S128: 0 | T128: 0 | V128: 8 | W128: 16347.55
A129: 124 | B129: COR JESU COLLEGE. | C129: METROBANK | D129: Customer | F129: 0 | G129: 0 | H129: 0 | J129: 0 | K129: 0 | L129: 0 | N129: 0 | O129: 0 | P129: 0 | R129: 0 | S129: 0 | T129: 0 | V129: 0 | W129: 0
A130: 125 | B130: COTABATO ELECTRIC COOPERATIVE, INC. (COTELCO)-MATALAM | C130: METROBANK | D130: Customer | F130: 119 | G130: 194719.27 | H130: 952 | J130: 0 | K130: 0 | L130: 0 | N130: 119 | O130: 194719.27 | P130: 952 | R130: 0 | S130: 0 | T130: 0 | V130: 119 | W130: 194719.27
A131: 126 | B131: COTABATO LIGHTS | C131: BDO | D131: Partner M. | F131: 35 | G131: 46021.5 | H131: 315 | J131: 0 | K131: 0 | L131: 0 | N131: 35 | O131: 46021.5 | P131: 315 | R131: 0 | S131: 0 | T131: 0 | V131: 35 | W131: 46021.5
A132: 127 | B132: COTELCO-MATALAM COLLECTIONS | C132: METROBANK | D132: Customer | F132: 0 | G132: 0 | H132: 0 | J132: 0 | K132: 0 | L132: 0 | N132: 0 | O132: 0 | P132: 0 | R132: 0 | S132: 0 | T132: 0 | V132: 0 | W132: 0
A133: 128 | B133: COVERBEST DISTRIBUTIONS CORPORATION | C133: SECURITY BANK | D133: Customer | F133: 0 | G133: 0 | H133: 0 | J133: 0 | K133: 0 | L133: 0 | N133: 0 | O133: 0 | P133: 0 | R133: 0 | S133: 0 | T133: 0 | V133: 0 | W133: 0
A134: 129 | B134: CSW - ILOILO INC. | C134: LANBANK | D134: Customer | F134: 0 | G134: 0 | H134: 0 | J134: 0 | K134: 0 | L134: 0 | N134: 0 | O134: 0 | P134: 0 | R134: 0 | S134: 0 | T134: 0 | V134: 0 | W134: 0
... A142: 137 | B142: DITO TELECOMMUNITY CORPORATION | C142: unionbank | D142: Customer | F142: 3 | G142: 1441.94 | H142: 30 | J142: 0 | K142: 0 | L142: 0 | N142: 3 | O142: 1441.94 | P142: 30 | R142: 0 | S142: 0 | T142: 0 | V142: 3 | W142: 1441.94
A143: 138 | B143: DMC COLLEGE FOUNDATION INC. | D143: Customer | F143: 1 | G143: 5000 | H143: 20 | J143: 0 | K143: 0 | L143: 0 | N143: 1 | O143: 5000 | P143: 20 | R143: 0 | S143: 0 | T143: 0 | V143: 1 | W143: 5000
A144: 139 | B144: DOKTORS GENERICS PHARMACY INC | C144: BDO CHECK | D144: Customer | F144: 5 | G144: 83117.5 | H144: 125 | J144: 0 | K144: 0 | L144: 0 | N144: 5 | O144: 83117.5 | P144: 125 | R144: 0 | S144: 0 | T144: 0 | V144: 5 | W144: 83117.5
...

Sheet 31
A1: MLHUILLIER PHILIPPINES
A2: BILLS PAYMENT REPORT
A3: Report Date : July 31, 2025
F4: MLKP7 | J4: Cancelled (web) | N4: Net Total Trxns | R4: Billed Amount | V4: Current Variance
A5: No. | B5: Partner's Name | C5: Billers Name | D5: Banks | F5: Vol | G5: Principal | H5: Charge | J5: Vol | K5: Principal | L5: Charge | N5: Vol | O5: Principal | P5: Charge | R5: Vol | S5: Amount | T5: Charge | V5: Vol | W5: Amount
A6: 1 | B6: 123 LENDING CORPORATION | C6: BDO | D6: Customer | F6: 5 | G6: 43567.17 | H6: 500 | J6: 0 | K6: 0 | L6: 0 | N6: 5 | O6: 43567.17 | P6: 500 | R6: 17 | S6: 221714.16 | T6: 0 | V6: =N6-R6 -> -12 | W6: =O6-S6-T6 -> -178146.99
A7: 2 | B7: A-1 MILLING CORPORATION | C7: METROBANK | D7: Customer | F7: 0 | G7: 0 | H7: 0 | J7: 0 | K7: 0 | L7: 0 | N7: 0 | O7: 0 | P7: 0 | R7: 1 | S7: 111555 | T7: 0 | V7: =N7-R7 -> -1 | W7: =O7-S7-T7 -> -111555
A8: 3 | B8: A2M GLOBAL DISTRIBUTION INC. | C8: METROBANK | D8: Partner | F8: 0 | G8: 0 | H8: 0 | J8: 0 | K8: 0 | L8: 0 | N8: 0 | O8: 0 | P8: 0 | R8: 3 | S8: 101795.69 | T8: 0 | V8: =N8-R8 -> -3 | W8: =O8-S8-T8 -> -101795.69
A9: 4 | B9: ABEJO WATERS CORP - CEBU | C9: BPI ONLINE | D9: Customer | F9: 0 | G9: 0 | H9: 0 | J9: 0 | K9: 0 | L9: 0 | N9: 0 | O9: 0 | P9: 0 | R9: 0 | S9: 0 | T9: 0 | V9: =N9-R9 -> 0 | W9: =O9-S9-T9 -> 0
A10: 5 | B10: ABEJO WATERS CORP - TALISAY | C10: CHINABANK | D10: Customer | F10: 0 | G10: 0 | H10: 0 | J10: 0 | K10: 0 | L10: 0 | N10: 0 | O10: 0 | P10: 0 | R10: 0 | S10: 0 | T10: 0 | V10: =N10-R10 -> 0 | W10: =O10-S10-T10 -> 0
A11: 6 | B11: AEON CREDIT SERVICE PHIL INC. API | C11: METROBANK | D11: Customer | F11: 15 | G11: 35205.94 | H11: 225 | J11: 0 | K11: 0 | L11: 0 | N11: 15 | O11: 35205.94 | P11: 225 | R11: 19 | S11: 42737.72 | T11: 0 | V11: =N11-R11 -> -4 | W11: =O11-S11-T11 -> -7531.78
A12: 7 | B12: AF PAYMENTS (BEEP LOADING) | C12: BPI CHECK | D12: Customer | F12: 0 | G12: 0 | H12: 0 | J12: 0 | K12: 0 | L12: 0 | N12: 0 | O12: 0 | P12: 0 | R12: 0 | S12: 0 | T12: 0 | V12: =N12-R12 -> 0 | W12: =O12-S12-T12 -> 0
A13: 8 | B13: AIA PHILIPPINES | C13: BPI | D13: Customer | F13: 8 | G13: 51123.76 | H13: 200 | J13: 0 | K13: 0 | L13: 0 | N13: 8 | O13: 51123.76 | P13: 200 | R13: 9 | S13: 66899.46 | T13: 0 | V13: =N13-R13 -> -1 | W13: =O13-S13-T13 -> -15775.7
A14: 9 | B14: AIR ASIA/ZEST AIR | C14: BDO | D14: Partner | F14: 3 | G14: 20308.88 | H14: 60 | J14: 0 | K14: 0 | L14: 0 | N14: 3 | O14: 20308.88 | P14: 60 | R14: 6 | S14: 20919.43 | T14: 120 | V14: =N14-R14 -> -3 | W14: =O14-S14-T14 -> -730.55
A15: 10 | B15: AIR YOU GO TRAVEL PHILS CO. | C15: BDO | D15: Customer | F15: 0 | G15: 0 | H15: 0 | J15: 0 | K15: 0 | L15: 0 | N15: 0 | O15: 0 | P15: 0 | R15: 0 | S15: 0 | T15: 0 | V15: =N15-R15 -> 0 | W15: =O15-S15-T15 -> 0
A16: 11 | B16: AKLAN CABLE NETWORK, INC. - LEMERY | D16: Customer | F16: 0 | G16: 0 | H16: 0 | J16: 0 | K16: 0 | L16: 0 | N16: 0 | O16: 0 | P16: 0 | R16: 0 | S16: 0 | T16: 0 | V16: =N16-R16 -> 0 | W16: =O16-S16-T16 -> 0
A17: 12 | B17: ALFA- ALL FOOD ASIA, INC. | C17: METROBANK | D17: Customer | F17: 0 | G17: 0 | H17: 0 | J17: 0 | K17: 0 | L17: 0 | N17: 0 | O17: 0 | P17: 0 | R17: 0 | S17: 0 | T17: 0 | V17: =N17-R17 -> 0 | W17: =O17-S17-T17 -> 0
A18: 13 | B18: AMBROSIA PHILS INC | C18: METROBANK | D18: Partner | F18: 56 | G18: 1412224.5 | H18: 1825 | J18: 0 | K18: 0 | L18: 0 | N18: 56 | O18: 1412224.5 | P18: 1825 | R18: 57 | S18: 1176187.2 | T18: 1675 | V18: =N18-R18 -> -1 | W18: =O18-S18-T18 -> 234362.25
A19: 14 | B19: ANECO | C19: BPI | D19: Customer | F19: 5 | G19: 3773.42 | H19: 25 | J19: 0 | K19: 0 | L19: 0 | N19: 5 | O19: 3773.42 | P19: 25 | R19: 16 | S19: 60110.21 | T19: 0 | V19: =N19-R19 -> -11 | W19: =O19-S19-T19 -> -56336.79
A20: 15 | B20: ANECO COLLECTIONS | C20: BPI | D20: Customer | F20: 0 | G20: 0 | H20: 0 | J20: 0 | K20: 0 | L20: 0 | N20: 0 | O20: 0 | P20: 0 | R20: 0 | S20: 0 | T20: 0 | V20: =N20-R20 -> 0 | W20: =O20-S20-T20 -> 0
A21: 16 | B21: ANGELES CITY WATER DISTRICT | C21: LANBANK | D21: Customer | F21: 0 | G21: 0 | H21: 0 | J21: 0 | K21: 0 | L21: 0 | N21: 0 | O21: 0 | P21: 0 | R21: 0 | S21: 0 | T21: 0 | V21: =N21-R21 -> 0 | W21: =O21-S21-T21 -> 0
A22: 17 | B22: AQUA CENTRO MWPV CORP. | C22: BPI ONLINE | D22: CusPart | F22: 1 | G22: 500 | H22: 7 | J22: 0 | K22: 0 | L22: 0 | N22: 1 | O22: 500 | P22: 7 | R22: 0 | S22: 0 | T22: 0 | V22: =N22-R22 -> 1 | W22: =O22-S22-T22 -> 500
A23: 18 | B23: ASIALINK FINANCE CORPORATION | C23: BDO | D23: Partner M. | F23: 284 | G23: 5061561.2 | H23: 4656 | J23: 0 | K23: 0 | L23: 0 | N23: 284 | O23: 5061561.2 | P23: 4656 | R23: 461 | S23: 9729177.5 | T23: 0 | V23: =N23-R23 -> -177 | W23: =O23-S23-T23 -> -4667616.3
A24: 19 | B24: ASIAN COLLEGE OF SCIENCE AND TECHNOLOGY FDN. INC. | C24: BPI ONLINE | D24: Customer | F24: 0 | G24: 0 | H24: 0 | J24: 0 | K24: 0 | L24: 0 | N24: 0 | O24: 0 | P24: 0 | R24: 0 | S24: 0 | T24: 0 | V24: =N24-R24 -> 0 | W24: =O24-S24-T24 -> 0
A25: 20 | B25: ASIAN COLLEGE OF TECHNOLOGY (ACT) | D25: Customer | F25: 0 | G25: 0 | H25: 0 | J25: 0 | K25: 0 | L25: 0 | N25: 0 | O25: 0 | P25: 0 | R25: 0 | S25: 0 | T25: 0 | V25: =N25-R25 -> 0 | W25: =O25-S25-T25 -> 0
A26: 21 | B26: ASIAN INTERNATIONAL SCHOOL OF AERONAUTICS AND TECHNOLOGY (AISAT) CORP. | C26: METROBANK | D26: Customer | F26: 1 | G26: 10500 | H26: 30 | J26: 0 | K26: 0 | L26: 0 | N26: 1 | O26: 10500 | P26: 30 | R26: 1 | S26: 19115 | T26: 0 | V26: =N26-R26 -> 0 | W26: =O26-S26-T26 -> -8615
A27: 22 | B27: ATENEO DE DAVAO UNIVERSITY | C27: PNB | D27: Customer | F27: 0 | G27: 0 | H27: 0 | J27: 0 | K27: 0 | L27: 0 | N27: 0 | O27: 0 | P27: 0 | R27: 0 | S27: 0 | T27: 0 | V27: =N27-R27 -> 0 | W27: =O27-S27-T27 -> 0
A28: 23 | B28: ATENEO DE ZAMBOANGA UNIVERSITY | C28: METROBANK | D28: Customer | F28: 0 | G28: 0 | H28: 0 | J28: 0 | K28: 0 | L28: 0 | N28: 0 | O28: 0 | P28: 0 | R28: 0 | S28: 0 | T28: 0 | V28: =N28-R28 -> 0 | W28: =O28-S28-T28 -> 0
A29: 24 | B29: ATLAS CEBU CORN MILL CORP | C29: CHINABANK | D29: Customer | F29: 0 | G29: 0 | H29: 0 | J29: 0 | K29: 0 | L29: 0 | N29: 0 | O29: 0 | P29: 0 | R29: 1 | S29: 36725 | T29: 0 | V29: =N29-R29 -> -1 | W29: =O29-S29-T29 -> -36725
A30: 25 | B30: BAKERS BEST MARKETING CORPORATION | C30: BPI | D30: Customer | F30: 2 | G30: 20200 | H30: 60 | J30: 0 | K30: 0 | L30: 0 | N30: 2 | O30: 20200 | P30: 60 | R30: 4 | S30: 18214 | T30: 0 | V30: =N30-R30 -> -2 | W30: =O30-S30-T30 -> 1986
A31: 26 | B31: BALAMBAN ENERZONE | D31: No Billers | F31: 0 | G31: 0 | H31: 0 | J31: 0 | K31: 0 | L31: 0 | N31: 0 | O31: 0 | P31: 0 | R31: 0 | S31: 0 | T31: 0 | V31: =N31-R31 -> 0 | W31: =O31-S31-T31 -> 0
A32: 27 | B32: BALAMBAN WATER DISTRICT | C32: LANBANK | D32: Customer | F32: 5 | G32: 1912.75 | H32: 50 | J32: 0 | K32: 0 | L32: 0 | N32: 5 | O32: 1912.75 | P32: 50 | R32: 0 | S32: 0 | T32: 0 | V32: =N32-R32 -> 5 | W32: =O32-S32-T32 -> 1912.75
A33: 28 | B33: BASIC WATER ENTERPRISES INC. | C33: METROBANK | D33: Partner | F33: 0 | G33: 0 | H33: 0 | J33: 0 | K33: 0 | L33: 0 | N33: 0 | O33: 0 | P33: 0 | R33: 0 | S33: 0 | T33: 0 | V33: =N33-R33 -> 0 | W33: =O33-S33-T33 -> 0
A34: 29 | B34: BATANGAS CATV, INC. - BATANGAS | D34: Customer | F34: 0 | G34: 0 | H34: 0 | J34: 0 | K34: 0 | L34: 0 | N34: 0 | O34: 0 | P34: 0 | R34: 0 | S34: 0 | T34: 0 | V34: =N34-R34 -> 0 | W34: =O34-S34-T34 -> 0
A35: 30 | B35: BATANGAS CATV, INC. - BAUAN | D35: Customer | F35: 0 | G35: 0 | H35: 0 | J35: 0 | K35: 0 | L35: 0 | N35: 0 | O35: 0 | P35: 0 | R35: 1 | S35: 1830 | T35: 0 | V35: =N35-R35 -> -1 | W35: =O35-S35-T35 -> -1830
A36: 31 | B36: BAYAD CENTER - NBI | D36: No Billers | F36: 0 | G36: 0 | H36: 0 | J36: 0 | K36: 0 | L36: 0 | N36: 0 | O36: 0 | P36: 0 | R36: 0 | S36: 0 | T36: 0 | V36: =N36-R36 -> 0 | W36: =O36-S36-T36 -> 0
A37: 32 | B37: BAYAN TELECOMMUNICATIONS INC | C37: BDO | D37: CusPart | F37: 0 | G37: 0 | H37: 0 | J37: 0 | K37: 0 | L37: 0 | N37: 0 | O37: 0 | P37: 0 | R37: 0 | S37: 0 | T37: 0 | V37: =N37-R37 -> 0 | W37: =O37-S37-T37 -> 0
A38: 33 | B38: BBBROTHERS DV GEN. MDSE INC | C38: BDO ONLINE | D38: Customer | F38: 2 | G38: 25895 | H38: 60 | J38: 0 | K38: 0 | L38: 0 | N38: 2 | O38: 25895 | P38: 60 | R38: 0 | S38: 0 | T38: 0 | V38: =N38-R38 -> 2 | W38: =O38-S38-T38 -> 25895
A39: 34 | B39: BBBROTHERS LAGUNA INC 001 | C39: BDO ONLINE | D39: Customer | F39: 0 | G39: 0 | H39: 0 | J39: 0 | K39: 0 | L39: 0 | N39: 0 | O39: 0 | P39: 0 | R39: 0 | S39: 0 | T39: 0 | V39: =N39-R39 -> 0 | W39: =O39-S39-T39 -> 0
A40: 35 | B40: BBBROTHERS LAGUNA INC 002 | C40: BDO ONLINE | D40: Customer | F40: 0 | G40: 0 | H40: 0 | J40: 0 | K40: 0 | L40: 0 | N40: 0 | O40: 0 | P40: 0 | R40: 7 | S40: 122268 | T40: 0 | V40: =N40-R40 -> -7 | W40: =O40-S40-T40 -> -122268
A41: 36 | B41: BBBROTHERS MASBATE GEN. MDSE INC | C41: BDO ONLINE | D41: Customer | F41: 1 | G41: 15000 | H41: 30 | J41: 0 | K41: 0 | L41: 0 | N41: 1 | O41: 15000 | P41: 30 | R41: 0 | S41: 0 | T41: 0 | V41: =N41-R41 -> 1 | W41: =O41-S41-T41 -> 15000
A42: 37 | B42: BBBROTHERS MINDANAO INC 001 | C42: BDO ONLINE | D42: Customer | F42: 0 | G42: 0 | H42: 0 | J42: 0 | K42: 0 | L42: 0 | N42: 0 | O42: 0 | P42: 0 | R42: 0 | S42: 0 | T42: 0 | V42: =N42-R42 -> 0 | W42: =O42-S42-T42 -> 0
A43: 38 | B43: BBBROTHERS MINDANAO INC 002 | C43: BDO ONLINE | D43: Customer | F43: 0 | G43: 0 | H43: 0 | J43: 0 | K43: 0 | L43: 0 | N43: 0 | O43: 0 | P43: 0 | R43: 2 | S43: 21525 | T43: 0 | V43: =N43-R43 -> -2 | W43: =O43-S43-T43 -> -21525
A44: 39 | B44: BBBROTHERS PHIL-BDO | C44: BDO | D44: Customer | F44: 0 | G44: 0 | H44: 0 | J44: 0 | K44: 0 | L44: 0 | N44: 0 | O44: 0 | P44: 0 | R44: 0 | S44: 0 | T44: 0 | V44: =N44-R44 -> 0 | W44: =O44-S44-T44 -> 0
A45: 40 | B45: BBBROTHERS PHIL-BPI | C45: BPI | D45: Customer | F45: 0 | G45: 0 | H45: 0 | J45: 0 | K45: 0 | L45: 0 | N45: 0 | O45: 0 | P45: 0 | R45: 0 | S45: 0 | T45: 0 | V45: =N45-R45 -> 0 | W45: =O45-S45-T45 -> 0
A46: 41 | B46: BBBROTHERS PHIL-DV/PNB | C46: PNB | D46: Customer | F46: 0 | G46: 0 | H46: 0 | J46: 0 | K46: 0 | L46: 0 | N46: 0 | O46: 0 | P46: 0 | R46: 0 | S46: 0 | T46: 0 | V46: =N46-R46 -> 0 | W46: =O46-S46-T46 -> 0
A47: 42 | B47: BBBROTHERS PHILIPPINES INC 001 | C47: BDO ONLINE | D47: Customer | F47: 22 | G47: 307934 | H47: 660 | J47: 0 | K47: 0 | L47: 0 | N47: 22 | O47: 307934 | P47: 660 | R47: 0 | S47: 0 | T47: 0 | V47: =N47-R47 -> 22 | W47: =O47-S47-T47 -> 307934
A48: 43 | B48: BBBROTHERS PHILLIPINES INC 002 | C48: BDO ONLINE | D48: Customer | F48: 13 | G48: 177265 | H48: 390 | J48: 0 | K48: 0 | L48: 0 | N48: 13 | O48: 177265 | P48: 390 | R48: 0 | S48: 0 | T48: 0 | V48: =N48-R48 -> 13 | W48: =O48-S48-T48 -> 177265
... A54: 49 | B54: BDMPC-MAIN OFFICE | C54: BDO | D54: Customer | F54: 0 | G54: 0 | H54: 0 | J54: 0 | K54: 0 | L54: 0 | N54: 0 | O54: 0 | P54: 0 | R54: 0 | S54: 0 | T54: 0 | V54: =N54-R54 -> 0 | W54: =O54-S54-T54 -> 0
A55: 50 | B55: BDMPC-PANGLAO | D55: Customer | F55: 0 | G55: 0 | H55: 0 | J55: 0 | K55: 0 | L55: 0 | N55: 0 | O55: 0 | P55: 0 | R55: 0 | S55: 0 | T55: 0 | V55: =N55-R55 -> 0 | W55: =O55-S55-T55 -> 0
A56: 51 | B56: BDMPC-TUBIGON | C56: METROBANK | D56: Customer | F56: 1 | G56: 3353 | H56: 50 | J56: 0 | K56: 0 | L56: 0 | N56: 1 | O56: 3353 | P56: 50 | R56: 1 | S56: 1500 | T56: 0 | V56: =N56-R56 -> 0 | W56: =O56-S56-T56 -> 1853
A57: 52 | B57: BDMPC-UBAY | C57: PNB | D57: Customer | F57: 0 | G57: 0 | H57: 0 | J57: 0 | K57: 0 | L57: 0 | N57: 0 | O57: 0 | P57: 0 | R57: 0 | S57: 0 | T57: 0 | V57: =N57-R57 -> 0 | W57: =O57-S57-T57 -> 0
A58: 53 | B58: BENEDICTO COLLEGE INC | D58: Customer | F58: 0 | G58: 0 | H58: 0 | J58: 0 | K58: 0 | L58: 0 | N58: 0 | O58: 0 | P58: 0 | R58: 0 | S58: 0 | T58: 0 | V58: =N58-R58 -> 0 | W58: =O58-S58-T58 -> 0
A59: 54 | B59: BICOL JL AGRI CORP | C59: METROBANK | D59: Partner | F59: 0 | G59: 0 | H59: 0 | J59: 0 | K59: 0 | L59: 0 | N59: 0 | O59: 0 | P59: 0 | R59: 0 | S59: 0 | T59: 0 | V59: =N59-R59 -> 0 | W59: =O59-S59-T59 -> 0
A60: 55 | B60: BILIRAN TELE TV NETWORK CORP | C60: AUB | D60: partner daily | F60: 0 | G60: 0 | H60: 0 | J60: 0 | K60: 0 | L60: 0 | N60: 0 | O60: 0 | P60: 0 | R60: 0 | S60: 0 | T60: 0 | V60: =N60-R60 -> 0 | W60: =O60-S60-T60 -> 0
A61: 56 | B61: BIYAHEKO.COM CORPORATION | C61: BPI | D61: Customer | F61: 1 | G61: 50000 | H61: 50 | J61: 0 | K61: 0 | L61: 0 | N61: 1 | O61: 50000 | P61: 50 | R61: 0 | S61: 0 | T61: 0 | V61: =N61-R61 -> 1 | W61: =O61-S61-T61 -> 50000
A62: 57 | B62: BNSC/BOHOL NORTHERN STAR COLLEGE | D62: Customer | F62: 0 | G62: 0 | H62: 0 | J62: 0 | K62: 0 | L62: 0 | N62: 0 | O62: 0 | P62: 0 | R62: 1 | S62: 44040 | T62: 50 | V62: =N62-R62 -> -1 | W62: =O62-S62-T62 -> -44090
A63: 58 | B63: BOARDWALK BUSINESS VENTURES | C63: SECURITY | D63: Customer | F63: 0 | G63: 0 | H63: 0 | J63: 0 | K63: 0 | L63: 0 | N63: 0 | O63: 0 | P63: 0 | R63: 3 | S63: 3410 | T63: 60 | V63: =N63-R63 -> -3 | W63: =O63-S63-T63 -> -3470
A64: 59 | B64: BOHECO 1 | C64: SECURITY BANK | D64: Customer | F64: 55 | G64: 72256.75 | H64: 550 | J64: 0 | K64: 0 | L64: 0 | N64: 55 | O64: 72256.75 | P64: 550 | R64: 0 | S64: 0 | T64: 0 | V64: =N64-R64 -> 55 | W64: =O64-S64-T64 -> 72256.75
A65: 60 | B65: BOHECO 2 | C65: METROBANK | D65: Customer | F65: 13 | G65: 11922.14 | H65: 65 | J65: 0 | K65: 0 | L65: 0 | N65: 13 | O65: 11922.14 | P65: 65 | R65: 0 | S65: 0 | T65: 0 | V65: =N65-R65 -> 13 | W65: =O65-S65-T65 -> 11922.14
A66: 61 | B66: BOHOL LIGHTS INC | C66: SECURITY BANK | D66: Customer | F66: 143 | G66: 406926.75 | H66: 1430 | J66: 0 | K66: 0 | L66: 0 | N66: 143 | O66: 406926.75 | P66: 1430 | R66: 0 | S66: 0 | T66: 0 | V66: =N66-R66 -> 143 | W66: =O66-S66-T66 -> 406926.75
A67: 62 | B67: BOHOL NORTHERNEASTERN EDUCATION FOUNDATION INC. | D67: Customer | F67: 0 | G67: 0 | H67: 0 | J67: 0 | K67: 0 | L67: 0 | N67: 0 | O67: 0 | P67: 0 | R67: 57 | S67: 108931.06 | T67: 0 | V67: =N67-R67 -> -57 | W67: =O67-S67-T67 -> -108931.06
A68: 63 | B68: BOHOL WATER UTILITIES INC. | C68: SECURITY BANK | D68: Customer | F68: 39 | G68: 14922.43 | H68: 390 | J68: 0 | K68: 0 | L68: 0 | N68: 39 | O68: 14922.43 | P68: 390 | R68: 33 | S68: 61883.14 | T68: 0 | V68: =N68-R68 -> 6 | W68: =O68-S68-T68 -> -46960.71
A69: 64 | B69: BONJOUR TRAVEL AND TOURS | C69: bpi online | D69: Partner | F69: 0 | G69: 0 | H69: 0 | J69: 0 | K69: 0 | L69: 0 | N69: 0 | O69: 0 | P69: 0 | R69: 213 | S69: 563523.65 | T69: 0 | V69: =N69-R69 -> -213 | W69: =O69-S69-T69 -> -563523.65
A70: 65 | B70: BOSTON FINANCE INVESTMENT CORP. | C70: CHINABANK | D70: Customer | F70: 1 | G70: 1000 | H70: 25 | J70: 0 | K70: 0 | L70: 0 | N70: 1 | O70: 1000 | P70: 25 | R70: 0 | S70: 0 | T70: 0 | V70: =N70-R70 -> 1 | W70: =O70-S70-T70 -> 1000
A71: 66 | B71: BOTICARD | C71: BPI | D71: Partner | F71: 2 | G71: 24876 | H71: 60 | J71: 0 | K71: 0 | L71: 0 | N71: 2 | O71: 24876 | P71: 60 | R71: 63 | S71: 40088.17 | T71: 0 | V71: =N71-R71 -> -61 | W71: =O71-S71-T71 -> -15212.17
A72: 67 | B72: BOUNTY PLUS - LUZON (PROVINCIAL FRESH LUZON) | C72: BPI CHECK | D72: PARTNER DAILY | F72: 0 | G72: 0 | H72: 0 | J72: 0 | K72: 0 | L72: 0 | N72: 0 | O72: 0 | P72: 0 | R72: 0 | S72: 0 | T72: 0 | V72: =N72-R72 -> 0 | W72: =O72-S72-T72 -> 0
A73: 68 | B73: BOUNTY PLUS - MINDANAO (PROVINCIAL FRESH MINDANAO) | C73: SECURITY BANK | D73: Partner | F73: 13 | G73: 1036556.6 | H73: 1080 | J73: 0 | K73: 0 | L73: 0 | N73: 13 | O73: 1036556.6 | P73: 1080 | R73: 0 | S73: 0 | T73: 0 | V73: =N73-R73 -> 13 | W73: =O73-S73-T73 -> 1036556.6
A74: 69 | B74: BOUNTY PLUS - VISAYAS (PROVINCIAL FRESH VISAYAS) | C74: BDO CHECK | D74: Partner | F74: 21 | G74: 924849.25 | H74: 1160 | J74: 0 | K74: 0 | L74: 0 | N74: 21 | O74: 924849.25 | P74: 1160 | R74: 3 | S74: 25453.97 | T74: 90 | V74: =N74-R74 -> 18 | W74: =O74-S74-T74 -> 899305.28
A75: 70 | B75: BP WATERWORKS | C75: BDO | D75: Partner M. | F75: 53 | G75: 26126.13 | H75: 424 | J75: 0 | K75: 0 | L75: 0 | N75: 53 | O75: 26126.13 | P75: 424 | R75: 0 | S75: 0 | T75: 0 | V75: =N75-R75 -> 53 | W75: =O75-S75-T75 -> 26126.13
A76: 71 | B76: BREAD AND MORE INC. | C76: METROBANK | D76: Partner | F76: 21 | G76: 646223 | H76: 630 | J76: 0 | K76: 0 | L76: 0 | N76: 21 | O76: 646223 | P76: 630 | R76: 0 | S76: 0 | T76: 0 | V76: =N76-R76 -> 21 | W76: =O76-S76-T76 -> 646223
A77: 72 | B77: BREAD AREA INC. | C77: METROBANK | D77: Partner | F77: 0 | G77: 0 | H77: 0 | J77: 0 | K77: 0 | L77: 0 | N77: 0 | O77: 0 | P77: 0 | R77: 6 | S77: 1645206.5 | T77: 1720 | V77: =N77-R77 -> -6 | W77: =O77-S77-T77 -> -1646926.5
A78: 73 | B78: BREAD BY PATTY CORPORATION | C78: CHINABANK | D78: Partner | F78: 38 | G78: 408268 | H78: 1140 | J78: 0 | K78: 0 | L78: 0 | N78: 38 | O78: 408268 | P78: 1140 | R78: 28 | S78: 1877633.9 | T78: 2360 | V78: =N78-R78 -> 10 | W78: =O78-S78-T78 -> -1471725.9
A79: 74 | B79: BREADPOINT | C79: METROBANK | D79: Customer | F79: 29 | G79: 324555 | H79: 1160 | J79: 0 | K79: 0 | L79: 0 | N79: 29 | O79: 324555 | P79: 1160 | R79: 134 | S79: 79786.44 | T79: 0 | V79: =N79-R79 -> -105 | W79: =O79-S79-T79 -> 244768.56
... A112: 107 | B112: CHARISSA'S FOOD ENTERPRISE | C112: eastwest | D112: Customer | F112: 0 | G112: 0 | H112: 0 | J112: 0 | K112: 0 | L112: 0 | N112: 0 | O112: 0 | P112: 0 | R112: 2 | S112: 25413.86 | T112: 0 | V112: =N112-R112 -> -2 | W112: =O112-S112-T112 -> -25413.86
A113: 108 | B113: CHARLES CATV SYSTEMS, INC. | D113: Customer | F113: 0 | G113: 0 | H113: 0 | J113: 0 | K113: 0 | L113: 0 | N113: 0 | O113: 0 | P113: 0 | R113: 4 | S113: 150991 | T113: 0 | V113: =N113-R113 -> -4 | W113: =O113-S113-T113 -> -150991
A114: 109 | B114: CHARLES PEAK | C114: BPI | D114: Customer | F114: 0 | G114: 0 | H114: 0 | J114: 0 | K114: 0 | L114: 0 | N114: 0 | O114: 0 | P114: 0 | R114: 2 | S114: 64742.88 | T114: 0 | V114: =N114-R114 -> -2 | W114: =O114-S114-T114 -> -64742.88
A115: 110 | B115: CHICKEN ESSENTIALS, INC | C115: SECURITY BANK | D115: Partner | F115: 0 | G115: 0 | H115: 0 | J115: 0 | K115: 0 | L115: 0 | N115: 0 | O115: 0 | P115: 0 | R115: 54 | S115: 1160604.2 | T115: 0 | V115: =N115-R115 -> -54 | W115: =O115-S115-T115 -> -1160604.2
A116: 111 | B116: CHICKY OINK | C116: CHINABANK | D116: Partner | F116: 63 | G116: 1959402 | H116: 2760 | J116: 0 | K116: 0 | L116: 0 | N116: 63 | O116: 1959402 | P116: 2760 | R116: 0 | S116: 0 | T116: 0 | V116: =N116-R116 -> 63 | W116: =O116-S116-T116 -> 1959402
A117: 112 | B117: CHOOKS TO GO | C117: BDO | D117: Partner | F117: 0 | G117: 0 | H117: 0 | J117: 0 | K117: 0 | L117: 0 | N117: 0 | O117: 0 | P117: 0 | R117: 1 | S117: 723 | T117: 0 | V117: =N117-R117 -> -1 | W117: =O117-S117-T117 -> -723
A118: 113 | B118: CHOOKS TO GO PILIPINAS | C118: CHINABANK | D118: partner daily | F118: 317 | G118: 7611312.6 | H118: 13280 | J118: 0 | K118: 0 | L118: 0 | N118: 317 | O118: 7611312.6 | P118: 13280 | R118: 8 | S118: 4227 | T118: 0 | V118: =N118-R118 -> 309 | W118: =O118-S118-T118 -> 7607085.6
A119: 114 | B119: CIS BAYAD CENTER INC. | C119: BDO | D119: Partner M. | F119: 1577 | G119: 3192702.3 | H119: 8885 | J119: 0 | K119: 0 | L119: 0 | N119: 1577 | O119: 3192702.3 | P119: 8885 | R119: 0 | S119: 0 | T119: 0 | V119: =N119-R119 -> 1577 | W119: =O119-S119-T119 -> 3192702.3
A120: 115 | B120: CITY SAVINGS BANK | C120: UNION BANK | D120: Partner M. | F120: 594 | G120: 2854079.5 | H120: 29700 | J120: 0 | K120: 0 | L120: 0 | N120: 594 | O120: 2854079.5 | P120: 29700 | R120: 0 | S120: 0 | T120: 0 | V120: =N120-R120 -> 594 | W120: =O120-S120-T120 -> 2854079.5
A121: 116 | B121: CLAVER TV AND INTERNET SERVICES | C121: METROBANK | D121: Customer | F121: 0 | G121: 0 | H121: 0 | J121: 0 | K121: 0 | L121: 0 | N121: 0 | O121: 0 | P121: 0 | R121: 294 | S121: 5256503.8 | T121: 11960 | V121: =N121-R121 -> -294 | W121: =O121-S121-T121 -> -5268463.8
A122: 117 | B122: COLEGIO DE DAGUPAN | D122: Customer | F122: 0 | G122: 0 | H122: 0 | J122: 0 | K122: 0 | L122: 0 | N122: 0 | O122: 0 | P122: 0 | R122: 2322 | S122: 4354317.7 | T122: 0 | V122: =N122-R122 -> -2322 | W122: =O122-S122-T122 -> -4354317.7
A123: 118 | B123: COLEGIO SAN AGUSTIN - BACOLOD | C123: BPI | D123: Customer | F123: 20 | G123: 327681 | H123: 600 | J123: 0 | K123: 0 | L123: 0 | N123: 20 | O123: 327681 | P123: 600 | R123: 800 | S123: 4200597.6 | T123: 0 | V123: =N123-R123 -> -780 | W123: =O123-S123-T123 -> -3872916.6
A124: 119 | B124: COLLEGE OF TECHNOLOGICAL SCIENCES CEBU INC. | C124: METROBANK | D124: Customer | F124: 0 | G124: 0 | H124: 0 | J124: 0 | K124: 0 | L124: 0 | N124: 0 | O124: 0 | P124: 0 | R124: 57 | S124: 1104224 | T124: 1800 | V124: =N124-R124 -> -57 | W124: =O124-S124-T124 -> -1106024
A125: 120 | B125: COLUMBAN MISSIONARY FOUNDATION INC. | C125: EASTWEST BANK | D125: Customer | F125: 0 | G125: 0 | H125: 0 | J125: 0 | K125: 0 | L125: 0 | N125: 0 | O125: 0 | P125: 0 | R125: 4 | S125: 5596 | T125: 0 | V125: =N125-R125 -> -4 | W125: =O125-S125-T125 -> -5596
A126: 121 | B126: COMMUNITY ECONOMIC VENTURES INC. | C126: BPI | D126: Customer | F126: 0 | G126: 0 | H126: 0 | J126: 0 | K126: 0 | L126: 0 | N126: 0 | O126: 0 | P126: 0 | R126: 0 | S126: 0 | T126: 0 | V126: =N126-R126 -> 0 | W126: =O126-S126-T126 -> 0
A127: 122 | B127: COMPASIA TECHNOLOGY PHILIPPINES INC. | C127: METROBANK | D127: Customer | F127: 0 | G127: 0 | H127: 0 | J127: 0 | K127: 0 | L127: 0 | N127: 0 | O127: 0 | P127: 0 | R127: 1 | S127: 1503 | T127: 0 | V127: =N127-R127 -> -1 | W127: =O127-S127-T127 -> -1503
A128: 123 | B128: COOPERATIVE BANK OF CEBU (COOPBANK) | C128: BANK OF COMMERCE | D128: Customer | F128: 6 | G128: 9212.78 | H128: 240 | J128: 0 | K128: 0 | L128: 0 | N128: 6 | O128: 9212.78 | P128: 240 | R128: 0 | S128: 0 | T128: 0 | V128: =N128-R128 -> 6 | W128: =O128-S128-T128 -> 9212.78
A129: 124 | B129: COR JESU COLLEGE. | C129: METROBANK | D129: Customer | F129: 0 | G129: 0 | H129: 0 | J129: 0 | K129: 0 | L129: 0 | N129: 0 | O129: 0 | P129: 0 | R129: 0 | S129: 0 | T129: 0 | V129: =N129-R129 -> 0 | W129: =O129-S129-T129 -> 0
A130: 125 | B130: COTABATO ELECTRIC COOPERATIVE, INC. (COTELCO)-MATALAM | C130: METROBANK | D130: Customer | F130: 95 | G130: 158113.63 | H130: 760 | J130: 0 | K130: 0 | L130: 0 | N130: 95 | O130: 158113.63 | P130: 760 | R130: 0 | S130: 0 | T130: 0 | V130: =N130-R130 -> 95 | W130: =O130-S130-T130 -> 158113.63
A131: 126 | B131: COTABATO LIGHTS | C131: BDO | D131: Partner M. | F131: 25 | G131: 32241.23 | H131: 225 | J131: 0 | K131: 0 | L131: 0 | N131: 25 | O131: 32241.23 | P131: 225 | R131: 0 | S131: 0 | T131: 0 | V131: =N131-R131 -> 25 | W131: =O131-S131-T131 -> 32241.23
A132: 127 | B132: COTELCO-MATALAM COLLECTIONS | C132: METROBANK | D132: Customer | F132: 0 | G132: 0 | H132: 0 | J132: 0 | K132: 0 | L132: 0 | N132: 0 | O132: 0 | P132: 0 | R132: 7 | S132: 29011.55 | T132: 0 | V132: =N132-R132 -> -7 | W132: =O132-S132-T132 -> -29011.55
A133: 128 | B133: COVERBEST DISTRIBUTIONS CORPORATION | C133: SECURITY BANK | D133: Customer | F133: 0 | G133: 0 | H133: 0 | J133: 0 | K133: 0 | L133: 0 | N133: 0 | O133: 0 | P133: 0 | R133: 0 | S133: 0 | T133: 0 | V133: =N133-R133 -> 0 | W133: =O133-S133-T133 -> 0
A134: 129 | B134: CSW - ILOILO INC. | C134: LANBANK | D134: Customer | F134: 0 | G134: 0 | H134: 0 | J134: 0 | K134: 0 | L134: 0 | N134: 0 | O134: 0 | P134: 0 | R134: 135 | S134: 187834.44 | T134: 0 | V134: =N134-R134 -> -135 | W134: =O134-S134-T134 -> -187834.44
... A142: 137 | B142: DITO TELECOMMUNITY CORPORATION | C142: unionbank | D142: Customer | F142: 3 | G142: 2492.13 | H142: 30 | J142: 0 | K142: 0 | L142: 0 | N142: 3 | O142: 2492.13 | P142: 30 | R142: 0 | S142: 0 | T142: 0 | V142: =N142-R142 -> 3 | W142: =O142-S142-T142 -> 2492.13
A143: 138 | B143: DMC COLLEGE FOUNDATION INC. | D143: Customer | F143: 1 | G143: 10740 | H143: 50 | J143: 0 | K143: 0 | L143: 0 | N143: 1 | O143: 10740 | P143: 50 | R143: 2 | S143: 3701 | T143: 0 | V143: =N143-R143 -> -1 | W143: =O143-S143-T143 -> 7039
A144: 139 | B144: DOKTORS GENERICS PHARMACY INC | C144: BDO CHECK | D144: Customer | F144: 0 | G144: 0 | H144: 0 | J144: 0 | K144: 0 | L144: 0 | N144: 0 | O144: 0 | P144: 0 | R144: 3 | S144: 7096 | T144: 0 | V144: =N144-R144 -> -3 | W144: =O144-S144-T144 -> -7096
...

Sheet AP AR
A1: MLHUILLIER PHILIPPINES
A2: BILLS PAYMENT REPORT
A3: Report Date : August 31, 2025
F4: MLKP7 | J4: Cancelled (web) | N4: Net Total Trxns | R4: Billed Amount | V4: Current Variance | Y4: Running Balance
A5: No. | B5: Partner's Name | C5: Billers Name | D5: Banks | F5: Vol | G5: Principal | H5: Charge | J5: Vol | K5: Principal | L5: Charge | N5: Vol | O5: Principal | P5: Charge | R5: Vol | S5: Amount | T5: Charge | V5: Vol | W5: Amount | Y5: Vol | Z5: Amount | AB5: August 31, 2025 | AD5: Paid Service Charge | AF5: Accounts Payable to Partner | AG5: Service Charge | AH5: BPW undeducted | AI5: BPX undeducted | AJ5: Audit findings | AK5: Banks | AL5: Others | AM5: Accounts Receivable from Partner | AN5: Balances as of August 31, 2025
A6: 1 | B6: 123 LENDING CORPORATION | C6: BDO | D6: Customer | F6: =+'29'!F6+'30'!F6+'31'!F6 -> 19 | G6: =+'29'!G6+'30'!G6+'31'!G6 -> 209430.5 | H6: =+'29'!H6+'30'!H6+'31'!H6 -> 1900 | J6: =+'29'!J6+'30'!J6+'31'!J6 -> 0 | K6: =+'29'!K6+'30'!K6+'31'!K6 -> 0 | L6: =+'29'!L6+'30'!L6+'31'!L6 -> 0 | M6: =+'29'!M6+'30'!M6+'31'!M6 -> 0 | N6: =+'29'!N6+'30'!N6+'31'!N6 -> 19 | O6: =+'29'!O6+'30'!O6+'31'!O6 -> 209430.5 | P6: =+'29'!P6+'30'!P6+'31'!P6 -> 1900 | R6: 19 | S6: 209430.5 | T6: 0 | V6: =N6-R6 -> 0 | W6: =O6-S6 -> 0 | Y6: =V6 -> 0 | Z6: =W6 -> 0 | AB6: =O6 -> 209430.5 | AF6: =AB6-AD6 -> 209430.5 | AM6: =SUM(AG6:AL6) -> 0 | AN6: =AF6-AM6 -> 209430.5
A7: 2 | B7: A-1 MILLING CORPORATION | C7: METROBANK | D7: Customer | F7: =+'29'!F7+'30'!F7+'31'!F7 -> 4 | G7: =+'29'!G7+'30'!G7+'31'!G7 -> 651400 | H7: =+'29'!H7+'30'!H7+'31'!H7 -> 350 | J7: =+'29'!J7+'30'!J7+'31'!J7 -> 0 | K7: =+'29'!K7+'30'!K7+'31'!K7 -> 0 | L7: =+'29'!L7+'30'!L7+'31'!L7 -> 0 | N7: =+'29'!N7+'30'!N7+'31'!N7 -> 4 | O7: =+'29'!O7+'30'!O7+'31'!O7 -> 651400 | P7: =+'29'!P7+'30'!P7+'31'!P7 -> 350 | R7: 4 | S7: 651400 | T7: 0 | V7: =N7-R7 -> 0 | W7: =O7-S7 -> 0 | Y7: =V7 -> 0 | Z7: =W7 -> 0 | AB7: =O7 -> 651400 | AF7: =AB7-AD7 -> 651400 | AM7: =SUM(AG7:AL7) -> 0 | AN7: =AF7-AM7 -> 651400
A8: 3 | B8: A2M GLOBAL DISTRIBUTION INC. | C8: METROBANK | D8: Partner | F8: =+'29'!F8+'30'!F8+'31'!F8 -> 12 | G8: =+'29'!G8+'30'!G8+'31'!G8 -> 185249.89 | H8: =+'29'!H8+'30'!H8+'31'!H8 -> 600 | J8: =+'29'!J8+'30'!J8+'31'!J8 -> 0 | K8: =+'29'!K8+'30'!K8+'31'!K8 -> 0 | L8: =+'29'!L8+'30'!L8+'31'!L8 -> 0 | N8: =+'29'!N8+'30'!N8+'31'!N8 -> 12 | O8: =+'29'!O8+'30'!O8+'31'!O8 -> 185249.89 | P8: =+'29'!P8+'30'!P8+'31'!P8 -> 600 | R8: 12 | S8: 185249.89 | T8: 0 | V8: =N8-R8 -> 0 | W8: =O8-S8 -> 0 | Y8: =V8 -> 0 | Z8: =W8 -> 0 | AB8: =O8 -> 185249.89 | AF8: =AB8-AD8 -> 185249.89 | AM8: =SUM(AG8:AL8) -> 0 | AN8: =AF8-AM8 -> 185249.89
A9: 4 | B9: ABEJO WATERS CORP - CEBU | C9: BPI ONLINE | D9: Customer | F9: =+'29'!F9+'30'!F9+'31'!F9 -> 0 | G9: =+'29'!G9+'30'!G9+'31'!G9 -> 0 | H9: =+'29'!H9+'30'!H9+'31'!H9 -> 0 | J9: =+'29'!J9+'30'!J9+'31'!J9 -> 0 | K9: =+'29'!K9+'30'!K9+'31'!K9 -> 0 | L9: =+'29'!L9+'30'!L9+'31'!L9 -> 0 | N9: =+'29'!N9+'30'!N9+'31'!N9 -> 0 | O9: =+'29'!O9+'30'!O9+'31'!O9 -> 0 | P9: =+'29'!P9+'30'!P9+'31'!P9 -> 0 | R9: 0 | S9: 0 | T9: 0 | V9: =N9-R9 -> 0 | W9: =O9-S9 -> 0 | Y9: =V9 -> 0 | Z9: =W9 -> 0 | AB9: =O9 -> 0 | AF9: =AB9-AD9 -> 0 | AM9: =SUM(AG9:AL9) -> 0 | AN9: =AF9-AM9 -> 0
A10: 5 | B10: ABEJO WATERS CORP - TALISAY | C10: CHINABANK | D10: Customer | F10: =+'29'!F10+'30'!F10+'31'!F10 -> 0 | G10: =+'29'!G10+'30'!G10+'31'!G10 -> 0 | H10: =+'29'!H10+'30'!H10+'31'!H10 -> 0 | J10: =+'29'!J10+'30'!J10+'31'!J10 -> 0 | K10: =+'29'!K10+'30'!K10+'31'!K10 -> 0 | L10: =+'29'!L10+'30'!L10+'31'!L10 -> 0 | N10: =+'29'!N10+'30'!N10+'31'!N10 -> 0 | O10: =+'29'!O10+'30'!O10+'31'!O10 -> 0 | P10: =+'29'!P10+'30'!P10+'31'!P10 -> 0 | R10: 0 | S10: 0 | T10: 0 | V10: =N10-R10 -> 0 | W10: =O10-S10 -> 0 | Y10: =V10 -> 0 | Z10: =W10 -> 0 | AB10: =O10 -> 0 | AF10: =AB10-AD10 -> 0 | AM10: =SUM(AG10:AL10) -> 0 | AN10: =AF10-AM10 -> 0
A11: 6 | B11: AEON CREDIT SERVICE PHIL INC. API | C11: METROBANK | D11: Customer | F11: =+'29'!F11+'30'!F11+'31'!F11 -> 36 | G11: =+'29'!G11+'30'!G11+'31'!G11 -> 91903.77 | H11: =+'29'!H11+'30'!H11+'31'!H11 -> 540 | J11: =+'29'!J11+'30'!J11+'31'!J11 -> 0 | K11: =+'29'!K11+'30'!K11+'31'!K11 -> 0 | L11: =+'29'!L11+'30'!L11+'31'!L11 -> 0 | N11: =+'29'!N11+'30'!N11+'31'!N11 -> 36 | O11: =+'29'!O11+'30'!O11+'31'!O11 -> 91903.77 | P11: =+'29'!P11+'30'!P11+'31'!P11 -> 540 | R11: 36 | S11: 91903.77 | T11: 0 | V11: =N11-R11 -> 0 | W11: =O11-S11 -> 0 | Y11: =V11 -> 0 | Z11: =W11 -> 0 | AB11: =O11 -> 91903.77 | AF11: =AB11-AD11 -> 91903.77 | AM11: =SUM(AG11:AL11) -> 0 | AN11: =AF11-AM11 -> 91903.77
A12: 7 | B12: AF PAYMENTS (BEEP LOADING) | C12: BPI CHECK | D12: Customer | F12: =+'29'!F12+'30'!F12+'31'!F12 -> 0 | G12: =+'29'!G12+'30'!G12+'31'!G12 -> 0 | H12: =+'29'!H12+'30'!H12+'31'!H12 -> 0 | J12: =+'29'!J12+'30'!J12+'31'!J12 -> 0 | K12: =+'29'!K12+'30'!K12+'31'!K12 -> 0 | L12: =+'29'!L12+'30'!L12+'31'!L12 -> 0 | N12: =+'29'!N12+'30'!N12+'31'!N12 -> 0 | O12: =+'29'!O12+'30'!O12+'31'!O12 -> 0 | P12: =+'29'!P12+'30'!P12+'31'!P12 -> 0 | R12: 0 | S12: 0 | T12: 0 | V12: =N12-R12 -> 0 | W12: =O12-S12 -> 0 | Y12: =V12 -> 0 | Z12: =W12 -> 0 | AB12: =O12 -> 0 | AF12: =AB12-AD12 -> 0 | AM12: =SUM(AG12:AL12) -> 0 | AN12: =AF12-AM12 -> 0
A13: 8 | B13: AIA PHILIPPINES | C13: BPI | D13: Customer | F13: =+'29'!F13+'30'!F13+'31'!F13 -> 26 | G13: =+'29'!G13+'30'!G13+'31'!G13 -> 210044.67 | H13: =+'29'!H13+'30'!H13+'31'!H13 -> 650 | J13: =+'29'!J13+'30'!J13+'31'!J13 -> 0 | K13: =+'29'!K13+'30'!K13+'31'!K13 -> 0 | L13: =+'29'!L13+'30'!L13+'31'!L13 -> 0 | N13: =+'29'!N13+'30'!N13+'31'!N13 -> 26 | O13: =+'29'!O13+'30'!O13+'31'!O13 -> 210044.67 | P13: =+'29'!P13+'30'!P13+'31'!P13 -> 650 | R13: 26 | S13: 210044.67 | T13: 0 | V13: =N13-R13 -> 0 | W13: =O13-S13 -> 0 | Y13: =V13 -> 0 | Z13: =W13 -> 0 | AB13: =O13 -> 210044.67 | AF13: =AB13-AD13 -> 210044.67 | AM13: =SUM(AG13:AL13) -> 0 | AN13: =AF13-AM13 -> 210044.67
A14: 9 | B14: AIR ASIA/ZEST AIR | C14: BDO | D14: Partner | F14: =+'29'!F14+'30'!F14+'31'!F14 -> 13 | G14: =+'29'!G14+'30'!G14+'31'!G14 -> 131749.39 | H14: =+'29'!H14+'30'!H14+'31'!H14 -> 300 | J14: =+'29'!J14+'30'!J14+'31'!J14 -> 0 | K14: =+'29'!K14+'30'!K14+'31'!K14 -> 0 | L14: =+'29'!L14+'30'!L14+'31'!L14 -> 0 | N14: =+'29'!N14+'30'!N14+'31'!N14 -> 13 | O14: =+'29'!O14+'30'!O14+'31'!O14 -> 131749.39 | P14: =+'29'!P14+'30'!P14+'31'!P14 -> 300 | R14: 13 | S14: 131449.39 | T14: 300 | V14: =N14-R14 -> 0 | W14: =O14-S14 -> 300 | Y14: =V14 -> 0 | Z14: =W14 -> 300 | AB14: =O14 -> 131749.39 | AF14: =AB14-AD14 -> 131749.39 | AM14: =SUM(AG14:AL14) -> 0 | AN14: =AF14-AM14 -> 131749.39
A15: 10 | B15: AIR YOU GO TRAVEL PHILS CO. | C15: BDO | D15: Customer | F15: =+'29'!F15+'30'!F15+'31'!F15 -> 0 | G15: =+'29'!G15+'30'!G15+'31'!G15 -> 0 | H15: =+'29'!H15+'30'!H15+'31'!H15 -> 0 | J15: =+'29'!J15+'30'!J15+'31'!J15 -> 0 | K15: =+'29'!K15+'30'!K15+'31'!K15 -> 0 | L15: =+'29'!L15+'30'!L15+'31'!L15 -> 0 | N15: =+'29'!N15+'30'!N15+'31'!N15 -> 0 | O15: =+'29'!O15+'30'!O15+'31'!O15 -> 0 | P15: =+'29'!P15+'30'!P15+'31'!P15 -> 0 | R15: 0 | S15: 0 | T15: 0 | V15: =N15-R15 -> 0 | W15: =O15-S15 -> 0 | Y15: =V15 -> 0 | Z15: =W15 -> 0 | AB15: =O15 -> 0 | AF15: =AB15-AD15 -> 0 | AM15: =SUM(AG15:AL15) -> 0 | AN15: =AF15-AM15 -> 0
A16: 11 | B16: AKLAN CABLE NETWORK, INC. - LEMERY | D16: Customer | F16: =+'29'!F16+'30'!F16+'31'!F16 -> 0 | G16: =+'29'!G16+'30'!G16+'31'!G16 -> 0 | H16: =+'29'!H16+'30'!H16+'31'!H16 -> 0 | J16: =+'29'!J16+'30'!J16+'31'!J16 -> 0 | K16: =+'29'!K16+'30'!K16+'31'!K16 -> 0 | L16: =+'29'!L16+'30'!L16+'31'!L16 -> 0 | N16: =+'29'!N16+'30'!N16+'31'!N16 -> 0 | O16: =+'29'!O16+'30'!O16+'31'!O16 -> 0 | P16: =+'29'!P16+'30'!P16+'31'!P16 -> 0 | R16: 0 | S16: 0 | T16: 0 | V16: =N16-R16 -> 0 | W16: =O16-S16 -> 0 | Y16: =V16 -> 0 | Z16: =W16 -> 0 | AB16: =O16 -> 0 | AF16: =AB16-AD16 -> 0 | AM16: =SUM(AG16:AL16) -> 0 | AN16: =AF16-AM16 -> 0
A17: 12 | B17: ALFA- ALL FOOD ASIA, INC. | C17: METROBANK | D17: Customer | F17: =+'29'!F17+'30'!F17+'31'!F17 -> 0 | G17: =+'29'!G17+'30'!G17+'31'!G17 -> 0 | H17: =+'29'!H17+'30'!H17+'31'!H17 -> 0 | J17: =+'29'!J17+'30'!J17+'31'!J17 -> 0 | K17: =+'29'!K17+'30'!K17+'31'!K17 -> 0 | L17: =+'29'!L17+'30'!L17+'31'!L17 -> 0 | N17: =+'29'!N17+'30'!N17+'31'!N17 -> 0 | O17: =+'29'!O17+'30'!O17+'31'!O17 -> 0 | P17: =+'29'!P17+'30'!P17+'31'!P17 -> 0 | R17: 0 | S17: 0 | T17: 0 | V17: =N17-R17 -> 0 | W17: =O17-S17 -> 0 | Y17: =V17 -> 0 | Z17: =W17 -> 0 | AB17: =O17 -> 0 | AF17: =AB17-AD17 -> 0 | AM17: =SUM(AG17:AL17) -> 0 | AN17: =AF17-AM17 -> 0
A18: 13 | B18: AMBROSIA PHILS INC | C18: METROBANK | D18: Partner | F18: =+'29'!F18+'30'!F18+'31'!F18 -> 170 | G18: =+'29'!G18+'30'!G18+'31'!G18 -> 3947448.5 | H18: =+'29'!H18+'30'!H18+'31'!H18 -> 5300 | J18: =+'29'!J18+'30'!J18+'31'!J18 -> 0 | K18: =+'29'!K18+'30'!K18+'31'!K18 -> 0 | L18: =+'29'!L18+'30'!L18+'31'!L18 -> 0 | N18: =+'29'!N18+'30'!N18+'31'!N18 -> 170 | O18: =+'29'!O18+'30'!O18+'31'!O18 -> 3947448.5 | P18: =+'29'!P18+'30'!P18+'31'!P18 -> 5300 | R18: 170 | S18: 3942148.5 | T18: 5300 | V18: =N18-R18 -> 0 | W18: =O18-S18 -> 5300 | Y18: =V18 -> 0 | Z18: =W18 -> 5300 | AB18: =O18 -> 3947448.5 | AF18: =AB18-AD18 -> 3947448.5 | AM18: =SUM(AG18:AL18) -> 0 | AN18: =AF18-AM18 -> 3947448.5
A19: 14 | B19: ANECO | C19: BPI | D19: Customer | F19: =+'29'!F19+'30'!F19+'31'!F19 -> 21 | G19: =+'29'!G19+'30'!G19+'31'!G19 -> 60905.99 | H19: =+'29'!H19+'30'!H19+'31'!H19 -> 105 | J19: =+'29'!J19+'30'!J19+'31'!J19 -> 0 | K19: =+'29'!K19+'30'!K19+'31'!K19 -> 0 | L19: =+'29'!L19+'30'!L19+'31'!L19 -> 0 | N19: =+'29'!N19+'30'!N19+'31'!N19 -> 21 | O19: =+'29'!O19+'30'!O19+'31'!O19 -> 60905.99 | P19: =+'29'!P19+'30'!P19+'31'!P19 -> 105 | R19: 21 | S19: 60905.99 | T19: 0 | V19: =N19-R19 -> 0 | W19: =O19-S19 -> 0 | Y19: =V19 -> 0 | Z19: =W19 -> 0 | AB19: =O19 -> 60905.99 | AD19: 1866.0714 | AF19: =AB19-AD19 -> 59039.919 | AG19: 4169.1964 | AM19: =SUM(AG19:AL19) -> 4169.1964 | AN19: =AF19-AM19 -> 54870.722
A20: 15 | B20: ANECO COLLECTIONS | C20: BPI | D20: Customer | F20: =+'29'!F20+'30'!F20+'31'!F20 -> 0 | G20: =+'29'!G20+'30'!G20+'31'!G20 -> 0 | H20: =+'29'!H20+'30'!H20+'31'!H20 -> 0 | J20: =+'29'!J20+'30'!J20+'31'!J20 -> 0 | K20: =+'29'!K20+'30'!K20+'31'!K20 -> 0 | L20: =+'29'!L20+'30'!L20+'31'!L20 -> 0 | N20: =+'29'!N20+'30'!N20+'31'!N20 -> 0 | O20: =+'29'!O20+'30'!O20+'31'!O20 -> 0 | P20: =+'29'!P20+'30'!P20+'31'!P20 -> 0 | R20: 0 | S20: 0 | T20: 0 | V20: =N20-R20 -> 0 | W20: =O20-S20 -> 0 | Y20: =V20 -> 0 | Z20: =W20 -> 0 | AB20: =O20 -> 0 | AF20: =AB20-AD20 -> 0 | AG20: 58.928571 | AM20: =SUM(AG20:AL20) -> 58.928571 | AN20: =AF20-AM20 -> -58.928571
A21: 16 | B21: ANGELES CITY WATER DISTRICT | C21: LANBANK | D21: Customer | F21: =+'29'!F21+'30'!F21+'31'!F21 -> 0 | G21: =+'29'!G21+'30'!G21+'31'!G21 -> 0 | H21: =+'29'!H21+'30'!H21+'31'!H21 -> 0 | J21: =+'29'!J21+'30'!J21+'31'!J21 -> 0 | K21: =+'29'!K21+'30'!K21+'31'!K21 -> 0 | L21: =+'29'!L21+'30'!L21+'31'!L21 -> 0 | N21: =+'29'!N21+'30'!N21+'31'!N21 -> 0 | O21: =+'29'!O21+'30'!O21+'31'!O21 -> 0 | P21: =+'29'!P21+'30'!P21+'31'!P21 -> 0 | R21: 0 | S21: 0 | T21: 0 | V21: =N21-R21 -> 0 | W21: =O21-S21 -> 0 | Y21: =V21 -> 0 | Z21: =W21 -> 0 | AB21: =O21 -> 0 | AF21: =AB21-AD21 -> 0 | AM21: =SUM(AG21:AL21) -> 0 | AN21: =AF21-AM21 -> 0
A22: 17 | B22: AQUA CENTRO MWPV CORP. | C22: BPI ONLINE | D22: CusPart | F22: =+'29'!F22+'30'!F22+'31'!F22 -> 2 | G22: =+'29'!G22+'30'!G22+'31'!G22 -> 2500 | H22: =+'29'!H22+'30'!H22+'31'!H22 -> 14 | J22: =+'29'!J22+'30'!J22+'31'!J22 -> 0 | K22: =+'29'!K22+'30'!K22+'31'!K22 -> 0 | L22: =+'29'!L22+'30'!L22+'31'!L22 -> 0 | N22: =+'29'!N22+'30'!N22+'31'!N22 -> 2 | O22: =+'29'!O22+'30'!O22+'31'!O22 -> 2500 | P22: =+'29'!P22+'30'!P22+'31'!P22 -> 14 | R22: 2 | S22: 2500 | T22: 0 | V22: =N22-R22 -> 0 | W22: =O22-S22 -> 0 | Y22: =V22 -> 0 | Z22: =W22 -> 0 | AB22: =O22 -> 2500 | AF22: =AB22-AD22 -> 2500 | AM22: =SUM(AG22:AL22) -> 0 | AN22: =AF22-AM22 -> 2500
A23: 18 | B23: ASIALINK FINANCE CORPORATION | C23: BDO | D23: Partner M. | F23: =+'29'!F23+'30'!F23+'31'!F23 -> 1488 | G23: =+'29'!G23+'30'!G23+'31'!G23 -> 29805467 | H23: =+'29'!H23+'30'!H23+'31'!H23 -> 24912 | J23: =+'29'!J23+'30'!J23+'31'!J23 -> 0 | K23: =+'29'!K23+'30'!K23+'31'!K23 -> 0 | L23: =+'29'!L23+'30'!L23+'31'!L23 -> 0 | N23: =+'29'!N23+'30'!N23+'31'!N23 -> 1488 | O23: =+'29'!O23+'30'!O23+'31'!O23 -> 29805467 | P23: =+'29'!P23+'30'!P23+'31'!P23 -> 24912 | R23: 1488 | S23: 29805467 | T23: 0 | V23: =N23-R23 -> 0 | W23: =O23-S23 -> 0 | Y23: =V23 -> 0 | Z23: =W23 -> 0 | AB23: =O23 -> 29805467 | AD23: 207664.29 | AF23: =AB23-AD23 -> 29597803 | AG23: 637151.43 | AM23: =SUM(AG23:AL23) -> 637151.43 | AN23: =AF23-AM23 -> 28960652
A24: 19 | B24: ASIAN COLLEGE OF SCIENCE AND TECHNOLOGY FDN. INC. | C24: BPI ONLINE | D24: Customer | F24: =+'29'!F24+'30'!F24+'31'!F24 -> 0 | G24: =+'29'!G24+'30'!G24+'31'!G24 -> 0 | H24: =+'29'!H24+'30'!H24+'31'!H24 -> 0 | J24: =+'29'!J24+'30'!J24+'31'!J24 -> 0 | K24: =+'29'!K24+'30'!K24+'31'!K24 -> 0 | L24: =+'29'!L24+'30'!L24+'31'!L24 -> 0 | N24: =+'29'!N24+'30'!N24+'31'!N24 -> 0 | O24: =+'29'!O24+'30'!O24+'31'!O24 -> 0 | P24: =+'29'!P24+'30'!P24+'31'!P24 -> 0 | R24: 0 | S24: 0 | T24: 0 | V24: =N24-R24 -> 0 | W24: =O24-S24 -> 0 | Y24: =V24 -> 0 | Z24: =W24 -> 0 | AB24: =O24 -> 0 | AF24: =AB24-AD24 -> 0 | AM24: =SUM(AG24:AL24) -> 0 | AN24: =AF24-AM24 -> 0
A25: 20 | B25: ASIAN COLLEGE OF TECHNOLOGY (ACT) | D25: Customer | F25: =+'29'!F25+'30'!F25+'31'!F25 -> 0 | G25: =+'29'!G25+'30'!G25+'31'!G25 -> 0 | H25: =+'29'!H25+'30'!H25+'31'!H25 -> 0 | J25: =+'29'!J25+'30'!J25+'31'!J25 -> 0 | K25: =+'29'!K25+'30'!K25+'31'!K25 -> 0 | L25: =+'29'!L25+'30'!L25+'31'!L25 -> 0 | N25: =+'29'!N25+'30'!N25+'31'!N25 -> 0 | O25: =+'29'!O25+'30'!O25+'31'!O25 -> 0 | P25: =+'29'!P25+'30'!P25+'31'!P25 -> 0 | R25: 0 | S25: 0 | T25: 0 | V25: =N25-R25 -> 0 | W25: =O25-S25 -> 0 | Y25: =V25 -> 0 | Z25: =W25 -> 0 | AB25: =O25 -> 0 | AF25: =AB25-AD25 -> 0 | AM25: =SUM(AG25:AL25) -> 0 | AN25: =AF25-AM25 -> 0
A26: 21 | B26: ASIAN INTERNATIONAL SCHOOL OF AERONAUTICS AND TECHNOLOGY (AISAT) CORP. | C26: METROBANK | D26: Customer | F26: =+'29'!F26+'30'!F26+'31'!F26 -> 2 | G26: =+'29'!G26+'30'!G26+'31'!G26 -> 18200 | H26: =+'29'!H26+'30'!H26+'31'!H26 -> 60 | J26: =+'29'!J26+'30'!J26+'31'!J26 -> 0 | K26: =+'29'!K26+'30'!K26+'31'!K26 -> 0 | L26: =+'29'!L26+'30'!L26+'31'!L26 -> 0 | N26: =+'29'!N26+'30'!N26+'31'!N26 -> 2 | O26: =+'29'!O26+'30'!O26+'31'!O26 -> 18200 | P26: =+'29'!P26+'30'!P26+'31'!P26 -> 60 | R26: 2 | S26: 18200 | T26: 0 | V26: =N26-R26 -> 0 | W26: =O26-S26 -> 0 | Y26: =V26 -> 0 | Z26: =W26 -> 0 | AB26: =O26 -> 18200 | AF26: =AB26-AD26 -> 18200 | AM26: =SUM(AG26:AL26) -> 0 | AN26: =AF26-AM26 -> 18200
A27: 22 | B27: ATENEO DE DAVAO UNIVERSITY | C27: PNB | D27: Customer | F27: =+'29'!F27+'30'!F27+'31'!F27 -> 0 | G27: =+'29'!G27+'30'!G27+'31'!G27 -> 0 | H27: =+'29'!H27+'30'!H27+'31'!H27 -> 0 | J27: =+'29'!J27+'30'!J27+'31'!J27 -> 0 | K27: =+'29'!K27+'30'!K27+'31'!K27 -> 0 | L27: =+'29'!L27+'30'!L27+'31'!L27 -> 0 | N27: =+'29'!N27+'30'!N27+'31'!N27 -> 0 | O27: =+'29'!O27+'30'!O27+'31'!O27 -> 0 | P27: =+'29'!P27+'30'!P27+'31'!P27 -> 0 | R27: 0 | S27: 0 | T27: 0 | V27: =N27-R27 -> 0 | W27: =O27-S27 -> 0 | Y27: =V27 -> 0 | Z27: =W27 -> 0 | AB27: =O27 -> 0 | AF27: =AB27-AD27 -> 0 | AM27: =SUM(AG27:AL27) -> 0 | AN27: =AF27-AM27 -> 0
A28: 23 | B28: ATENEO DE ZAMBOANGA UNIVERSITY | C28: METROBANK | D28: Customer | F28: =+'29'!F28+'30'!F28+'31'!F28 -> 0 | G28: =+'29'!G28+'30'!G28+'31'!G28 -> 0 | H28: =+'29'!H28+'30'!H28+'31'!H28 -> 0 | J28: =+'29'!J28+'30'!J28+'31'!J28 -> 0 | K28: =+'29'!K28+'30'!K28+'31'!K28 -> 0 | L28: =+'29'!L28+'30'!L28+'31'!L28 -> 0 | N28: =+'29'!N28+'30'!N28+'31'!N28 -> 0 | O28: =+'29'!O28+'30'!O28+'31'!O28 -> 0 | P28: =+'29'!P28+'30'!P28+'31'!P28 -> 0 | R28: 0 | S28: 0 | T28: 0 | V28: =N28-R28 -> 0 | W28: =O28-S28 -> 0 | Y28: =V28 -> 0 | Z28: =W28 -> 0 | AB28: =O28 -> 0 | AF28: =AB28-AD28 -> 0 | AM28: =SUM(AG28:AL28) -> 0 | AN28: =AF28-AM28 -> 0
A29: 24 | B29: ATLAS CEBU CORN MILL CORP | C29: CHINABANK | D29: Customer | F29: =+'29'!F29+'30'!F29+'31'!F29 -> 11 | G29: =+'29'!G29+'30'!G29+'31'!G29 -> 634315 | H29: =+'29'!H29+'30'!H29+'31'!H29 -> 550 | J29: =+'29'!J29+'30'!J29+'31'!J29 -> 0 | K29: =+'29'!K29+'30'!K29+'31'!K29 -> 0 | L29: =+'29'!L29+'30'!L29+'31'!L29 -> 0 | N29: =+'29'!N29+'30'!N29+'31'!N29 -> 11 | O29: =+'29'!O29+'30'!O29+'31'!O29 -> 634315 | P29: =+'29'!P29+'30'!P29+'31'!P29 -> 550 | R29: 11 | S29: 634315 | T29: 0 | V29: =N29-R29 -> 0 | W29: =O29-S29 -> 0 | Y29: =V29 -> 0 | Z29: =W29 -> 0 | AB29: =O29 -> 634315 | AF29: =AB29-AD29 -> 634315 | AM29: =SUM(AG29:AL29) -> 0 | AN29: =AF29-AM29 -> 634315
A30: 25 | B30: BAKERS BEST MARKETING CORPORATION | C30: BPI | D30: Customer | F30: =+'29'!F30+'30'!F30+'31'!F30 -> 7 | G30: =+'29'!G30+'30'!G30+'31'!G30 -> 48204 | H30: =+'29'!H30+'30'!H30+'31'!H30 -> 210 | J30: =+'29'!J30+'30'!J30+'31'!J30 -> 0 | K30: =+'29'!K30+'30'!K30+'31'!K30 -> 0 | L30: =+'29'!L30+'30'!L30+'31'!L30 -> 0 | N30: =+'29'!N30+'30'!N30+'31'!N30 -> 7 | O30: =+'29'!O30+'30'!O30+'31'!O30 -> 48204 | P30: =+'29'!P30+'30'!P30+'31'!P30 -> 210 | R30: 7 | S30: 48204 | T30: 0 | V30: =N30-R30 -> 0 | W30: =O30-S30 -> 0 | Y30: =V30 -> 0 | Z30: =W30 -> 0 | AB30: =O30 -> 48204 | AF30: =AB30-AD30 -> 48204 | AM30: =SUM(AG30:AL30) -> 0 | AN30: =AF30-AM30 -> 48204
A31: 26 | B31: BALAMBAN ENERZONE | D31: No Billers | F31: =+'29'!F31+'30'!F31+'31'!F31 -> 0 | G31: =+'29'!G31+'30'!G31+'31'!G31 -> 0 | H31: =+'29'!H31+'30'!H31+'31'!H31 -> 0 | J31: =+'29'!J31+'30'!J31+'31'!J31 -> 0 | K31: =+'29'!K31+'30'!K31+'31'!K31 -> 0 | L31: =+'29'!L31+'30'!L31+'31'!L31 -> 0 | N31: =+'29'!N31+'30'!N31+'31'!N31 -> 0 | O31: =+'29'!O31+'30'!O31+'31'!O31 -> 0 | P31: =+'29'!P31+'30'!P31+'31'!P31 -> 0 | R31: 0 | S31: 0 | T31: 0 | V31: =N31-R31 -> 0 | W31: =O31-S31 -> 0 | Y31: =V31 -> 0 | Z31: =W31 -> 0 | AB31: =O31 -> 0 | AF31: =AB31-AD31 -> 0 | AM31: =SUM(AG31:AL31) -> 0 | AN31: =AF31-AM31 -> 0
A32: 27 | B32: BALAMBAN WATER DISTRICT | C32: LANBANK | D32: Customer | F32: =+'29'!F32+'30'!F32+'31'!F32 -> 27 | G32: =+'29'!G32+'30'!G32+'31'!G32 -> 12767.65 | H32: =+'29'!H32+'30'!H32+'31'!H32 -> 270 | J32: =+'29'!J32+'30'!J32+'31'!J32 -> 0 | K32: =+'29'!K32+'30'!K32+'31'!K32 -> 0 | L32: =+'29'!L32+'30'!L32+'31'!L32 -> 0 | N32: =+'29'!N32+'30'!N32+'31'!N32 -> 27 | O32: =+'29'!O32+'30'!O32+'31'!O32 -> 12767.65 | P32: =+'29'!P32+'30'!P32+'31'!P32 -> 270 | R32: 27 | S32: 12767.65 | T32: 0 | V32: =N32-R32 -> 0 | W32: =O32-S32 -> 0 | Y32: =V32 -> 0 | Z32: =W32 -> 0 | AB32: =O32 -> 12767.65 | AF32: =AB32-AD32 -> 12767.65 | AM32: =SUM(AG32:AL32) -> 0 | AN32: =AF32-AM32 -> 12767.65
A33: 28 | B33: BASIC WATER ENTERPRISES INC. | C33: METROBANK | D33: Partner | F33: =+'29'!F33+'30'!F33+'31'!F33 -> 0 | G33: =+'29'!G33+'30'!G33+'31'!G33 -> 0 | H33: =+'29'!H33+'30'!H33+'31'!H33 -> 0 | J33: =+'29'!J33+'30'!J33+'31'!J33 -> 0 | K33: =+'29'!K33+'30'!K33+'31'!K33 -> 0 | L33: =+'29'!L33+'30'!L33+'31'!L33 -> 0 | N33: =+'29'!N33+'30'!N33+'31'!N33 -> 0 | O33: =+'29'!O33+'30'!O33+'31'!O33 -> 0 | P33: =+'29'!P33+'30'!P33+'31'!P33 -> 0 | R33: 0 | S33: 0 | T33: 0 | V33: =N33-R33 -> 0 | W33: =O33-S33 -> 0 | Y33: =V33 -> 0 | Z33: =W33 -> 0 | AB33: =O33 -> 0 | AF33: =AB33-AD33 -> 0 | AM33: =SUM(AG33:AL33) -> 0 | AN33: =AF33-AM33 -> 0
A34: 29 | B34: BATANGAS CATV, INC. - BATANGAS | D34: Customer | F34: =+'29'!F34+'30'!F34+'31'!F34 -> 0 | G34: =+'29'!G34+'30'!G34+'31'!G34 -> 0 | H34: =+'29'!H34+'30'!H34+'31'!H34 -> 0 | J34: =+'29'!J34+'30'!J34+'31'!J34 -> 0 | K34: =+'29'!K34+'30'!K34+'31'!K34 -> 0 | L34: =+'29'!L34+'30'!L34+'31'!L34 -> 0 | N34: =+'29'!N34+'30'!N34+'31'!N34 -> 0 | O34: =+'29'!O34+'30'!O34+'31'!O34 -> 0 | P34: =+'29'!P34+'30'!P34+'31'!P34 -> 0 | R34: 0 | S34: 0 | T34: 0 | V34: =N34-R34 -> 0 | W34: =O34-S34 -> 0 | Y34: =V34 -> 0 | Z34: =W34 -> 0 | AB34: =O34 -> 0 | AF34: =AB34-AD34 -> 0 | AM34: =SUM(AG34:AL34) -> 0 | AN34: =AF34-AM34 -> 0
A35: 30 | B35: BATANGAS CATV, INC. - BAUAN | D35: Customer | F35: =+'29'!F35+'30'!F35+'31'!F35 -> 0 | G35: =+'29'!G35+'30'!G35+'31'!G35 -> 0 | H35: =+'29'!H35+'30'!H35+'31'!H35 -> 0 | J35: =+'29'!J35+'30'!J35+'31'!J35 -> 0 | K35: =+'29'!K35+'30'!K35+'31'!K35 -> 0 | L35: =+'29'!L35+'30'!L35+'31'!L35 -> 0 | N35: =+'29'!N35+'30'!N35+'31'!N35 -> 0 | O35: =+'29'!O35+'30'!O35+'31'!O35 -> 0 | P35: =+'29'!P35+'30'!P35+'31'!P35 -> 0 | R35: 0 | S35: 0 | T35: 0 | V35: =N35-R35 -> 0 | W35: =O35-S35 -> 0 | Y35: =V35 -> 0 | Z35: =W35 -> 0 | AB35: =O35 -> 0 | AF35: =AB35-AD35 -> 0 | AM35: =SUM(AG35:AL35) -> 0 | AN35: =AF35-AM35 -> 0
A36: 31 | B36: BAYAD CENTER - NBI | D36: No Billers | F36: =+'29'!F36+'30'!F36+'31'!F36 -> 0 | G36: =+'29'!G36+'30'!G36+'31'!G36 -> 0 | H36: =+'29'!H36+'30'!H36+'31'!H36 -> 0 | J36: =+'29'!J36+'30'!J36+'31'!J36 -> 0 | K36: =+'29'!K36+'30'!K36+'31'!K36 -> 0 | L36: =+'29'!L36+'30'!L36+'31'!L36 -> 0 | N36: =+'29'!N36+'30'!N36+'31'!N36 -> 0 | O36: =+'29'!O36+'30'!O36+'31'!O36 -> 0 | P36: =+'29'!P36+'30'!P36+'31'!P36 -> 0 | R36: 0 | S36: 0 | T36: 0 | V36: =N36-R36 -> 0 | W36: =O36-S36 -> 0 | Y36: =V36 -> 0 | Z36: =W36 -> 0 | AB36: =O36 -> 0 | AF36: =AB36-AD36 -> 0 | AM36: =SUM(AG36:AL36) -> 0 | AN36: =AF36-AM36 -> 0
A37: 32 | B37: BAYAN TELECOMMUNICATIONS INC | C37: BDO | D37: CusPart | F37: =+'29'!F37+'30'!F37+'31'!F37 -> 0 | G37: =+'29'!G37+'30'!G37+'31'!G37 -> 0 | H37: =+'29'!H37+'30'!H37+'31'!H37 -> 0 | J37: =+'29'!J37+'30'!J37+'31'!J37 -> 0 | K37: =+'29'!K37+'30'!K37+'31'!K37 -> 0 | L37: =+'29'!L37+'30'!L37+'31'!L37 -> 0 | N37: =+'29'!N37+'30'!N37+'31'!N37 -> 0 | O37: =+'29'!O37+'30'!O37+'31'!O37 -> 0 | P37: =+'29'!P37+'30'!P37+'31'!P37 -> 0 | R37: 0 | S37: 0 | T37: 0 | V37: =N37-R37 -> 0 | W37: =O37-S37 -> 0 | Y37: =V37 -> 0 | Z37: =W37 -> 0 | AB37: =O37 -> 0 | AF37: =AB37-AD37 -> 0 | AM37: =SUM(AG37:AL37) -> 0 | AN37: =AF37-AM37 -> 0
A38: 33 | B38: BBBROTHERS DV GEN. MDSE INC | C38: BDO ONLINE | D38: Customer | F38: =+'29'!F38+'30'!F38+'31'!F38 -> 5 | G38: =+'29'!G38+'30'!G38+'31'!G38 -> 58165 | H38: =+'29'!H38+'30'!H38+'31'!H38 -> 150 | J38: =+'29'!J38+'30'!J38+'31'!J38 -> 0 | K38: =+'29'!K38+'30'!K38+'31'!K38 -> 0 | L38: =+'29'!L38+'30'!L38+'31'!L38 -> 0 | N38: =+'29'!N38+'30'!N38+'31'!N38 -> 5 | O38: =+'29'!O38+'30'!O38+'31'!O38 -> 58165 | P38: =+'29'!P38+'30'!P38+'31'!P38 -> 150 | R38: 5 | S38: 58165 | T38: 0 | V38: =N38-R38 -> 0 | W38: =O38-S38 -> 0 | Y38: =V38 -> 0 | Z38: =W38 -> 0 | AB38: =O38 -> 58165 | AF38: =AB38-AD38 -> 58165 | AM38: =SUM(AG38:AL38) -> 0 | AN38: =AF38-AM38 -> 58165
A39: 34 | B39: BBBROTHERS LAGUNA INC 001 | C39: BDO ONLINE | D39: Customer | F39: =+'29'!F39+'30'!F39+'31'!F39 -> 0 | G39: =+'29'!G39+'30'!G39+'31'!G39 -> 0 | H39: =+'29'!H39+'30'!H39+'31'!H39 -> 0 | J39: =+'29'!J39+'30'!J39+'31'!J39 -> 0 | K39: =+'29'!K39+'30'!K39+'31'!K39 -> 0 | L39: =+'29'!L39+'30'!L39+'31'!L39 -> 0 | N39: =+'29'!N39+'30'!N39+'31'!N39 -> 0 | O39: =+'29'!O39+'30'!O39+'31'!O39 -> 0 | P39: =+'29'!P39+'30'!P39+'31'!P39 -> 0 | R39: 0 | S39: 0 | T39: 0 | V39: =N39-R39 -> 0 | W39: =O39-S39 -> 0 | Y39: =V39 -> 0 | Z39: =W39 -> 0 | AB39: =O39 -> 0 | AF39: =AB39-AD39 -> 0 | AM39: =SUM(AG39:AL39) -> 0 | AN39: =AF39-AM39 -> 0
A40: 35 | B40: BBBROTHERS LAGUNA INC 002 | C40: BDO ONLINE | D40: Customer | F40: =+'29'!F40+'30'!F40+'31'!F40 -> 0 | G40: =+'29'!G40+'30'!G40+'31'!G40 -> 0 | H40: =+'29'!H40+'30'!H40+'31'!H40 -> 0 | J40: =+'29'!J40+'30'!J40+'31'!J40 -> 0 | K40: =+'29'!K40+'30'!K40+'31'!K40 -> 0 | L40: =+'29'!L40+'30'!L40+'31'!L40 -> 0 | N40: =+'29'!N40+'30'!N40+'31'!N40 -> 0 | O40: =+'29'!O40+'30'!O40+'31'!O40 -> 0 | P40: =+'29'!P40+'30'!P40+'31'!P40 -> 0 | R40: 0 | S40: 0 | T40: 0 | V40: =N40-R40 -> 0 | W40: =O40-S40 -> 0 | Y40: =V40 -> 0 | Z40: =W40 -> 0 | AB40: =O40 -> 0 | AF40: =AB40-AD40 -> 0 | AM40: =SUM(AG40:AL40) -> 0 | AN40: =AF40-AM40 -> 0
A41: 36 | B41: BBBROTHERS MASBATE GEN. MDSE INC | C41: BDO ONLINE | D41: Customer | F41: =+'29'!F41+'30'!F41+'31'!F41 -> 2 | G41: =+'29'!G41+'30'!G41+'31'!G41 -> 25720 | H41: =+'29'!H41+'30'!H41+'31'!H41 -> 60 | J41: =+'29'!J41+'30'!J41+'31'!J41 -> 0 | K41: =+'29'!K41+'30'!K41+'31'!K41 -> 0 | L41: =+'29'!L41+'30'!L41+'31'!L41 -> 0 | N41: =+'29'!N41+'30'!N41+'31'!N41 -> 2 | O41: =+'29'!O41+'30'!O41+'31'!O41 -> 25720 | P41: =+'29'!P41+'30'!P41+'31'!P41 -> 60 | R41: 2 | S41: 25720 | T41: 0 | V41: =N41-R41 -> 0 | W41: =O41-S41 -> 0 | Y41: =V41 -> 0 | Z41: =W41 -> 0 | AB41: =O41 -> 25720 | AF41: =AB41-AD41 -> 25720 | AM41: =SUM(AG41:AL41) -> 0 | AN41: =AF41-AM41 -> 25720
A42: 37 | B42: BBBROTHERS MINDANAO INC 001 | C42: BDO ONLINE | D42: Customer | F42: =+'29'!F42+'30'!F42+'31'!F42 -> 0 | G42: =+'29'!G42+'30'!G42+'31'!G42 -> 0 | H42: =+'29'!H42+'30'!H42+'31'!H42 -> 0 | J42: =+'29'!J42+'30'!J42+'31'!J42 -> 0 | K42: =+'29'!K42+'30'!K42+'31'!K42 -> 0 | L42: =+'29'!L42+'30'!L42+'31'!L42 -> 0 | N42: =+'29'!N42+'30'!N42+'31'!N42 -> 0 | O42: =+'29'!O42+'30'!O42+'31'!O42 -> 0 | P42: =+'29'!P42+'30'!P42+'31'!P42 -> 0 | R42: 0 | S42: 0 | T42: 0 | V42: =N42-R42 -> 0 | W42: =O42-S42 -> 0 | Y42: =V42 -> 0 | Z42: =W42 -> 0 | AB42: =O42 -> 0 | AF42: =AB42-AD42 -> 0 | AM42: =SUM(AG42:AL42) -> 0 | AN42: =AF42-AM42 -> 0
A43: 38 | B43: BBBROTHERS MINDANAO INC 002 | C43: BDO ONLINE | D43: Customer | F43: =+'29'!F43+'30'!F43+'31'!F43 -> 0 | G43: =+'29'!G43+'30'!G43+'31'!G43 -> 0 | H43: =+'29'!H43+'30'!H43+'31'!H43 -> 0 | J43: =+'29'!J43+'30'!J43+'31'!J43 -> 0 | K43: =+'29'!K43+'30'!K43+'31'!K43 -> 0 | L43: =+'29'!L43+'30'!L43+'31'!L43 -> 0 | N43: =+'29'!N43+'30'!N43+'31'!N43 -> 0 | O43: =+'29'!O43+'30'!O43+'31'!O43 -> 0 | P43: =+'29'!P43+'30'!P43+'31'!P43 -> 0 | R43: 0 | S43: 0 | T43: 0 | V43: =N43-R43 -> 0 | W43: =O43-S43 -> 0 | Y43: =V43 -> 0 | Z43: =W43 -> 0 | AB43: =O43 -> 0 | AF43: =AB43-AD43 -> 0 | AM43: =SUM(AG43:AL43) -> 0 | AN43: =AF43-AM43 -> 0
A44: 39 | B44: BBBROTHERS PHIL-BDO | C44: BDO | D44: Customer | F44: =+'29'!F44+'30'!F44+'31'!F44 -> 0 | G44: =+'29'!G44+'30'!G44+'31'!G44 -> 0 | H44: =+'29'!H44+'30'!H44+'31'!H44 -> 0 | J44: =+'29'!J44+'30'!J44+'31'!J44 -> 0 | K44: =+'29'!K44+'30'!K44+'31'!K44 -> 0 | L44: =+'29'!L44+'30'!L44+'31'!L44 -> 0 | N44: =+'29'!N44+'30'!N44+'31'!N44 -> 0 | O44: =+'29'!O44+'30'!O44+'31'!O44 -> 0 | P44: =+'29'!P44+'30'!P44+'31'!P44 -> 0 | R44: 0 | S44: 0 | T44: 0 | V44: =N44-R44 -> 0 | W44: =O44-S44 -> 0 | Y44: =V44 -> 0 | Z44: =W44 -> 0 | AB44: =O44 -> 0 | AF44: =AB44-AD44 -> 0 | AM44: =SUM(AG44:AL44) -> 0 | AN44: =AF44-AM44 -> 0
A45: 40 | B45: BBBROTHERS PHIL-BPI | C45: BPI | D45: Customer | F45: =+'29'!F45+'30'!F45+'31'!F45 -> 0 | G45: =+'29'!G45+'30'!G45+'31'!G45 -> 0 | H45: =+'29'!H45+'30'!H45+'31'!H45 -> 0 | J45: =+'29'!J45+'30'!J45+'31'!J45 -> 0 | K45: =+'29'!K45+'30'!K45+'31'!K45 -> 0 | L45: =+'29'!L45+'30'!L45+'31'!L45 -> 0 | N45: =+'29'!N45+'30'!N45+'31'!N45 -> 0 | O45: =+'29'!O45+'30'!O45+'31'!O45 -> 0 | P45: =+'29'!P45+'30'!P45+'31'!P45 -> 0 | R45: 0 | S45: 0 | T45: 0 | V45: =N45-R45 -> 0 | W45: =O45-S45 -> 0 | Y45: =V45 -> 0 | Z45: =W45 -> 0 | AB45: =O45 -> 0 | AF45: =AB45-AD45 -> 0 | AM45: =SUM(AG45:AL45) -> 0 | AN45: =AF45-AM45 -> 0
A46: 41 | B46: BBBROTHERS PHIL-DV/PNB | C46: PNB | D46: Customer | F46: =+'29'!F46+'30'!F46+'31'!F46 -> 0 | G46: =+'29'!G46+'30'!G46+'31'!G46 -> 0 | H46: =+'29'!H46+'30'!H46+'31'!H46 -> 0 | J46: =+'29'!J46+'30'!J46+'31'!J46 -> 0 | K46: =+'29'!K46+'30'!K46+'31'!K46 -> 0 | L46: =+'29'!L46+'30'!L46+'31'!L46 -> 0 | N46: =+'29'!N46+'30'!N46+'31'!N46 -> 0 | O46: =+'29'!O46+'30'!O46+'31'!O46 -> 0 | P46: =+'29'!P46+'30'!P46+'31'!P46 -> 0 | R46: 0 | S46: 0 | T46: 0 | V46: =N46-R46 -> 0 | W46: =O46-S46 -> 0 | Y46: =V46 -> 0 | Z46: =W46 -> 0 | AB46: =O46 -> 0 | AF46: =AB46-AD46 -> 0 | AM46: =SUM(AG46:AL46) -> 0 | AN46: =AF46-AM46 -> 0
A47: 42 | B47: BBBROTHERS PHILIPPINES INC 001 | C47: BDO ONLINE | D47: Customer | F47: =+'29'!F47+'30'!F47+'31'!F47 -> 63 | G47: =+'29'!G47+'30'!G47+'31'!G47 -> 737612 | H47: =+'29'!H47+'30'!H47+'31'!H47 -> 1890 | J47: =+'29'!J47+'30'!J47+'31'!J47 -> 0 | K47: =+'29'!K47+'30'!K47+'31'!K47 -> 0 | L47: =+'29'!L47+'30'!L47+'31'!L47 -> 0 | N47: =+'29'!N47+'30'!N47+'31'!N47 -> 63 | O47: =+'29'!O47+'30'!O47+'31'!O47 -> 737612 | P47: =+'29'!P47+'30'!P47+'31'!P47 -> 1890 | R47: 63 | S47: 737612 | T47: 0 | V47: =N47-R47 -> 0 | W47: =O47-S47 -> 0 | Y47: =V47 -> 0 | Z47: =W47 -> 0 | AB47: =O47 -> 737612 | AF47: =AB47-AD47 -> 737612 | AM47: =SUM(AG47:AL47) -> 0 | AN47: =AF47-AM47 -> 737612
A48: 43 | B48: BBBROTHERS PHILLIPINES INC 002 | C48: BDO ONLINE | D48: Customer | F48: =+'29'!F48+'30'!F48+'31'!F48 -> 43 | G48: =+'29'!G48+'30'!G48+'31'!G48 -> 531204 | H48: =+'29'!H48+'30'!H48+'31'!H48 -> 1290 | J48: =+'29'!J48+'30'!J48+'31'!J48 -> 0 | K48: =+'29'!K48+'30'!K48+'31'!K48 -> 0 | L48: =+'29'!L48+'30'!L48+'31'!L48 -> 0 | N48: =+'29'!N48+'30'!N48+'31'!N48 -> 43 | O48: =+'29'!O48+'30'!O48+'31'!O48 -> 531204 | P48: =+'29'!P48+'30'!P48+'31'!P48 -> 1290 | R48: 43 | S48: 531204 | T48: 0 | V48: =N48-R48 -> 0 | W48: =O48-S48 -> 0 | Y48: =V48 -> 0 | Z48: =W48 -> 0 | AB48: =O48 -> 531204 | AF48: =AB48-AD48 -> 531204 | AM48: =SUM(AG48:AL48) -> 0 | AN48: =AF48-AM48 -> 531204
... A54: 49 | B54: BDMPC-MAIN OFFICE | C54: BDO | D54: Customer | F54: =+'29'!F54+'30'!F54+'31'!F54 -> 1 | G54: =+'29'!G54+'30'!G54+'31'!G54 -> 1000 | H54: =+'29'!H54+'30'!H54+'31'!H54 -> 50 | J54: =+'29'!J54+'30'!J54+'31'!J54 -> 0 | K54: =+'29'!K54+'30'!K54+'31'!K54 -> 0 | L54: =+'29'!L54+'30'!L54+'31'!L54 -> 0 | N54: =+'29'!N54+'30'!N54+'31'!N54 -> 1 | O54: =+'29'!O54+'30'!O54+'31'!O54 -> 1000 | P54: =+'29'!P54+'30'!P54+'31'!P54 -> 50 | R54: 1 | S54: 1000 | T54: 0 | V54: =N54-R54 -> 0 | W54: =O54-S54 -> 0 | Y54: =V54 -> 0 | Z54: =W54 -> 0 | AB54: =O54 -> 1000 | AF54: =AB54-AD54 -> 1000 | AM54: =SUM(AG54:AL54) -> 0 | AN54: =AF54-AM54 -> 1000
A55: 50 | B55: BDMPC-PANGLAO | D55: Customer | F55: =+'29'!F55+'30'!F55+'31'!F55 -> 0 | G55: =+'29'!G55+'30'!G55+'31'!G55 -> 0 | H55: =+'29'!H55+'30'!H55+'31'!H55 -> 0 | J55: =+'29'!J55+'30'!J55+'31'!J55 -> 0 | K55: =+'29'!K55+'30'!K55+'31'!K55 -> 0 | L55: =+'29'!L55+'30'!L55+'31'!L55 -> 0 | N55: =+'29'!N55+'30'!N55+'31'!N55 -> 0 | O55: =+'29'!O55+'30'!O55+'31'!O55 -> 0 | P55: =+'29'!P55+'30'!P55+'31'!P55 -> 0 | R55: 0 | S55: 0 | T55: 0 | V55: =N55-R55 -> 0 | W55: =O55-S55 -> 0 | Y55: =V55 -> 0 | Z55: =W55 -> 0 | AB55: =O55 -> 0 | AF55: =AB55-AD55 -> 0 | AM55: =SUM(AG55:AL55) -> 0 | AN55: =AF55-AM55 -> 0
A56: 51 | B56: BDMPC-TUBIGON | C56: METROBANK | D56: Customer | F56: =+'29'!F56+'30'!F56+'31'!F56 -> 2 | G56: =+'29'!G56+'30'!G56+'31'!G56 -> 6353 | H56: =+'29'!H56+'30'!H56+'31'!H56 -> 100 | J56: =+'29'!J56+'30'!J56+'31'!J56 -> 0 | K56: =+'29'!K56+'30'!K56+'31'!K56 -> 0 | L56: =+'29'!L56+'30'!L56+'31'!L56 -> 0 | N56: =+'29'!N56+'30'!N56+'31'!N56 -> 2 | O56: =+'29'!O56+'30'!O56+'31'!O56 -> 6353 | P56: =+'29'!P56+'30'!P56+'31'!P56 -> 100 | R56: 2 | S56: 6353 | T56: 0 | V56: =N56-R56 -> 0 | W56: =O56-S56 -> 0 | Y56: =V56 -> 0 | Z56: =W56 -> 0 | AB56: =O56 -> 6353 | AF56: =AB56-AD56 -> 6353 | AM56: =SUM(AG56:AL56) -> 0 | AN56: =AF56-AM56 -> 6353
A57: 52 | B57: BDMPC-UBAY | C57: PNB | D57: Customer | F57: =+'29'!F57+'30'!F57+'31'!F57 -> 0 | G57: =+'29'!G57+'30'!G57+'31'!G57 -> 0 | H57: =+'29'!H57+'30'!H57+'31'!H57 -> 0 | J57: =+'29'!J57+'30'!J57+'31'!J57 -> 0 | K57: =+'29'!K57+'30'!K57+'31'!K57 -> 0 | L57: =+'29'!L57+'30'!L57+'31'!L57 -> 0 | N57: =+'29'!N57+'30'!N57+'31'!N57 -> 0 | O57: =+'29'!O57+'30'!O57+'31'!O57 -> 0 | P57: =+'29'!P57+'30'!P57+'31'!P57 -> 0 | R57: 0 | S57: 0 | T57: 0 | V57: =N57-R57 -> 0 | W57: =O57-S57 -> 0 | Y57: =V57 -> 0 | Z57: =W57 -> 0 | AB57: =O57 -> 0 | AF57: =AB57-AD57 -> 0 | AM57: =SUM(AG57:AL57) -> 0 | AN57: =AF57-AM57 -> 0
A58: 53 | B58: BENEDICTO COLLEGE INC | D58: Customer | F58: =+'29'!F58+'30'!F58+'31'!F58 -> 0 | G58: =+'29'!G58+'30'!G58+'31'!G58 -> 0 | H58: =+'29'!H58+'30'!H58+'31'!H58 -> 0 | J58: =+'29'!J58+'30'!J58+'31'!J58 -> 0 | K58: =+'29'!K58+'30'!K58+'31'!K58 -> 0 | L58: =+'29'!L58+'30'!L58+'31'!L58 -> 0 | N58: =+'29'!N58+'30'!N58+'31'!N58 -> 0 | O58: =+'29'!O58+'30'!O58+'31'!O58 -> 0 | P58: =+'29'!P58+'30'!P58+'31'!P58 -> 0 | R58: 0 | S58: 0 | T58: 0 | V58: =N58-R58 -> 0 | W58: =O58-S58 -> 0 | Y58: =V58 -> 0 | Z58: =W58 -> 0 | AB58: =O58 -> 0 | AF58: =AB58-AD58 -> 0 | AM58: =SUM(AG58:AL58) -> 0 | AN58: =AF58-AM58 -> 0
A59: 54 | B59: BICOL JL AGRI CORP | C59: METROBANK | D59: Partner | F59: =+'29'!F59+'30'!F59+'31'!F59 -> 3 | G59: =+'29'!G59+'30'!G59+'31'!G59 -> 119314 | H59: =+'29'!H59+'30'!H59+'31'!H59 -> 150 | J59: =+'29'!J59+'30'!J59+'31'!J59 -> 0 | K59: =+'29'!K59+'30'!K59+'31'!K59 -> 0 | L59: =+'29'!L59+'30'!L59+'31'!L59 -> 0 | N59: =+'29'!N59+'30'!N59+'31'!N59 -> 3 | O59: =+'29'!O59+'30'!O59+'31'!O59 -> 119314 | P59: =+'29'!P59+'30'!P59+'31'!P59 -> 150 | R59: 3 | S59: 119164 | T59: 150 | V59: =N59-R59 -> 0 | W59: =O59-S59 -> 150 | Y59: =V59 -> 0 | Z59: =W59 -> 150 | AB59: =O59 -> 119314 | AF59: =AB59-AD59 -> 119314 | AM59: =SUM(AG59:AL59) -> 0 | AN59: =AF59-AM59 -> 119314
A60: 55 | B60: BILIRAN TELE TV NETWORK CORP | C60: AUB | D60: partner daily | F60: =+'29'!F60+'30'!F60+'31'!F60 -> 7 | G60: =+'29'!G60+'30'!G60+'31'!G60 -> 27804 | H60: =+'29'!H60+'30'!H60+'31'!H60 -> 140 | J60: =+'29'!J60+'30'!J60+'31'!J60 -> 0 | K60: =+'29'!K60+'30'!K60+'31'!K60 -> 0 | L60: =+'29'!L60+'30'!L60+'31'!L60 -> 0 | N60: =+'29'!N60+'30'!N60+'31'!N60 -> 7 | O60: =+'29'!O60+'30'!O60+'31'!O60 -> 27804 | P60: =+'29'!P60+'30'!P60+'31'!P60 -> 140 | R60: 7 | S60: 27664 | T60: 140 | V60: =N60-R60 -> 0 | W60: =O60-S60 -> 140 | Y60: =V60 -> 0 | Z60: =W60 -> 140 | AB60: =O60 -> 27804 | AF60: =AB60-AD60 -> 27804 | AM60: =SUM(AG60:AL60) -> 0 | AN60: =AF60-AM60 -> 27804
A61: 56 | B61: BIYAHEKO.COM CORPORATION | C61: BPI | D61: Customer | F61: =+'29'!F61+'30'!F61+'31'!F61 -> 4 | G61: =+'29'!G61+'30'!G61+'31'!G61 -> 78950 | H61: =+'29'!H61+'30'!H61+'31'!H61 -> 200 | J61: =+'29'!J61+'30'!J61+'31'!J61 -> 0 | K61: =+'29'!K61+'30'!K61+'31'!K61 -> 0 | L61: =+'29'!L61+'30'!L61+'31'!L61 -> 0 | N61: =+'29'!N61+'30'!N61+'31'!N61 -> 4 | O61: =+'29'!O61+'30'!O61+'31'!O61 -> 78950 | P61: =+'29'!P61+'30'!P61+'31'!P61 -> 200 | R61: 4 | S61: 78950 | T61: 0 | V61: =N61-R61 -> 0 | W61: =O61-S61 -> 0 | Y61: =V61 -> 0 | Z61: =W61 -> 0 | AB61: =O61 -> 78950 | AF61: =AB61-AD61 -> 78950 | AH61: 20000 | AM61: =SUM(AG61:AL61) -> 20000 | AN61: =AF61-AM61 -> 58950
A62: 57 | B62: BNSC/BOHOL NORTHERN STAR COLLEGE | D62: Customer | F62: =+'29'!F62+'30'!F62+'31'!F62 -> 0 | G62: =+'29'!G62+'30'!G62+'31'!G62 -> 0 | H62: =+'29'!H62+'30'!H62+'31'!H62 -> 0 | J62: =+'29'!J62+'30'!J62+'31'!J62 -> 0 | K62: =+'29'!K62+'30'!K62+'31'!K62 -> 0 | L62: =+'29'!L62+'30'!L62+'31'!L62 -> 0 | N62: =+'29'!N62+'30'!N62+'31'!N62 -> 0 | O62: =+'29'!O62+'30'!O62+'31'!O62 -> 0 | P62: =+'29'!P62+'30'!P62+'31'!P62 -> 0 | R62: 0 | S62: 0 | T62: 0 | V62: =N62-R62 -> 0 | W62: =O62-S62 -> 0 | Y62: =V62 -> 0 | Z62: =W62 -> 0 | AB62: =O62 -> 0 | AF62: =AB62-AD62 -> 0 | AM62: =SUM(AG62:AL62) -> 0 | AN62: =AF62-AM62 -> 0
A63: 58 | B63: BOARDWALK BUSINESS VENTURES | C63: SECURITY | D63: Customer | F63: =+'29'!F63+'30'!F63+'31'!F63 -> 0 | G63: =+'29'!G63+'30'!G63+'31'!G63 -> 0 | H63: =+'29'!H63+'30'!H63+'31'!H63 -> 0 | J63: =+'29'!J63+'30'!J63+'31'!J63 -> 0 | K63: =+'29'!K63+'30'!K63+'31'!K63 -> 0 | L63: =+'29'!L63+'30'!L63+'31'!L63 -> 0 | N63: =+'29'!N63+'30'!N63+'31'!N63 -> 0 | O63: =+'29'!O63+'30'!O63+'31'!O63 -> 0 | P63: =+'29'!P63+'30'!P63+'31'!P63 -> 0 | R63: 0 | S63: 0 | T63: 0 | V63: =N63-R63 -> 0 | W63: =O63-S63 -> 0 | Y63: =V63 -> 0 | Z63: =W63 -> 0 | AB63: =O63 -> 0 | AF63: =AB63-AD63 -> 0 | AM63: =SUM(AG63:AL63) -> 0 | AN63: =AF63-AM63 -> 0
A64: 59 | B64: BOHECO 1 | C64: SECURITY BANK | D64: Customer | F64: =+'29'!F64+'30'!F64+'31'!F64 -> 188 | G64: =+'29'!G64+'30'!G64+'31'!G64 -> 353763.62 | H64: =+'29'!H64+'30'!H64+'31'!H64 -> 1880 | J64: =+'29'!J64+'30'!J64+'31'!J64 -> 0 | K64: =+'29'!K64+'30'!K64+'31'!K64 -> 0 | L64: =+'29'!L64+'30'!L64+'31'!L64 -> 0 | N64: =+'29'!N64+'30'!N64+'31'!N64 -> 188 | O64: =+'29'!O64+'30'!O64+'31'!O64 -> 353763.62 | P64: =+'29'!P64+'30'!P64+'31'!P64 -> 1880 | R64: 188 | S64: 353763.62 | T64: 0 | V64: =N64-R64 -> 0 | W64: =O64-S64 -> 0 | Y64: =V64 -> 0 | Z64: =W64 -> 0 | AB64: =O64 -> 353763.62 | AF64: =AB64-AD64 -> 353763.62 | AM64: =SUM(AG64:AL64) -> 0 | AN64: =AF64-AM64 -> 353763.62
A65: 60 | B65: BOHECO 2 | C65: METROBANK | D65: Customer | F65: =+'29'!F65+'30'!F65+'31'!F65 -> 45 | G65: =+'29'!G65+'30'!G65+'31'!G65 -> 52851.03 | H65: =+'29'!H65+'30'!H65+'31'!H65 -> 225 | J65: =+'29'!J65+'30'!J65+'31'!J65 -> 0 | K65: =+'29'!K65+'30'!K65+'31'!K65 -> 0 | L65: =+'29'!L65+'30'!L65+'31'!L65 -> 0 | N65: =+'29'!N65+'30'!N65+'31'!N65 -> 45 | O65: =+'29'!O65+'30'!O65+'31'!O65 -> 52851.03 | P65: =+'29'!P65+'30'!P65+'31'!P65 -> 225 | R65: 45 | S65: 52851.03 | T65: 0 | V65: =N65-R65 -> 0 | W65: =O65-S65 -> 0 | Y65: =V65 -> 0 | Z65: =W65 -> 0 | AB65: =O65 -> 52851.03 | AF65: =AB65-AD65 -> 52851.03 | AM65: =SUM(AG65:AL65) -> 0 | AN65: =AF65-AM65 -> 52851.03
A66: 61 | B66: BOHOL LIGHTS INC | C66: SECURITY BANK | D66: Customer | F66: =+'29'!F66+'30'!F66+'31'!F66 -> 584 | G66: =+'29'!G66+'30'!G66+'31'!G66 -> 1950951.4 | H66: =+'29'!H66+'30'!H66+'31'!H66 -> 5840 | J66: =+'29'!J66+'30'!J66+'31'!J66 -> -2 | K66: =+'29'!K66+'30'!K66+'31'!K66 -> -7037.27 | L66: =+'29'!L66+'30'!L66+'31'!L66 -> -20 | N66: =+'29'!N66+'30'!N66+'31'!N66 -> 582 | O66: =+'29'!O66+'30'!O66+'31'!O66 -> 1943914.1 | P66: =+'29'!P66+'30'!P66+'31'!P66 -> 5820 | R66: 582 | S66: 1943914.1 | T66: 0 | V66: =N66-R66 -> 0 | W66: =O66-S66 -> 0 | Y66: =V66 -> 0 | Z66: =W66 -> 0 | AB66: =O66 -> 1943914.1 | AF66: =AB66-AD66 -> 1943914.1 | AM66: =SUM(AG66:AL66) -> 0 | AN66: =AF66-AM66 -> 1943914.1
A67: 62 | B67: BOHOL NORTHERNEASTERN EDUCATION FOUNDATION INC. | D67: Customer | F67: =+'29'!F67+'30'!F67+'31'!F67 -> 0 | G67: =+'29'!G67+'30'!G67+'31'!G67 -> 0 | H67: =+'29'!H67+'30'!H67+'31'!H67 -> 0 | J67: =+'29'!J67+'30'!J67+'31'!J67 -> 0 | K67: =+'29'!K67+'30'!K67+'31'!K67 -> 0 | L67: =+'29'!L67+'30'!L67+'31'!L67 -> 0 | N67: =+'29'!N67+'30'!N67+'31'!N67 -> 0 | O67: =+'29'!O67+'30'!O67+'31'!O67 -> 0 | P67: =+'29'!P67+'30'!P67+'31'!P67 -> 0 | R67: 0 | S67: 0 | T67: 0 | V67: =N67-R67 -> 0 | W67: =O67-S67 -> 0 | Y67: =V67 -> 0 | Z67: =W67 -> 0 | AB67: =O67 -> 0 | AF67: =AB67-AD67 -> 0 | AM67: =SUM(AG67:AL67) -> 0 | AN67: =AF67-AM67 -> 0
A68: 63 | B68: BOHOL WATER UTILITIES INC. | C68: SECURITY BANK | D68: Customer | F68: =+'29'!F68+'30'!F68+'31'!F68 -> 141 | G68: =+'29'!G68+'30'!G68+'31'!G68 -> 99338.45 | H68: =+'29'!H68+'30'!H68+'31'!H68 -> 1410 | J68: =+'29'!J68+'30'!J68+'31'!J68 -> 0 | K68: =+'29'!K68+'30'!K68+'31'!K68 -> 0 | L68: =+'29'!L68+'30'!L68+'31'!L68 -> 0 | N68: =+'29'!N68+'30'!N68+'31'!N68 -> 141 | O68: =+'29'!O68+'30'!O68+'31'!O68 -> 99338.45 | P68: =+'29'!P68+'30'!P68+'31'!P68 -> 1410 | R68: 141 | S68: 99338.45 | T68: 0 | V68: =N68-R68 -> 0 | W68: =O68-S68 -> 0 | Y68: =V68 -> 0 | Z68: =W68 -> 0 | AB68: =O68 -> 99338.45 | AF68: =AB68-AD68 -> 99338.45 | AM68: =SUM(AG68:AL68) -> 0 | AN68: =AF68-AM68 -> 99338.45
A69: 64 | B69: BONJOUR TRAVEL AND TOURS | C69: bpi online | D69: Partner | F69: =+'29'!F69+'30'!F69+'31'!F69 -> 0 | G69: =+'29'!G69+'30'!G69+'31'!G69 -> 0 | H69: =+'29'!H69+'30'!H69+'31'!H69 -> 0 | J69: =+'29'!J69+'30'!J69+'31'!J69 -> 0 | K69: =+'29'!K69+'30'!K69+'31'!K69 -> 0 | L69: =+'29'!L69+'30'!L69+'31'!L69 -> 0 | N69: =+'29'!N69+'30'!N69+'31'!N69 -> 0 | O69: =+'29'!O69+'30'!O69+'31'!O69 -> 0 | P69: =+'29'!P69+'30'!P69+'31'!P69 -> 0 | R69: 0 | S69: 0 | T69: 0 | V69: =N69-R69 -> 0 | W69: =O69-S69 -> 0 | Y69: =V69 -> 0 | Z69: =W69 -> 0 | AB69: =O69 -> 0 | AF69: =AB69-AD69 -> 0 | AM69: =SUM(AG69:AL69) -> 0 | AN69: =AF69-AM69 -> 0
A70: 65 | B70: BOSTON FINANCE INVESTMENT CORP. | C70: CHINABANK | D70: Customer | F70: =+'29'!F70+'30'!F70+'31'!F70 -> 1 | G70: =+'29'!G70+'30'!G70+'31'!G70 -> 1000 | H70: =+'29'!H70+'30'!H70+'31'!H70 -> 25 | J70: =+'29'!J70+'30'!J70+'31'!J70 -> 0 | K70: =+'29'!K70+'30'!K70+'31'!K70 -> 0 | L70: =+'29'!L70+'30'!L70+'31'!L70 -> 0 | N70: =+'29'!N70+'30'!N70+'31'!N70 -> 1 | O70: =+'29'!O70+'30'!O70+'31'!O70 -> 1000 | P70: =+'29'!P70+'30'!P70+'31'!P70 -> 25 | R70: 1 | S70: 1000 | T70: 0 | V70: =N70-R70 -> 0 | W70: =O70-S70 -> 0 | Y70: =V70 -> 0 | Z70: =W70 -> 0 | AB70: =O70 -> 1000 | AF70: =AB70-AD70 -> 1000 | AM70: =SUM(AG70:AL70) -> 0 | AN70: =AF70-AM70 -> 1000
A71: 66 | B71: BOTICARD | C71: BPI | D71: Partner | F71: =+'29'!F71+'30'!F71+'31'!F71 -> 6 | G71: =+'29'!G71+'30'!G71+'31'!G71 -> 59585 | H71: =+'29'!H71+'30'!H71+'31'!H71 -> 180 | J71: =+'29'!J71+'30'!J71+'31'!J71 -> 0 | K71: =+'29'!K71+'30'!K71+'31'!K71 -> 0 | L71: =+'29'!L71+'30'!L71+'31'!L71 -> 0 | N71: =+'29'!N71+'30'!N71+'31'!N71 -> 6 | O71: =+'29'!O71+'30'!O71+'31'!O71 -> 59585 | P71: =+'29'!P71+'30'!P71+'31'!P71 -> 180 | R71: 6 | S71: 59405 | T71: 180 | V71: =N71-R71 -> 0 | W71: =O71-S71 -> 180 | Y71: =V71 -> 0 | Z71: =W71 -> 180 | AB71: =O71 -> 59585 | AF71: =AB71-AD71 -> 59585 | AM71: =SUM(AG71:AL71) -> 0 | AN71: =AF71-AM71 -> 59585
A72: 67 | B72: BOUNTY PLUS - LUZON (PROVINCIAL FRESH LUZON) | C72: BPI CHECK | D72: PARTNER DAILY | F72: =+'29'!F72+'30'!F72+'31'!F72 -> 0 | G72: =+'29'!G72+'30'!G72+'31'!G72 -> 0 | H72: =+'29'!H72+'30'!H72+'31'!H72 -> 0 | J72: =+'29'!J72+'30'!J72+'31'!J72 -> 0 | K72: =+'29'!K72+'30'!K72+'31'!K72 -> 0 | L72: =+'29'!L72+'30'!L72+'31'!L72 -> 0 | N72: =+'29'!N72+'30'!N72+'31'!N72 -> 0 | O72: =+'29'!O72+'30'!O72+'31'!O72 -> 0 | P72: =+'29'!P72+'30'!P72+'31'!P72 -> 0 | R72: 0 | S72: 0 | T72: 0 | V72: =N72-R72 -> 0 | W72: =O72-S72 -> 0 | Y72: =V72 -> 0 | Z72: =W72 -> 0 | AB72: =O72 -> 0 | AF72: =AB72-AD72 -> 0 | AM72: =SUM(AG72:AL72) -> 0 | AN72: =AF72-AM72 -> 0
A73: 68 | B73: BOUNTY PLUS - MINDANAO (PROVINCIAL FRESH MINDANAO) | C73: SECURITY BANK | D73: Partner | F73: =+'29'!F73+'30'!F73+'31'!F73 -> 45 | G73: =+'29'!G73+'30'!G73+'31'!G73 -> 3104816.3 | H73: =+'29'!H73+'30'!H73+'31'!H73 -> 3440 | J73: =+'29'!J73+'30'!J73+'31'!J73 -> 0 | K73: =+'29'!K73+'30'!K73+'31'!K73 -> 0 | L73: =+'29'!L73+'30'!L73+'31'!L73 -> 0 | N73: =+'29'!N73+'30'!N73+'31'!N73 -> 45 | O73: =+'29'!O73+'30'!O73+'31'!O73 -> 3104816.3 | P73: =+'29'!P73+'30'!P73+'31'!P73 -> 3440 | R73: 2 | S73: 3101376.3 | T73: 3440 | V73: =N73-R73 -> 43 | W73: =O73-S73 -> 3440 | Y73: =V73 -> 43 | Z73: =W73 -> 3440 | AB73: =O73 -> 3104816.3 | AF73: =AB73-AD73 -> 3104816.3 | AM73: =SUM(AG73:AL73) -> 0 | AN73: =AF73-AM73 -> 3104816.3
A74: 69 | B74: BOUNTY PLUS - VISAYAS (PROVINCIAL FRESH VISAYAS) | C74: BDO CHECK | D74: Partner | F74: =+'29'!F74+'30'!F74+'31'!F74 -> 139 | G74: =+'29'!G74+'30'!G74+'31'!G74 -> 4864863.6 | H74: =+'29'!H74+'30'!H74+'31'!H74 -> 7280 | J74: =+'29'!J74+'30'!J74+'31'!J74 -> 0 | K74: =+'29'!K74+'30'!K74+'31'!K74 -> 0 | L74: =+'29'!L74+'30'!L74+'31'!L74 -> 0 | N74: =+'29'!N74+'30'!N74+'31'!N74 -> 139 | O74: =+'29'!O74+'30'!O74+'31'!O74 -> 4864863.6 | P74: =+'29'!P74+'30'!P74+'31'!P74 -> 7280 | R74: 3 | S74: 4857583.6 | T74: 7280 | V74: =N74-R74 -> 136 | W74: =O74-S74 -> 7280 | Y74: =V74 -> 136 | Z74: =W74 -> 7280 | AB74: =O74 -> 4864863.6 | AF74: =AB74-AD74 -> 4864863.6 | AM74: =SUM(AG74:AL74) -> 0 | AN74: =AF74-AM74 -> 4864863.6
A75: 70 | B75: BP WATERWORKS | C75: BDO | D75: Partner M. | F75: =+'29'!F75+'30'!F75+'31'!F75 -> 291 | G75: =+'29'!G75+'30'!G75+'31'!G75 -> 193692.23 | H75: =+'29'!H75+'30'!H75+'31'!H75 -> 2328 | J75: =+'29'!J75+'30'!J75+'31'!J75 -> 0 | K75: =+'29'!K75+'30'!K75+'31'!K75 -> 0 | L75: =+'29'!L75+'30'!L75+'31'!L75 -> 0 | N75: =+'29'!N75+'30'!N75+'31'!N75 -> 291 | O75: =+'29'!O75+'30'!O75+'31'!O75 -> 193692.23 | P75: =+'29'!P75+'30'!P75+'31'!P75 -> 2328 | R75: 291 | S75: 193692.23 | T75: 0 | V75: =N75-R75 -> 0 | W75: =O75-S75 -> 0 | Y75: =V75 -> 0 | Z75: =W75 -> 0 | AB75: =O75 -> 193692.23 | AF75: =AB75-AD75 -> 193692.23 | AM75: =SUM(AG75:AL75) -> 0 | AN75: =AF75-AM75 -> 193692.23
A76: 71 | B76: BREAD AND MORE INC. | C76: METROBANK | D76: Partner | F76: =+'29'!F76+'30'!F76+'31'!F76 -> 57 | G76: =+'29'!G76+'30'!G76+'31'!G76 -> 1602835.9 | H76: =+'29'!H76+'30'!H76+'31'!H76 -> 1710 | J76: =+'29'!J76+'30'!J76+'31'!J76 -> 0 | K76: =+'29'!K76+'30'!K76+'31'!K76 -> 0 | L76: =+'29'!L76+'30'!L76+'31'!L76 -> 0 | N76: =+'29'!N76+'30'!N76+'31'!N76 -> 57 | O76: =+'29'!O76+'30'!O76+'31'!O76 -> 1602835.9 | P76: =+'29'!P76+'30'!P76+'31'!P76 -> 1710 | R76: 57 | S76: 1601125.9 | T76: 1710 | V76: =N76-R76 -> 0 | W76: =O76-S76 -> 1710 | Y76: =V76 -> 0 | Z76: =W76 -> 1710 | AB76: =O76 -> 1602835.9 | AF76: =AB76-AD76 -> 1602835.9 | AM76: =SUM(AG76:AL76) -> 0 | AN76: =AF76-AM76 -> 1602835.9
A77: 72 | B77: BREAD AREA INC. | C77: METROBANK | D77: Partner | F77: =+'29'!F77+'30'!F77+'31'!F77 -> 0 | G77: =+'29'!G77+'30'!G77+'31'!G77 -> 0 | H77: =+'29'!H77+'30'!H77+'31'!H77 -> 0 | J77: =+'29'!J77+'30'!J77+'31'!J77 -> 0 | K77: =+'29'!K77+'30'!K77+'31'!K77 -> 0 | L77: =+'29'!L77+'30'!L77+'31'!L77 -> 0 | N77: =+'29'!N77+'30'!N77+'31'!N77 -> 0 | O77: =+'29'!O77+'30'!O77+'31'!O77 -> 0 | P77: =+'29'!P77+'30'!P77+'31'!P77 -> 0 | R77: 0 | S77: 0 | T77: 0 | V77: =N77-R77 -> 0 | W77: =O77-S77 -> 0 | Y77: =V77 -> 0 | Z77: =W77 -> 0 | AB77: =O77 -> 0 | AF77: =AB77-AD77 -> 0 | AM77: =SUM(AG77:AL77) -> 0 | AN77: =AF77-AM77 -> 0
A78: 73 | B78: BREAD BY PATTY CORPORATION | C78: CHINABANK | D78: Partner | F78: =+'29'!F78+'30'!F78+'31'!F78 -> 90 | G78: =+'29'!G78+'30'!G78+'31'!G78 -> 675734 | H78: =+'29'!H78+'30'!H78+'31'!H78 -> 2700 | J78: =+'29'!J78+'30'!J78+'31'!J78 -> 0 | K78: =+'29'!K78+'30'!K78+'31'!K78 -> 0 | L78: =+'29'!L78+'30'!L78+'31'!L78 -> 0 | N78: =+'29'!N78+'30'!N78+'31'!N78 -> 90 | O78: =+'29'!O78+'30'!O78+'31'!O78 -> 675734 | P78: =+'29'!P78+'30'!P78+'31'!P78 -> 2700 | R78: 90 | S78: 673034 | T78: 2700 | V78: =N78-R78 -> 0 | W78: =O78-S78 -> 2700 | Y78: =V78 -> 0 | Z78: =W78 -> 2700 | AB78: =O78 -> 675734 | AF78: =AB78-AD78 -> 675734 | AM78: =SUM(AG78:AL78) -> 0 | AN78: =AF78-AM78 -> 675734
A79: 74 | B79: BREADPOINT | C79: METROBANK | D79: Customer | F79: =+'29'!F79+'30'!F79+'31'!F79 -> 88 | G79: =+'29'!G79+'30'!G79+'31'!G79 -> 929417 | H79: =+'29'!H79+'30'!H79+'31'!H79 -> 3520 | J79: =+'29'!J79+'30'!J79+'31'!J79 -> 0 | K79: =+'29'!K79+'30'!K79+'31'!K79 -> 0 | L79: =+'29'!L79+'30'!L79+'31'!L79 -> 0 | N79: =+'29'!N79+'30'!N79+'31'!N79 -> 88 | O79: =+'29'!O79+'30'!O79+'31'!O79 -> 929417 | P79: =+'29'!P79+'30'!P79+'31'!P79 -> 3520 | R79: 88 | S79: 929417 | T79: 0 | V79: =N79-R79 -> 0 | W79: =O79-S79 -> 0 | Y79: =V79 -> 0 | Z79: =W79 -> 0 | AB79: =O79 -> 929417 | AF79: =AB79-AD79 -> 929417 | AM79: =SUM(AG79:AL79) -> 0 | AN79: =AF79-AM79 -> 929417
... A99: 94 | B99: CEBU DOCTORS UNIVERSITY | C99: BDO | D99: Customer | F99: =+'29'!F99+'30'!F99+'31'!F99 -> 1 | G99: =+'29'!G99+'30'!G99+'31'!G99 -> 1500 | H99: =+'29'!H99+'30'!H99+'31'!H99 -> 15 | J99: =+'29'!J99+'30'!J99+'31'!J99 -> 0 | K99: =+'29'!K99+'30'!K99+'31'!K99 -> 0 | L99: =+'29'!L99+'30'!L99+'31'!L99 -> 0 | N99: =+'29'!N99+'30'!N99+'31'!N99 -> 1 | O99: =+'29'!O99+'30'!O99+'31'!O99 -> 1500 | P99: =+'29'!P99+'30'!P99+'31'!P99 -> 15 | R99: 1 | S99: 1500 | T99: 0 | V99: =N99-R99 -> 0 | W99: =O99-S99 -> 0 | Y99: =V99 -> 0 | Z99: =W99 -> 0 | AB99: =O99 -> 1500 | AF99: =AB99-AD99 -> 1500 | AM99: =SUM(AG99:AL99) -> 0 | AN99: =AF99-AM99 -> 1500
A100: 95 | B100: CEBU GEMS INNOVATION AND CAREER DEVELOPMENT CENTER, INC. | C100: BPI | D100: Partner M. | F100: =+'29'!F100+'30'!F100+'31'!F100 -> 0 | G100: =+'29'!G100+'30'!G100+'31'!G100 -> 0 | H100: =+'29'!H100+'30'!H100+'31'!H100 -> 0 | J100: =+'29'!J100+'30'!J100+'31'!J100 -> 0 | K100: =+'29'!K100+'30'!K100+'31'!K100 -> 0 | L100: =+'29'!L100+'30'!L100+'31'!L100 -> 0 | N100: =+'29'!N100+'30'!N100+'31'!N100 -> 0 | O100: =+'29'!O100+'30'!O100+'31'!O100 -> 0 | P100: =+'29'!P100+'30'!P100+'31'!P100 -> 0 | R100: 0 | S100: 0 | T100: 0 | V100: =N100-R100 -> 0 | W100: =O100-S100 -> 0 | Y100: =V100 -> 0 | Z100: =W100 -> 0 | AB100: =O100 -> 0 | AF100: =AB100-AD100 -> 0 | AG100: 98.214286 | AM100: =SUM(AG100:AL100) -> 98.214286 | AN100: =AF100-AM100 -> -98.214286
A101: 96 | B101: CEBU III ELECTRIC COOP, INC. (CEBECO III) | C101: pnb | D101: Customer | F101: =+'29'!F101+'30'!F101+'31'!F101 -> 25 | G101: =+'29'!G101+'30'!G101+'31'!G101 -> 25703.53 | H101: =+'29'!H101+'30'!H101+'31'!H101 -> 250 | J101: =+'29'!J101+'30'!J101+'31'!J101 -> 0 | K101: =+'29'!K101+'30'!K101+'31'!K101 -> 0 | L101: =+'29'!L101+'30'!L101+'31'!L101 -> 0 | N101: =+'29'!N101+'30'!N101+'31'!N101 -> 25 | O101: =+'29'!O101+'30'!O101+'31'!O101 -> 25703.53 | P101: =+'29'!P101+'30'!P101+'31'!P101 -> 250 | R101: 25 | S101: 25703.53 | T101: 0 | V101: =N101-R101 -> 0 | W101: =O101-S101 -> 0 | Y101: =V101 -> 0 | Z101: =W101 -> 0 | AB101: =O101 -> 25703.53 | AF101: =AB101-AD101 -> 25703.53 | AM101: =SUM(AG101:AL101) -> 0 | AN101: =AF101-AM101 -> 25703.53
A102: 97 | B102: CEBU INSTITUTE OF TECHNOLOGY | C102: BPI | D102: Customer | F102: =+'29'!F102+'30'!F102+'31'!F102 -> 47 | G102: =+'29'!G102+'30'!G102+'31'!G102 -> 547306.53 | H102: =+'29'!H102+'30'!H102+'31'!H102 -> 1175 | J102: =+'29'!J102+'30'!J102+'31'!J102 -> 0 | K102: =+'29'!K102+'30'!K102+'31'!K102 -> 0 | L102: =+'29'!L102+'30'!L102+'31'!L102 -> 0 | N102: =+'29'!N102+'30'!N102+'31'!N102 -> 47 | O102: =+'29'!O102+'30'!O102+'31'!O102 -> 547306.53 | P102: =+'29'!P102+'30'!P102+'31'!P102 -> 1175 | R102: 47 | S102: 547306.53 | T102: 0 | V102: =N102-R102 -> 0 | W102: =O102-S102 -> 0 | Y102: =V102 -> 0 | Z102: =W102 -> 0 | AB102: =O102 -> 547306.53 | AF102: =AB102-AD102 -> 547306.53 | AM102: =SUM(AG102:AL102) -> 0 | AN102: =AF102-AM102 -> 547306.53
A103: 98 | B103: CEBU LANDMASTERS INC. | C103: BPI CHECK | D103: Customer | F103: =+'29'!F103+'30'!F103+'31'!F103 -> 3 | G103: =+'29'!G103+'30'!G103+'31'!G103 -> 21700 | H103: =+'29'!H103+'30'!H103+'31'!H103 -> 75 | J103: =+'29'!J103+'30'!J103+'31'!J103 -> 0 | K103: =+'29'!K103+'30'!K103+'31'!K103 -> 0 | L103: =+'29'!L103+'30'!L103+'31'!L103 -> 0 | N103: =+'29'!N103+'30'!N103+'31'!N103 -> 3 | O103: =+'29'!O103+'30'!O103+'31'!O103 -> 21700 | P103: =+'29'!P103+'30'!P103+'31'!P103 -> 75 | R103: 3 | S103: 21700 | T103: 0 | V103: =N103-R103 -> 0 | W103: =O103-S103 -> 0 | Y103: =V103 -> 0 | Z103: =W103 -> 0 | AB103: =O103 -> 21700 | AF103: =AB103-AD103 -> 21700 | AM103: =SUM(AG103:AL103) -> 0 | AN103: =AF103-AM103 -> 21700
A104: 99 | B104: CEBU OVEN MAGIC CORP. | C104: bpi online | D104: Partner | F104: =+'29'!F104+'30'!F104+'31'!F104 -> 203 | G104: =+'29'!G104+'30'!G104+'31'!G104 -> 2158500.5 | H104: =+'29'!H104+'30'!H104+'31'!H104 -> 6090 | J104: =+'29'!J104+'30'!J104+'31'!J104 -> 0 | K104: =+'29'!K104+'30'!K104+'31'!K104 -> 0 | L104: =+'29'!L104+'30'!L104+'31'!L104 -> 0 | N104: =+'29'!N104+'30'!N104+'31'!N104 -> 203 | O104: =+'29'!O104+'30'!O104+'31'!O104 -> 2158500.5 | P104: =+'29'!P104+'30'!P104+'31'!P104 -> 6090 | R104: 203 | S104: 2152410.5 | T104: 6090 | V104: =N104-R104 -> 0 | W104: =O104-S104 -> 6090 | Y104: =V104 -> 0 | Z104: =W104 -> 6090 | AB104: =O104 -> 2158500.5 | AF104: =AB104-AD104 -> 2158500.5 | AM104: =SUM(AG104:AL104) -> 0 | AN104: =AF104-AM104 -> 2158500.5
A105: 100 | B105: CEBU PEOPLE'S MULTI-PURPOSE COOPERATIVE | C105: BPI | D105: Customer | F105: =+'29'!F105+'30'!F105+'31'!F105 -> 0 | G105: =+'29'!G105+'30'!G105+'31'!G105 -> 0 | H105: =+'29'!H105+'30'!H105+'31'!H105 -> 0 | J105: =+'29'!J105+'30'!J105+'31'!J105 -> 0 | K105: =+'29'!K105+'30'!K105+'31'!K105 -> 0 | L105: =+'29'!L105+'30'!L105+'31'!L105 -> 0 | N105: =+'29'!N105+'30'!N105+'31'!N105 -> 0 | O105: =+'29'!O105+'30'!O105+'31'!O105 -> 0 | P105: =+'29'!P105+'30'!P105+'31'!P105 -> 0 | R105: 0 | S105: 0 | T105: 0 | V105: =N105-R105 -> 0 | W105: =O105-S105 -> 0 | Y105: =V105 -> 0 | Z105: =W105 -> 0 | AB105: =O105 -> 0 | AF105: =AB105-AD105 -> 0 | AM105: =SUM(AG105:AL105) -> 0 | AN105: =AF105-AM105 -> 0
A106: 101 | B106: CEBU SEVEN FIELDS REALTY INC | C106: METROBANK | D106: Customer | F106: =+'29'!F106+'30'!F106+'31'!F106 -> 0 | G106: =+'29'!G106+'30'!G106+'31'!G106 -> 0 | H106: =+'29'!H106+'30'!H106+'31'!H106 -> 0 | J106: =+'29'!J106+'30'!J106+'31'!J106 -> 0 | K106: =+'29'!K106+'30'!K106+'31'!K106 -> 0 | L106: =+'29'!L106+'30'!L106+'31'!L106 -> 0 | N106: =+'29'!N106+'30'!N106+'31'!N106 -> 0 | O106: =+'29'!O106+'30'!O106+'31'!O106 -> 0 | P106: =+'29'!P106+'30'!P106+'31'!P106 -> 0 | R106: 0 | S106: 0 | T106: 0 | V106: =N106-R106 -> 0 | W106: =O106-S106 -> 0 | Y106: =V106 -> 0 | Z106: =W106 -> 0 | AB106: =O106 -> 0 | AF106: =AB106-AD106 -> 0 | AM106: =SUM(AG106:AL106) -> 0 | AN106: =AF106-AM106 -> 0
A107: 102 | B107: CELESTIAL MEADOWS - CMDC1 | C107: PNB | D107: Customer | F107: =+'29'!F107+'30'!F107+'31'!F107 -> 9 | G107: =+'29'!G107+'30'!G107+'31'!G107 -> 272101.34 | H107: =+'29'!H107+'30'!H107+'31'!H107 -> 335 | J107: =+'29'!J107+'30'!J107+'31'!J107 -> 0 | K107: =+'29'!K107+'30'!K107+'31'!K107 -> 0 | L107: =+'29'!L107+'30'!L107+'31'!L107 -> 0 | N107: =+'29'!N107+'30'!N107+'31'!N107 -> 9 | O107: =+'29'!O107+'30'!O107+'31'!O107 -> 272101.34 | P107: =+'29'!P107+'30'!P107+'31'!P107 -> 335 | R107: 9 | S107: 272101.34 | T107: 0 | V107: =N107-R107 -> 0 | W107: =O107-S107 -> 0 | Y107: =V107 -> 0 | Z107: =W107 -> 0 | AB107: =O107 -> 272101.34 | AF107: =AB107-AD107 -> 272101.34 | AM107: =SUM(AG107:AL107) -> 0 | AN107: =AF107-AM107 -> 272101.34
A108: 103 | B108: CELESTIAL MEADOWS - CMDC3 | C108: pnb | D108: Customer | F108: =+'29'!F108+'30'!F108+'31'!F108 -> 6 | G108: =+'29'!G108+'30'!G108+'31'!G108 -> 149880.73 | H108: =+'29'!H108+'30'!H108+'31'!H108 -> 210 | J108: =+'29'!J108+'30'!J108+'31'!J108 -> 0 | K108: =+'29'!K108+'30'!K108+'31'!K108 -> 0 | L108: =+'29'!L108+'30'!L108+'31'!L108 -> 0 | N108: =+'29'!N108+'30'!N108+'31'!N108 -> 6 | O108: =+'29'!O108+'30'!O108+'31'!O108 -> 149880.73 | P108: =+'29'!P108+'30'!P108+'31'!P108 -> 210 | R108: 6 | S108: 149880.73 | T108: 0 | V108: =N108-R108 -> 0 | W108: =O108-S108 -> 0 | Y108: =V108 -> 0 | Z108: =W108 -> 0 | AB108: =O108 -> 149880.73 | AF108: =AB108-AD108 -> 149880.73 | AM108: =SUM(AG108:AL108) -> 0 | AN108: =AF108-AM108 -> 149880.73
A109: 104 | B109: CENTRO ESCOLAR UNIVERSITY-MAKATI | C109: BDO | D109: Customer | F109: =+'29'!F109+'30'!F109+'31'!F109 -> 6 | G109: =+'29'!G109+'30'!G109+'31'!G109 -> 101515 | H109: =+'29'!H109+'30'!H109+'31'!H109 -> 150 | J109: =+'29'!J109+'30'!J109+'31'!J109 -> 0 | K109: =+'29'!K109+'30'!K109+'31'!K109 -> 0 | L109: =+'29'!L109+'30'!L109+'31'!L109 -> 0 | N109: =+'29'!N109+'30'!N109+'31'!N109 -> 6 | O109: =+'29'!O109+'30'!O109+'31'!O109 -> 101515 | P109: =+'29'!P109+'30'!P109+'31'!P109 -> 150 | R109: 6 | S109: 101515 | T109: 0 | V109: =N109-R109 -> 0 | W109: =O109-S109 -> 0 | Y109: =V109 -> 0 | Z109: =W109 -> 0 | AB109: =O109 -> 101515 | AF109: =AB109-AD109 -> 101515 | AM109: =SUM(AG109:AL109) -> 0 | AN109: =AF109-AM109 -> 101515
A110: 105 | B110: CENTRO ESCOLAR UNIVERSITY-MALOLOS | C110: BDO | D110: Customer | F110: =+'29'!F110+'30'!F110+'31'!F110 -> 0 | G110: =+'29'!G110+'30'!G110+'31'!G110 -> 0 | H110: =+'29'!H110+'30'!H110+'31'!H110 -> 0 | J110: =+'29'!J110+'30'!J110+'31'!J110 -> 0 | K110: =+'29'!K110+'30'!K110+'31'!K110 -> 0 | L110: =+'29'!L110+'30'!L110+'31'!L110 -> 0 | N110: =+'29'!N110+'30'!N110+'31'!N110 -> 0 | O110: =+'29'!O110+'30'!O110+'31'!O110 -> 0 | P110: =+'29'!P110+'30'!P110+'31'!P110 -> 0 | R110: 0 | S110: 0 | T110: 0 | V110: =N110-R110 -> 0 | W110: =O110-S110 -> 0 | Y110: =V110 -> 0 | Z110: =W110 -> 0 | AB110: =O110 -> 0 | AF110: =AB110-AD110 -> 0 | AM110: =SUM(AG110:AL110) -> 0 | AN110: =AF110-AM110 -> 0
A111: 106 | B111: CENTRO ESCOLAR UNIVERSITY-MANILA | C111: BDO | D111: Customer | F111: =+'29'!F111+'30'!F111+'31'!F111 -> 22 | G111: =+'29'!G111+'30'!G111+'31'!G111 -> 322710 | H111: =+'29'!H111+'30'!H111+'31'!H111 -> 550 | J111: =+'29'!J111+'30'!J111+'31'!J111 -> 0 | K111: =+'29'!K111+'30'!K111+'31'!K111 -> 0 | L111: =+'29'!L111+'30'!L111+'31'!L111 -> 0 | N111: =+'29'!N111+'30'!N111+'31'!N111 -> 22 | O111: =+'29'!O111+'30'!O111+'31'!O111 -> 322710 | P111: =+'29'!P111+'30'!P111+'31'!P111 -> 550 | R111: 22 | S111: 322710 | T111: 0 | V111: =N111-R111 -> 0 | W111: =O111-S111 -> 0 | Y111: =V111 -> 0 | Z111: =W111 -> 0 | AB111: =O111 -> 322710 | AF111: =AB111-AD111 -> 322710 | AM111: =SUM(AG111:AL111) -> 0 | AN111: =AF111-AM111 -> 322710
A112: 107 | B112: CHARISSA'S FOOD ENTERPRISE | C112: eastwest | D112: Customer | F112: =+'29'!F112+'30'!F112+'31'!F112 -> 0 | G112: =+'29'!G112+'30'!G112+'31'!G112 -> 0 | H112: =+'29'!H112+'30'!H112+'31'!H112 -> 0 | J112: =+'29'!J112+'30'!J112+'31'!J112 -> 0 | K112: =+'29'!K112+'30'!K112+'31'!K112 -> 0 | L112: =+'29'!L112+'30'!L112+'31'!L112 -> 0 | N112: =+'29'!N112+'30'!N112+'31'!N112 -> 0 | O112: =+'29'!O112+'30'!O112+'31'!O112 -> 0 | P112: =+'29'!P112+'30'!P112+'31'!P112 -> 0 | R112: 0 | S112: 0 | T112: 0 | V112: =N112-R112 -> 0 | W112: =O112-S112 -> 0 | Y112: =V112 -> 0 | Z112: =W112 -> 0 | AB112: =O112 -> 0 | AF112: =AB112-AD112 -> 0 | AM112: =SUM(AG112:AL112) -> 0 | AN112: =AF112-AM112 -> 0
A113: 108 | B113: CHARLES CATV SYSTEMS, INC. | D113: Customer | F113: =+'29'!F113+'30'!F113+'31'!F113 -> 0 | G113: =+'29'!G113+'30'!G113+'31'!G113 -> 0 | H113: =+'29'!H113+'30'!H113+'31'!H113 -> 0 | J113: =+'29'!J113+'30'!J113+'31'!J113 -> 0 | K113: =+'29'!K113+'30'!K113+'31'!K113 -> 0 | L113: =+'29'!L113+'30'!L113+'31'!L113 -> 0 | N113: =+'29'!N113+'30'!N113+'31'!N113 -> 0 | O113: =+'29'!O113+'30'!O113+'31'!O113 -> 0 | P113: =+'29'!P113+'30'!P113+'31'!P113 -> 0 | R113: 0 | S113: 0 | T113: 0 | V113: =N113-R113 -> 0 | W113: =O113-S113 -> 0 | Y113: =V113 -> 0 | Z113: =W113 -> 0 | AB113: =O113 -> 0 | AF113: =AB113-AD113 -> 0 | AM113: =SUM(AG113:AL113) -> 0 | AN113: =AF113-AM113 -> 0
A114: 109 | B114: CHARLES PEAK | C114: BPI | D114: Customer | F114: =+'29'!F114+'30'!F114+'31'!F114 -> 10 | G114: =+'29'!G114+'30'!G114+'31'!G114 -> 6106 | H114: =+'29'!H114+'30'!H114+'31'!H114 -> 100 | J114: =+'29'!J114+'30'!J114+'31'!J114 -> 0 | K114: =+'29'!K114+'30'!K114+'31'!K114 -> 0 | L114: =+'29'!L114+'30'!L114+'31'!L114 -> 0 | N114: =+'29'!N114+'30'!N114+'31'!N114 -> 10 | O114: =+'29'!O114+'30'!O114+'31'!O114 -> 6106 | P114: =+'29'!P114+'30'!P114+'31'!P114 -> 100 | R114: 10 | S114: 6106 | T114: 0 | V114: =N114-R114 -> 0 | W114: =O114-S114 -> 0 | Y114: =V114 -> 0 | Z114: =W114 -> 0 | AB114: =O114 -> 6106 | AF114: =AB114-AD114 -> 6106 | AM114: =SUM(AG114:AL114) -> 0 | AN114: =AF114-AM114 -> 6106
A115: 110 | B115: CHICKEN ESSENTIALS, INC | C115: SECURITY BANK | D115: Partner | F115: =+'29'!F115+'30'!F115+'31'!F115 -> 0 | G115: =+'29'!G115+'30'!G115+'31'!G115 -> 0 | H115: =+'29'!H115+'30'!H115+'31'!H115 -> 0 | J115: =+'29'!J115+'30'!J115+'31'!J115 -> 0 | K115: =+'29'!K115+'30'!K115+'31'!K115 -> 0 | L115: =+'29'!L115+'30'!L115+'31'!L115 -> 0 | N115: =+'29'!N115+'30'!N115+'31'!N115 -> 0 | O115: =+'29'!O115+'30'!O115+'31'!O115 -> 0 | P115: =+'29'!P115+'30'!P115+'31'!P115 -> 0 | R115: 0 | S115: 0 | T115: 0 | V115: =N115-R115 -> 0 | W115: =O115-S115 -> 0 | Y115: =V115 -> 0 | Z115: =W115 -> 0 | AB115: =O115 -> 0 | AF115: =AB115-AD115 -> 0 | AM115: =SUM(AG115:AL115) -> 0 | AN115: =AF115-AM115 -> 0
A116: 111 | B116: CHICKY OINK | C116: CHINABANK | D116: Partner | F116: =+'29'!F116+'30'!F116+'31'!F116 -> 189 | G116: =+'29'!G116+'30'!G116+'31'!G116 -> 4752450 | H116: =+'29'!H116+'30'!H116+'31'!H116 -> 7175 | J116: =+'29'!J116+'30'!J116+'31'!J116 -> 0 | K116: =+'29'!K116+'30'!K116+'31'!K116 -> 0 | L116: =+'29'!L116+'30'!L116+'31'!L116 -> 0 | N116: =+'29'!N116+'30'!N116+'31'!N116 -> 189 | O116: =+'29'!O116+'30'!O116+'31'!O116 -> 4752450 | P116: =+'29'!P116+'30'!P116+'31'!P116 -> 7175 | R116: 189 | S116: 4745275 | T116: 7175 | V116: =N116-R116 -> 0 | W116: =O116-S116 -> 7175 | Y116: =V116 -> 0 | Z116: =W116 -> 7175 | AB116: =O116 -> 4752450 | AF116: =AB116-AD116 -> 4752450 | AM116: =SUM(AG116:AL116) -> 0 | AN116: =AF116-AM116 -> 4752450
A117: 112 | B117: CHOOKS TO GO | C117: BDO | D117: Partner | F117: =+'29'!F117+'30'!F117+'31'!F117 -> 0 | G117: =+'29'!G117+'30'!G117+'31'!G117 -> 0 | H117: =+'29'!H117+'30'!H117+'31'!H117 -> 0 | J117: =+'29'!J117+'30'!J117+'31'!J117 -> 0 | K117: =+'29'!K117+'30'!K117+'31'!K117 -> 0 | L117: =+'29'!L117+'30'!L117+'31'!L117 -> 0 | N117: =+'29'!N117+'30'!N117+'31'!N117 -> 0 | O117: =+'29'!O117+'30'!O117+'31'!O117 -> 0 | P117: =+'29'!P117+'30'!P117+'31'!P117 -> 0 | R117: 0 | S117: 0 | T117: 0 | V117: =N117-R117 -> 0 | W117: =O117-S117 -> 0 | Y117: =V117 -> 0 | Z117: =W117 -> 0 | AB117: =O117 -> 0 | AF117: =AB117-AD117 -> 0 | AM117: =SUM(AG117:AL117) -> 0 | AN117: =AF117-AM117 -> 0
A118: 113 | B118: CHOOKS TO GO PILIPINAS | C118: CHINABANK | D118: partner daily | F118: =+'29'!F118+'30'!F118+'31'!F118 -> 907 | G118: =+'29'!G118+'30'!G118+'31'!G118 -> 18916380 | H118: =+'29'!H118+'30'!H118+'31'!H118 -> 37400 | J118: =+'29'!J118+'30'!J118+'31'!J118 -> 0 | K118: =+'29'!K118+'30'!K118+'31'!K118 -> 0 | L118: =+'29'!L118+'30'!L118+'31'!L118 -> 0 | N118: =+'29'!N118+'30'!N118+'31'!N118 -> 907 | O118: =+'29'!O118+'30'!O118+'31'!O118 -> 18916380 | P118: =+'29'!P118+'30'!P118+'31'!P118 -> 37400 | R118: 907 | S118: 18878980 | T118: 37400 | V118: =N118-R118 -> 0 | W118: =O118-S118 -> 37400 | Y118: =V118 -> 0 | Z118: =W118 -> 37400 | AB118: =O118 -> 18916380 | AF118: =AB118-AD118 -> 18916380 | AM118: =SUM(AG118:AL118) -> 0 | AN118: =AF118-AM118 -> 18916380
A119: 114 | B119: CIS BAYAD CENTER INC. | C119: BDO | D119: Partner M. | F119: =+'29'!F119+'30'!F119+'31'!F119 -> 6807 | G119: =+'29'!G119+'30'!G119+'31'!G119 -> 13590549 | H119: =+'29'!H119+'30'!H119+'31'!H119 -> 38267.5 | J119: =+'29'!J119+'30'!J119+'31'!J119 -> 0 | K119: =+'29'!K119+'30'!K119+'31'!K119 -> 0 | L119: =+'29'!L119+'30'!L119+'31'!L119 -> 0 | N119: =+'29'!N119+'30'!N119+'31'!N119 -> 6807 | O119: =+'29'!O119+'30'!O119+'31'!O119 -> 13590549 | P119: =+'29'!P119+'30'!P119+'31'!P119 -> 38267.5 | R119: 6807 | S119: 13590549 | T119: 0 | V119: =N119-R119 -> 0 | W119: =O119-S119 -> 0 | Y119: =V119 -> 0 | Z119: =W119 -> 0 | AB119: =O119 -> 13590549 | AF119: =AB119-AD119 -> 13590549 | AG119: 2262863.6 | AJ119: 2000 | AM119: =SUM(AG119:AL119) -> 2264863.6 | AN119: =AF119-AM119 -> 11325685
A120: 115 | B120: CITY SAVINGS BANK | C120: UNION BANK | D120: Partner M. | F120: =+'29'!F120+'30'!F120+'31'!F120 -> 2134 | G120: =+'29'!G120+'30'!G120+'31'!G120 -> 11155739 | H120: =+'29'!H120+'30'!H120+'31'!H120 -> 106700 | J120: =+'29'!J120+'30'!J120+'31'!J120 -> 0 | K120: =+'29'!K120+'30'!K120+'31'!K120 -> 0 | L120: =+'29'!L120+'30'!L120+'31'!L120 -> 0 | N120: =+'29'!N120+'30'!N120+'31'!N120 -> 2134 | O120: =+'29'!O120+'30'!O120+'31'!O120 -> 11155739 | P120: =+'29'!P120+'30'!P120+'31'!P120 -> 106700 | R120: 2134 | S120: 11155739 | T120: 0 | V120: =N120-R120 -> 0 | W120: =O120-S120 -> 0 | Y120: =V120 -> 0 | Z120: =W120 -> 0 | AB120: =O120 -> 11155739 | AF120: =AB120-AD120 -> 11155739 | AG120: 2645843.8 | AI120: 12500 | AM120: =SUM(AG120:AL120) -> 2658343.8 | AN120: =AF120-AM120 -> 8497395.3
A121: 116 | B121: CLAVER TV AND INTERNET SERVICES | C121: METROBANK | D121: Customer | F121: =+'29'!F121+'30'!F121+'31'!F121 -> 6 | G121: =+'29'!G121+'30'!G121+'31'!G121 -> 7597 | H121: =+'29'!H121+'30'!H121+'31'!H121 -> 110 | J121: =+'29'!J121+'30'!J121+'31'!J121 -> 0 | K121: =+'29'!K121+'30'!K121+'31'!K121 -> 0 | L121: =+'29'!L121+'30'!L121+'31'!L121 -> 0 | N121: =+'29'!N121+'30'!N121+'31'!N121 -> 6 | O121: =+'29'!O121+'30'!O121+'31'!O121 -> 7597 | P121: =+'29'!P121+'30'!P121+'31'!P121 -> 110 | R121: 6 | S121: 7597 | T121: 0 | V121: =N121-R121 -> 0 | W121: =O121-S121 -> 0 | Y121: =V121 -> 0 | Z121: =W121 -> 0 | AB121: =O121 -> 7597 | AF121: =AB121-AD121 -> 7597 | AM121: =SUM(AG121:AL121) -> 0 | AN121: =AF121-AM121 -> 7597
A122: 117 | B122: COLEGIO DE DAGUPAN | D122: Customer | F122: =+'29'!F122+'30'!F122+'31'!F122 -> 0 | G122: =+'29'!G122+'30'!G122+'31'!G122 -> 0 | H122: =+'29'!H122+'30'!H122+'31'!H122 -> 0 | J122: =+'29'!J122+'30'!J122+'31'!J122 -> 0 | K122: =+'29'!K122+'30'!K122+'31'!K122 -> 0 | L122: =+'29'!L122+'30'!L122+'31'!L122 -> 0 | N122: =+'29'!N122+'30'!N122+'31'!N122 -> 0 | O122: =+'29'!O122+'30'!O122+'31'!O122 -> 0 | P122: =+'29'!P122+'30'!P122+'31'!P122 -> 0 | R122: 0 | S122: 0 | T122: 0 | V122: =N122-R122 -> 0 | W122: =O122-S122 -> 0 | Y122: =V122 -> 0 | Z122: =W122 -> 0 | AB122: =O122 -> 0 | AF122: =AB122-AD122 -> 0 | AM122: =SUM(AG122:AL122) -> 0 | AN122: =AF122-AM122 -> 0
A123: 118 | B123: COLEGIO SAN AGUSTIN - BACOLOD | C123: BPI | D123: Customer | F123: =+'29'!F123+'30'!F123+'31'!F123 -> 42 | G123: =+'29'!G123+'30'!G123+'31'!G123 -> 719350.77 | H123: =+'29'!H123+'30'!H123+'31'!H123 -> 1260 | J123: =+'29'!J123+'30'!J123+'31'!J123 -> 0 | K123: =+'29'!K123+'30'!K123+'31'!K123 -> 0 | L123: =+'29'!L123+'30'!L123+'31'!L123 -> 0 | N123: =+'29'!N123+'30'!N123+'31'!N123 -> 42 | O123: =+'29'!O123+'30'!O123+'31'!O123 -> 719350.77 | P123: =+'29'!P123+'30'!P123+'31'!P123 -> 1260 | R123: 42 | S123: 719350.77 | T123: 0 | V123: =N123-R123 -> 0 | W123: =O123-S123 -> 0 | Y123: =V123 -> 0 | Z123: =W123 -> 0 | AB123: =O123 -> 719350.77 | AF123: =AB123-AD123 -> 719350.77 | AM123: =SUM(AG123:AL123) -> 0 | AN123: =AF123-AM123 -> 719350.77
A124: 119 | B124: COLLEGE OF TECHNOLOGICAL SCIENCES CEBU INC. | C124: METROBANK | D124: Customer | F124: =+'29'!F124+'30'!F124+'31'!F124 -> 0 | G124: =+'29'!G124+'30'!G124+'31'!G124 -> 0 | H124: =+'29'!H124+'30'!H124+'31'!H124 -> 0 | J124: =+'29'!J124+'30'!J124+'31'!J124 -> 0 | K124: =+'29'!K124+'30'!K124+'31'!K124 -> 0 | L124: =+'29'!L124+'30'!L124+'31'!L124 -> 0 | N124: =+'29'!N124+'30'!N124+'31'!N124 -> 0 | O124: =+'29'!O124+'30'!O124+'31'!O124 -> 0 | P124: =+'29'!P124+'30'!P124+'31'!P124 -> 0 | R124: 0 | S124: 0 | T124: 0 | V124: =N124-R124 -> 0 | W124: =O124-S124 -> 0 | Y124: =V124 -> 0 | Z124: =W124 -> 0 | AB124: =O124 -> 0 | AF124: =AB124-AD124 -> 0 | AM124: =SUM(AG124:AL124) -> 0 | AN124: =AF124-AM124 -> 0
...

Sheet PAID SC
A1: COLLECTION MONITORING
A2: As of August 31, 2025
B4: AUGUST 2025
B5: AMOUNT | C5: PAYMENT PERIOD
A6: SPICA DISTRIBUTION | B6: 0
A7: PLDT | B7: 0
A8: NORECO | B8: 0
A9: HAPPY WELL | B9: 0
A10: KALUNASAN | B10: 0
A11: RELEVANTTECH 5-DSP | B11: 25638.839 | C11: JULY 2025
A12: RELEVANTTECH 5-PROJECT | B12: 4964.7321 | C12: JULY 2025
A13: RELEVANTTECH 5-SUB DEALER | B13: 2254.0179 | C13: JULY 2025
A14: RELEVANTTECH 6-DSP | B14: 37468.75 | C14: JULY 2025
A15: RELEVANTTECH 6-PROJECT | B15: 5112.0536 | C15: JULY 2025
A16: RELEVANTTECH 6-SUB DEALER | B16: 3221.4286 | C16: JULY 2025
A17: PRIMUS VENTURES | B17: 0
A18: MANILA WATER VENTURE | B18: 474.48 | C18: AUGUST 2024 & FEBRUARY 2025
A19: PAL | B19: 4611.16 | C19: APRIL-JUNE 2025
A20: RYKOM | B20: 0
A21: WATER PHILS | B21: 2003.57 | C21: MAY-JUNE 2025
A22: CITY SAVINGS | B22: 0
A23: CEBU GEMS | B23: 0
A24: ASIALINK | B24: 207664.29 | C24: JUNE 2025
A25: FINASWIDE | B25: 0
A26: SUBIC ENERZONE | B26: 0
A27: DAVAO LIGHT | B27: 0
A28: VECO | B28: 0
A29: COTABATO LIGHT | B29: 0
A30: ANECO | B30: 1866.0714 | C30: JUNE 2025
A31: ANECO - COLLECTION | B31: 0
A32: GENTRADE | B32: 699305.36 | C32: JUNE-JULY 2025
A33: POWERCYCLE | B33: 156042.86 | C33: JUNE-JULY 2025
A34: UNISTAR-FINANCE | B34: 70596.43 | C34: JUNE-JULY 2025
A35: UNISTAR-CUSTOMER | B35: 486.16 | C35: JUNE-JULY 2025
A36: MILLENIUM | B36: 61708.036 | C36: JULY 2025
A37: MAKATI-CUSTOMER | B37: 810.27 | C37: MAY-JUNE 2025
A38: MAKATI-FINANCE | B38: 21852.68 | C38: MAY-JUNE 2025
A39: MICROVENTURES | B39: 0
A40: DRAGONPAY | B40: 1943275.7 | C40: June 16-July 31, 2025
A41: CIS BAYAD CENTER | B41: 0
A42: SECURITY BANK - LAZADA | B42: 8570100 | C42: NOVEMBER-APRIL 2025
A43: RAFI MICROFINANCE | B43: 101082.14 | C43: July 16-31, 2025
A44: RCBC-AMWSLAI | B44: 14.732143 | C44: July 16-31, 2025
A45: RCBC-BUFFALO FARM | B45: 1944.6429 | C45: July 16-31, 2025
A46: RCBC-BUFFALO IND 1 | B46: 3152.6786 | C46: July 16-31, 2025
A47: RCBC-BUFFALO IND 2 | B47: 117.85714 | C47: July 16-31, 2025
A48: RCBC-CITIBANK | B48: 0
A49: RCBC-COCOMART | B49: 13141.071 | C49: July 16-31, 2025
A50: RCBC-CONSUMER LOANS | B50: 1070.5357 | C50: July 16-31, 2025
A51: RCBC-EASTERN VISAYAS | B51: 98.214286 | C51: July 16-31, 2025
A52: RCBC-GLOBAL | B52: 2475 | C52: July 16-31, 2025
A53: RCBC-JPT OIL | B53: 3624.11 | C53: May 16-31, 2025 & 'July 16-31, 2025
A54: RCBC-LUZON | B54: 7866.9643 | C54: July 16-31, 2025
A55: RCBC-RAMAS | B55: 46671.429 | C55: July 16-31, 2025
A56: RCBC-MINDANAO | B56: 11991.964 | C56: July 16-31, 2025
A57: RCBC-PRIME | B57: 1237.5 | C57: July 16-31, 2025
A58: RCBC-RUSCO | B58: 21096.429 | C58: July 16-31, 2025
A59: RCBC-SAGA | B59: 10725 | C59: July 16-31, 2025
A60: RCBC-SOLID VIEW | B60: 0
A61: RCBC-DWIGHT STEEL | B61: 0
A62: LDS - ONLINE STORE | B62: 2322.77 | C62: June 22-Jul 5, 2024 & Jul 5-18, 2025
A63: LDS - PEF LOAN | B63: 6811.16 | C63: April 27-May 10, 2024, June 22-Jul 5, 2024 & Jul 5-18, 2025
A64: LDS - REMITTANCE | B64: 398263.84 | C64: June 22-Jul 5, 2024 & Jul 5-18, 2025
A65: LDS - SAR | B65: 142.41071 | C65: Jul 5-18, 2025
A66: CARD 2 | B66: 291401.79 | C66: Jul 14-Aug 17, 2025
A67: JTIP | B67: 1773084 | C67: Jul 14-Aug 3, 2025
A68: SERVIAMUS | B68: 0
A69: TOTAL: | B69: =SUM(B6:B68) -> 14517793

Sheet UNPAID SF
A1: BILLS PAYMENT SERVICE CHARGE RECEIVABLES
A2: As of August 31, 2025
D3: 45870 | E3: 45839 | F3: 45809 | G3: 45778 | H3: 45748 | I3: March 2025 & Previous
F4: AGING
A5: PARTNER | B5: AMOUNT | C5: REMARKS | D5: CURRENT | E5: 1-30 DAYS | F5: 31-60 DAYS | G5: 61-90 DAYS | H5: 90 DAYS | I5: OVER 90 DAYS
A6: SPICA | B6: =SUM(D6:I6) -> 10017.857 | D6: 2916.9643 | E6: 3908.9286 | F6: 3191.9643 | G6: 0 | H6: 0 | I6: 0
A7: NORECO | B7: =SUM(D7:I7) -> 110687.5 | D7: 13897.321 | E7: 14241.071 | F7: 13062.5 | G7: 12767.857 | H7: 12227.679 | I7: =29857.1428571429+14633.9285714286 -> 44491.071
A8: HAPPY WELL | B8: =SUM(D8:I8) -> 1178.5714 | D8: 495 | E8: 361.42857 | F8: 322.14286 | G8: 0 | H8: 0 | I8: 0
A9: KALUNASAN | B9: =SUM(D9:I9) -> 0 | D9: 0 | E9: 0 | F9: 0 | G9: 0 | H9: 0 | I9: 0
A10: RELEVANTTECH 5-DSP | B10: =SUM(D10:I10) -> 19917.857 | D10: 19917.857 | E10: 0 | F10: 0 | G10: 0 | H10: 0 | I10: 0
A11: RELEVANTTECH 5-PROJECT | B11: =SUM(D11:I11) -> 3378.5714 | D11: 3378.5714 | E11: 0 | F11: 0 | G11: 0 | H11: 0 | I11: 0
A12: RELEVANTTECH 5-SUB DEALER | B12: =SUM(D12:I12) -> 1738.3929 | D12: 1738.3929 | E12: 0 | F12: 0 | G12: 0 | H12: 0 | I12: 0
A13: RELEVANTTECH 6-DSP | B13: =SUM(D13:I13) -> 30657.589 | D13: 30657.589 | E13: 0 | F13: 0 | G13: 0 | H13: 0 | I13: 0
A14: RELEVANTTECH 6-PROJECT | B14: =SUM(D14:I14) -> 4144.6429 | D14: 4144.6429 | E14: 0 | F14: 0 | G14: 0 | H14: 0 | I14: 0
A15: RELEVANTTECH 6-SUB DEALER | B15: =SUM(D15:I15) -> 4566.9643 | D15: 4566.9643 | E15: 0 | F15: 0 | G15: 0 | H15: 0 | I15: 0
A16: PRIMUS VENTURES | B16: =SUM(D16:I16) -> 39737.5 | D16: 29336.607 | E16: 3211.6071 | F16: 5136.6071 | H16: 1021.4286 | I16: 1031.25
A17: MANILA WATER VENTURE | B17: =SUM(D17:I17) -> 137.5 | D17: 0 | E17: 0 | F17: 0 | G17: 0 | H17: 0 | I17: 137.5
A18: OBANDO WATER | B18: =SUM(D18:I18) -> 55 | D18: 0 | E18: 0 | F18: 0 | G18: 0 | H18: 0 | I18: 55
A19: LAGUNA WATER CORP | B19: =SUM(D19:I19) -> 2667.5 | D19: 2667.5 | E19: 0 | F19: 0 | G19: 0 | H19: 0 | I19: 0
A20: PAL | B20: =SUM(D20:I20) -> 2003.5714 | D20: 987.05357 | E20: 1016.5179 | F20: 0 | G20: 0 | H20: 0 | I20: 0
A21: RYKOM | B21: =SUM(D21:I21) -> 10675 | D21: 4950 | E21: 5725 | F21: 0 | G21: 0 | H21: 0 | I21: 0
A22: WATER PHILS | B22: =SUM(D22:I22) -> 2003.5714 | D22: 1031.25 | E22: 972.32143 | F22: 0 | G22: 0 | H22: 0 | I22: 0
A23: CITY SAVINGS | B23: =SUM(D23:I23) -> 2645843.8 | D23: 1313223.2 | E23: 1332620.5 | F23: 0 | G23: 0 | H23: 0 | I23: 0
A24: CEBU GEMS | B24: =SUM(D24:I24) -> 98.214286 | D24: 0 | E24: 0 | F24: 0 | G24: 0 | H24: 0 | I24: 98.214286
A25: ASIALINK | B25: =SUM(D25:I25) -> 637151.43 | D25: 208120 | E25: 211922.86 | F25: 0 | G25: 217108.57 | H25: 0 | I25: 0
A26: FINASWIDE | B26: =SUM(D26:I26) -> 1147.1429 | D26: 110 | E26: 235.71429 | F26: 251.42857 | G26: 0 | H26: 330 | I26: 220
A27: SUBIC ENERZONE | B27: =SUM(D27:I27) -> 68.6 | D27: 14.7 | E27: 14.7 | F27: 19.6 | G27: 19.6 | H27: 0 | I27: 0
A28: DAVAO LIGHT | B28: =SUM(D28:I28) -> 103974.55 | D28: 33770.982 | E28: 35853.125 | F28: 34350.446 | G28: 0 | H28: 0 | I28: 0
... A44: RAFI MICROFINANCE | B44: =SUM(D44:I44) -> 182953.57 | D44: 182953.57 | E44: 0 | F44: 0 | G44: 0 | H44: 0 | I44: 0
A45: RCBC- AMWSLAI | B45: =SUM(D45:I45) -> 358.48214 | D45: 358.48214 | E45: 0 | G45: 0 | H45: 0 | I45: 0
A46: RCBC-BUFFALO FARM | B46: =SUM(D46:I46) -> 3977.6786 | D46: 3977.6786 | E46: 0 | F46: 0 | G46: 0 | H46: 0 | I46: 0
A47: RCBC-BUFFALO IND 1 | B47: =SUM(D47:I47) -> 6806.25 | D47: 6806.25 | E47: 0 | F47: 0 | G47: 0 | H47: 0 | I47: 0
A48: RCBC-BUFFALO IND 2 | B48: =SUM(D48:I48) -> 58.928571 | D48: 58.928571 | E48: 0 | F48: 0 | G48: 0 | H48: 0 | I48: 0
A49: RCBC-CITIBANK | B49: =SUM(D49:I49) -> 68.75 | D49: 0 | E49: 0 | F49: 0 | G49: 0 | H49: 49.107143 | I49: 19.642857
A50: RCBC-CEBU SEA CHARTERERS | B50: =SUM(D50:I50) -> 3683.0343 | D50: 3653.57 | E50: 29.464286 | F50: 0 | G50: 0 | H50: 0 | I50: 0
A51: RCBC-CONSUMER LOANS | B51: =SUM(D51:I51) -> 1198.2143 | D51: 1198.2143 | E51: 0 | F51: 0 | G51: 0 | H51: 0 | I51: 0
A52: RCBC-COCOMART | B52: =SUM(D52:I52) -> 21891.964 | D52: 21891.964 | E52: 0 | F52: 0 | G52: 0 | H52: 0 | I52: 0
A53: RCBC-DWIGHT STEEL | B53: =SUM(D53:I53) -> 0 | D53: 0 | E53: 0 | F53: 0 | G53: 0 | H53: 0 | I53: 0
A54: RCBC-EASTERN VISAYAS | B54: =SUM(D54:I54) -> 142.41071 | D54: 142.41071 | E54: 0 | F54: 0 | G54: 0 | H54: 0 | I54: 0
A55: RCBC-GLOBAL | B55: =SUM(D55:I55) -> 4596.4286 | D55: 4596.4286 | E55: 0 | F55: 0 | G55: 0 | H55: 0 | I55: 0
A56: RCBC - JPT OIL CORPORATION | B56: =SUM(D56:I56) -> 5185.7143 | D56: 5185.7143 | E56: 0 | F56: 0 | G56: 0 | H56: 0 | I56: 0
A57: RCBC- LUZON | B57: =SUM(D57:I57) -> 15881.25 | D57: 15881.25 | E57: 0 | F57: 0 | G57: 0 | H57: 0 | I57: 0
A58: RCBC-RAMAS | B58: =SUM(D58:I58) -> 119124.11 | D58: 119124.11 | E58: 0 | F58: 0 | G58: 0 | H58: 0 | I58: 0
A59: RCBC-MINDANAO | B59: =SUM(D59:I59) -> 37714.283 | D59: 28344.64 | E59: 0 | F59: 0 | G59: 9369.6429
A60: RCBC-PRIME | B60: =SUM(D60:I60) -> 8191.0714 | D60: 8191.0714 | E60: 0 | F60: 0 | G60: 0 | H60: 0 | I60: 0
A61: RCBC-RUSCO | B61: =SUM(D61:I61) -> 42664.286 | D61: 42664.286 | E61: 0 | F61: 0 | G61: 0 | H61: 0 | I61: 0
A62: RCBC-SAGA | B62: =SUM(D62:I62) -> 35710.714 | D62: 35710.714 | E62: 0 | F62: 0 | G62: 0 | H62: 0 | I62: 0
A63: RCBC- SOLID VIEW | B63: =SUM(D63:I63) -> 559.82 | D63: 353.57 | E63: 206.25 | F63: 0 | G63: 0 | H63: 0 | I63: 0
A64: LDS - ONLINE STORE | B64: =SUM(D64:I64) -> 2931.7 | D64: 2312.95 | E64: 618.75 | F64: 0 | G64: 0 | H64: 0 | I64: 0
A65: LDS - PEF LOAN | B65: =SUM(D65:I65) -> 6064.7293 | D65: 3869.64 | E65: 2195.0893 | F65: 0 | G65: 0 | H65: 0 | I65: 0
A66: LDS - REMITTANCE | B66: =SUM(D66:I66) -> 558579.01 | D66: 378768.3 | E66: 179810.71 | F66: 0 | G66: 0 | H66: 0 | I66: 0
A67: LDS - SAR | B67: =SUM(D67:I67) -> 412.50143 | D67: 333.93 | E67: 78.571429 | F67: 0 | G67: 0 | H67: 0 | I67: 0
A68: CARD 2 | B68: =SUM(D68:I68) -> 87950.893 | D68: 87950.893 | E68: 0 | F68: 0 | G68: 0 | H68: 0 | I68: 0
A69: JTIP | B69: =SUM(D69:I69) -> 2496096 | D69: 2496096 | E69: 0 | F69: 0 | G69: 0 | H69: 0 | I69: 0
A70: SERVIAMUS | B70: =SUM(D70:I70) -> 13365 | D70: 2695 | E70: 4730 | F70: 3025 | G70: 0 | H70: 0 | I70: 2915
A71: TOTAL | B71: =SUM(B6:B70) -> 20245992 | D71: =SUM(D6:D70) -> 9588217.3 | E71: =SUM(E6:E70) -> 5486541.3 | F71: =SUM(F6:F70) -> 2292950 | G71: =SUM(G6:G70) -> 2328200.5 | H71: =SUM(H6:H70) -> 500408.23 | I71: =SUM(I6:I70) -> 49674.821

Sheet BPW UNDEDUCTED
A1: As of March 31, 2025
A2: As of April 30, 2025
A3: DATE OF TRANSACTION | B3: REFERENCE | C3: ACCOUNT NAME | D3: ACCOUNT NO. | E3: BP PARTNER | F3: TRXN | G3: AMOUNT | H3: AMOUNT FOR REFUND | J3: TOTAL PER BP | K3: REMARKS
A4: 43968.022 | B4: BPW00111749884005 | C4: ROEL SILVANO SAYSON | D4: 20040000384075 | E4: DRAGON PAY CORPORATION | F4: 1 | G4: 650 | H4: 650 | I4: 20 | K4: not allowed for reversal, successfully posted to their partner
A5: 43970.533 | B5: BPW00111914906605 | C5: TERESA CENIZA PALCIS | D5: 17040000015156 | E5: DRAGON PAY CORPORATION | F5: 1 | G5: 855 | H5: 855 | I5: 20 | K5: not allowed for reversal, successfully posted to their partner
A6: 43894.004 | B6: BPW00110447760203 | C6: KATHLEEN MAY RAMIREZ SALANO | D6: 19110000318514 | E6: DRAGON PAY CORPORATION | F6: 1 | G6: 1794 | H6: 1794 | I6: 20 | J6: =SUM(H4:H6) -> 3299 | K6: not allowed for reversal, successfully posted to their partner
A7: 2020-02-14 15:39:41 PM | B7: BPW00111496572802 | C7: MERASOL CAFE BAGALANON | D7: 18030000036261 | E7: GI PHILIPPINES CORP. | F7: 1 | G7: 5000 | H7: 5000 | K7: PARTNER NOT ALLOWED FOR MANUAL ADJUSTMENT
A8: 43970.414 | B8: BPW00111983957805 | C8: DANNIELYN GRACE LUNA PEREZ | D8: 18120000131450 | E8: GI PHILIPPINES CORP. | F8: 1 | G8: 5000 | H8: 5000 | I8: 50 | K8: PARTNER NOT ALLOWED FOR MANUAL ADJUSTMENT
A9: 2020-06-01 11:39:02 AM | B9: BPW00110155044906 | C9: PEREZ, DANNIELYN GRACE LUNA | D9: 18120000131450 | E9: GI PHILIPPINES CORP. | F9: 1 | G9: 10000 | H9: 10000 | I9: 50 | J9: =SUM(H7:H9) -> 20000 | K9: PARTNER NOT ALLOWED FOR MANUAL ADJUSTMENT
A10: 43972.333 | B10: BPW00112142559405 | C10: ADRIAN MOLIDOR PONTIPEDRA | D10: 17010000006196 | E10: LAZADA PH | F10: 1 | G10: 500 | H10: 500 | I10: 0 | J10: =SUM(H10) -> 500 | K10: not allowed for reversal, successfully posted to their partner
A11: 2020-06-26 21:02:18 PM | B11: BPW00112695252706 | C11: WAMILDA, EYEIN LYNN MERISAAR | D11: 19110000326037 | E11: SKYPAY API | F11: 1 | G11: 800 | H11: 800 | I11: 20 | J11: =SUM(H11) -> 800 | K11: Lending refused to cancel due to customer have reloan again
A13: SUMMARY:
A14: DRAGON PAY CORPORATION | B14: 3299
A15: BIYAHEKO.COM | B15: 20000
A16: LAZADA PH | B16: 500
A17: SKYPAY API | B17: 800
B18: =SUM(B14:B17) -> 24599

Sheet BPX UNDEDUCTED
A1: As of August 31, 2025
A2: BPX UNDEDUCTED
A4: DATE | B4: REFERENCE | C4: ACCOUNT NAME | D4: BP PARTNER | E4: AMOUNT | F4: TOTAL AMOUNT PER BP | G4: REASON | H4: REMARKS
A5: 2021-05-01 09:50:44 | B5: BPX00110162242105 | C5: LEVINIA COLEGA SEGUIN | D5: CITY SAVINGS BANK | E5: 12500 | F5: =E5 -> 12500 | G5: unposted and undeductec on agent wallet balance | H5: emailed 05/08/2021
A6: 2021-06-02 15:29:37 | B6: BPX00110220819606 | C6: NCDIMARUCUT2851 | D6: ILECO 3 | E6: 495.66 | G6: unposted and undeducted on agent wallet balance | H6: waiting for partner's approval
A7: 2021-06-02 16:00:14 | B7: BPX00110271350306 | C7: NCDIMARUCUT2851 | D7: ILECO 3 | E7: 233.72 | F7: =E7+E6 -> 729.38 | G7: unposted and undeducted on agent wallet balance | H7: waiting for partner's approval
A8: 2021-02-26 10:45:12 AM | B8: BPX00112625562102 | C8: danertagadan38 | D8: MY SUPER PAY | E8: 4560 | F8: =E8 -> 4560 | G8: unposted and undeducted on our monthly report (FOR ADJUSTMENT-NO TRXN OF SUPERPAY YET) | H8: still no transaction yet; for adjustment
A9: 2021-05-03 11:43:23 | B9: BPX00110369639605 | C9: ARGY GUMANGAN CAASI | D9: PANELCO 1 | E9: 34 | F9: =E9 -> 34 | G9: unposted and undeductec on agent wallet balance | H9: emailed partner for approval, last ff. 4/20/22
A10: 2020-10-20 11:03:35 AM | B10: BPX00112068500310 | C10: EPHRAINE NICOLE GO REDONA | D10: SKYPAY | E10: 8050 | G10: Lending not approved due to customer account already settled on their end, can't be adjust or cancel | H10: not allowed for reversal
A11: 2020-10-20 10:57:43 AM | B11: BPX00112073845610 | C11: EPHRAINE NICOLE GO REDONA | D11: SKYPAY | E11: 8050 | G11: Lending not approved due to customer account already settled on their end, can't be adjust or cancel | H11: not allowed for reversal
A12: 2020-10-21 10:46:04 AM | B12: BPX00112160978010 | C12: MARY GRACE LUMBANG LAREZA | D12: SKYPAY | E12: 3500 | G12: Lending not approved | H12: Lending not approved
A13: 2020-10-20 01:13:12 PM | B13: BPX00112020551910 | C13: RAISA HARMONY CHOMAPOY LALO | D13: SKYPAY | E13: 2125 | G13: Lending not approved | H13: Lending not approved
A14: 2021-01-03 10:28:03 AM | B14: BPX00110369653401 | C14: ASUGAO, BENJIE PEPITO | D14: SKYPAY | E14: 2200 | G14: posted on your web report but unposted and undeducted to our transaction history report | H14: not allowed for reversal
A15: 2021-01-11 09:55:00 AM | B15: BPX00111136906601 | C15: MENIANO, LORELIE REYES | D15: SKYPAY | E15: 2500 | G15: posted on your web report but unposted and undeducted to our transaction history report | H15: not allowed for reversal
A16: 2019-12-28 03:34:30 PM | B16: BPX00112831443712 | C16: ERIC SAWATI CATTE | D16: SKYPAY API | E16: 2000 | H16: Lending not approved
A17: 2019-12-28 03:36:31 PM | B17: BPX00112841790612 | C17: ERIC SAWATI CATTE | D17: SKYPAY API | E17: 2000 | H17: Lending not approved
A18: 2020-01-08 04:14:23 PM | B18: BPX00110812123701 | C18: CATHERINE DEMAOSA ENDOMA | D18: SKYPAY API | E18: 3000 | G18: With receipt but reference not match | H18: lending not approved
A19: 2020-01-07 02:07:25 PM | B19: BPX00110728689001 | C19: ERIC SAWATI CATTE | D19: SKYPAY API | E19: 280 | G19: With receipt but reference not match | H19: Lending not approved due to customer have repeat loan
A20: 2020-01-07 10:58:53 AM | B20: BPX00110731901801 | C20: ERIC SAWATI CATTE | D20: SKYPAY API | E20: 7980 | G20: With receipt but reference not match | H20: NOT APPROVED TO CANCEL due to customer account already settled in lending’s end
A21: 2020-01-07 04:47:10 PM | B21: BPX00110736885101 | C21: JOCELYN CIRUELA SAKAY | D21: SKYPAY API | E21: 2000 | H21: Lending not approved
A22: 2020-01-07 04:49:08 PM | B22: BPX00110767047801 | C22: JOCELYN CIRUELA SAKAY | D22: SKYPAY API | E22: 2000 | H22: Lending not approved
A23: 2020-01-08 01:28:39 PM | B23: BPX00110866032201 | C23: EILYN ABROGENA DIZON | D23: SKYPAY API | E23: 3570 | H23: Lending not approved
A24: 2020-01-07 06:13:42 PM | B24: BPX00110756498901 | C24: FRANCISCO JR DILIM AGBAYANI | D24: SKYPAY API | E24: 1650 | G24: As per Agent no Transaction Found | H24: Lending not approved due to customer have repeat loan
A25: 2020-01-07 06:25:44 PM | B25: BPX00110792610001 | C25: GAYLE GARCIA BENITO | D25: SKYPAY API | E25: 3923 | H25: Lending not approved
A26: 2020-01-08 04:14:11 PM | B26: BPX00110828458101 | C26: MARY GRACE TALLONGON ASWIT | D26: SKYPAY API | E26: 2140 | G26: No receipt- unreflected on agent's transaction history | H26: Lending not approved
A27: 2020-01-07 05:28:37 PM | B27: BPX00110795931701 | C27: RICRAI444 | D27: SKYPAY API | E27: 4500 | G27: With receipt | H27: Lending not approved
A28: 2020-02-10 01:18:21 PM | B28: BPX00111091107602 | C28: RONALD CABBAB VILORIA | D28: SKYPAY API | E28: 3000 | H28: Lending not approved
A29: 2020-03-04 08:38:24 AM | B29: BPX00110464917103 | C29: ALIENA EQUIZA BALBABOCO | D29: SKYPAY API | E29: 3960 | H29: Lending not approved
A30: 2020-09-23 13:29:15 | B30: BPX00112351848709 | C30: BALBABOCO, ALIENA EQUIZA | D30: SKYPAY API | E30: 4500 | G30: undeducted | H30: Lending not approved
A31: 2020-10-20 09:59:52 | B31: BPX00112046761910 | C31: COSEP, CATHERINE IMPRON | D31: SKYPAY API | E31: 3500 | H31: Lending not approved due to customer have repeat loan
A32: 2020-10-20 09:50:20 AM | B32: BPX00112043226410 | C32: CATHERINE IMPRON COSEP | D32: SKYPAY | E32: 3500 | G32: LENDING COMPANY REFUSED TO REFUND/ DISAPPROVED THE REQUEST | H32: not allowed for reversal
A33: 2020-10-20 09:54:39 AM | B33: BPX00112045653210 | C33: CATHERINE IMPRON COSEP | D33: SKYPAY | E33: 3500 | G33: LENDING COMPANY REFUSED TO REFUND/ DISAPPROVED THE REQUEST | H33: not allowed for reversal
A34: 2020-10-21 10:45:46 AM | B34: BPX00112168377610 | C34: RODEL CARANZO BENITEZ | D34: SKYPAY | E34: 1000 | G34: LENDING COMPANY REFUSED TO REFUND/ DISAPPROVED THE REQUEST | H34: not allowed for reversal
A35: 11/26/2020 | B35: BPX00112620499611 | C35: Raisasmile25 | D35: SKYPAY API | E35: 5000 | G35: LENDING COMPANY REFUSED TO REFUND/ DISAPPROVED THE REQUEST | H35: not allowed for reversal
A36: 2021-03-27 13:49:07 | B36: BPX00112724854603 | C36: MLWkimpav13 | D36: SKYPAY API | E36: 3000 | F36: =SUM(E10:E36) -> 92428 | G36: Lending NOT approved due to customer has loan with them | H36: not allowed for reversal
A37: 2021-05-11 09:24:54 | B37: BPX00111182130705 | C37: CERVANTES, MARICEL TOLENTINO | D37: SMART/SMARTBRO/SUNCELL/SUNBROADBAND | E37: 1000 | F37: =E37 -> 1000 | G37: unposted and undeductec on agent wallet balance | H37: emailed partner for approval, last ff. 6/07/22
A38: 2020-09-30 10:59:10 | B38: BPX00113081738409 | C38: ERRO, RUSSELL BALUNSAT | D38: UNIVERSITY OF CAGAYAN VALLEY, INC | E38: 2000 | F38: =E38 -> 2000 | G38: undeducted | H38: NOT ALLOWED FOR REVERSAL
A39: 43160 | B39: BPX00110147613603 | C39: PLDT/miseal dio caliso/3800282288 | D39: PLDT | E39: 1425 | G39: WRONG BILLER
A40: 43741 | B40: BPX00110318213610 | C40: PLDT/ANGEL BAES/719582915 | D40: PLDT | E40: 1000 | G40: WRONG BILLER
A41: 44684 | B41: BPX00110360392505 | C41: EMELYN S DE DIOS/316891950 | D41: PLDT | E41: 1399 | G41: unposted and undeducted on agent wallet balance
A42: 43773 | B42: BPX00110441663511 | C42: PLDT/Amor Solo/246042489 | D42: PLDT | E42: 1299 | G42: VOID TRANSACTION(Agent request to cancel since no payment received from customer but deducted from agent's account)
A43: 44655 | B43: BPX00110485143504 | C43: PLDT/HERNAN TABAN/0323001200 | D43: PLDT | E43: 1399 | G43: unposted and undeducted to agent wallet balance
A44: 44747 | B44: BPX00110563170607 | C44: randolph de sagun huertas/0272478430 | D44: PLDT | E44: 1300 | G44: Undeducted/No Payment Received
A45: 44718 | B45: BPX00110651885506 | C45: RODRIGO TENORIO/0290977045 | D45: PLDT | E45: 1450 | G45: Undeducted/No Payment Received
A46: 44718 | B46: BPX00110670784806 | C46: mitchelle utrillo/0303434356 | D46: PLDT | E46: 1300 | G46: Undeducted/No Payment Received
A47: 44718 | B47: BPX00110676465206 | C47: JOEY MANIBUG/0326268151 | D47: PLDT | E47: 1420 | G47: Undeducted/No Payment Received
A48: 44718 | B48: BPX00110682696606 | C48: RODRIGO TENORIO/0290977045 | D48: PLDT | E48: 1450 | G48: Undeducted/No Payment Received
A49: 44718 | B49: BPX00110682872606 | C49: RODRIGO TENORIO/0290977045 | D49: PLDT | E49: 1450 | G49: Undeducted/No Payment Received
A50: 44718 | B50: BPX00110698117406 | C50: RODRIGO TENORIO/0290977045 | D50: PLDT | E50: 1450 | G50: Undeducted/No Payment Received
... A53: 44649 | B53: BPX00112949349603 | C53: PLDT/joan mendoza/0252770402 | D53: PLDT | E53: 1299 | G53: unposted and undeducted to agent wallet balance
A54: 44649 | B54: BPX00112967437403 | C54: PLDT/joan mendoza/0252770402 | D54: PLDT | E54: 1299 | F54: =SUM(E39:E54) -> 22942 | G54: unposted and undeducted to agent wallet balance
A55: 44718 | B55: BPX00110634707206 | C55: VALLE, PEDRO/UP | D55: MCWD | E55: 276 | F55: =E55 -> 276 | G55: Undeducted/No Payment Received | H55: waiting for refund
A66: SUMMARY:
A67: CITY SAVINGS BANK | B67: =F5 -> 12500
A68: ILECO 3 | B68: =F7 -> 729.38
A69: MY SUPER PAY | B69: =F8 -> 4560
A70: PANELCO 1 | B70: =F9 -> 34
A71: SKYPAY API | B71: =F36 -> 92428
A72: SMART/SMARTBRO/SUNCELL/SUNBROADBAND | B72: =F37 -> 1000
A73: UNIVERSITY OF CAGAYAN VALLEY, INC | B73: =F38 -> 2000
A74: PLDT | B74: =F54 -> 22942
A75: MCWD | B75: =F55 -> 276
A77: TOTAL | B77: =SUM(B67:B76) -> 136469.38

Sheet AUDIT FINDINGS
A1: As of August 31, 2025
A2: FOR REFUND (RECEIVABLE)
A4: PERIOD | B4: PARTNERS | C4: TXN DATE | D4: REFERENCE NUMBER | E4: AMOUNT | F4: TOTAL PER BP
A5: AUGUST 2019 | B5: AIR YOU GO TRAVELS PHILS. CO. | C5: 8/29/2019 | D5: CV#293380;BDO001091 | E5: 779675.07 | F5: =E5 -> 779675.07
A6: SEPTEMBER 2018 | B6: ASTROKIDD TRAVEL AND TOURS | C6: 9/16/2018 | D6: CV#253793;BPI00820 | E6: 40777 | F6: =E6 -> 40777 | H6: 1000.00 unadjusted
A7: SEPTEMBER 2019 | B7: CIS BAYAD CENTER | C7: 9/28-29/2019 | D7: BPP58612432337407 | E7: 2000 | F7: =E7 -> 2000
A8: 44440 | B8: Cotabato Light & Power Company | C8: Sept. 1 & 28 | E8: 4613.67 | F8: =E8 -> 4613.67
A9: APRIL 2021 | B9: DAVAO LIGHTS & POWER CO., INC. | C9: 44291 | D9: BDO001499 | E9: 1635
A10: JANUARY 2018 | B10: DAVAO LIGHTS & POWER CO., INC. | C10: 01/16/2018 | D10: BPP98111829462712 | E10: 1075
A11: NOVEMBER 2017 | B11: DAVAO LIGHTS & POWER CO., INC. | C11: 42836 | D11: BPP54112713830110 | E11: 1817 | F11: =SUM(E9:E11) -> 4527
A12: NOVEMBER 2018 | B12: JCASS TOURS AND TRAVEL | C12: 11/20/2018 | D12: 268070;CV#261275;JCASS00031 | E12: 100 | F12: =E12 -> 100
A13: JULY 2019 | B13: NEGROS ORIENTAL ELECTRIC COOP. (JACULBE) | C13: 7/18/2019 | D13: BPW00110611869404 | E13: 1116.37 | F13: =E13 -> 1116.37
A14: AUGUST 2017 | B14: PAYSAVED PAYMENT SOLUTIONS | C14: 08/20/2017 | D14: CV#210073;PAYSAVED0013 | E14: 50
A15: JULY 2017 | B15: PAYSAVED PAYMENT SOLUTIONS | C15: 07/25/2017 | D15: CV#206416;PAYSAVED0006 | E15: 50
A16: MAY 2017 | B16: PAYSAVED PAYMENT SOLUTIONS | C16: 05/27/2017 | D16: CV#198054;PAYSAVED0003 | E16: 50 | F16: =SUM(E14:E16) -> 150
A17: DECEMBER 2019 | B17: PESOLOAN - MASAGANANG BUHAY FINANCE PHILS CORP. | C17: 12/26/2019 | D17: BPP83622421569012 | E17: 3500 | F17: =E17 -> 3500
A18: JANUARY 2021 | B18: RST TELECOMS | C18: 44200 | D18: BDOCHECK0858 | E18: 3500 | F18: =E18 -> 3500
A19: SEPTEMBER 2019 | B19: SHOP4FUN INC. | C19: 43594 | D19: CV#294407;BDO0010697 | E19: 980 | F19: =E19 -> 980
A20: FEBRUARY 2019 | B20: SKYBRIDGE PAYMENT INC. | C20: 2/22/2019 | D20: BPP50312050499702 | E20: 2964
A21: JANUARY 2020 | B21: SKYBRIDGE PAYMENT INC. | C21: 43831 | D21: Variance in CSO service charge | E21: 6.16
A22: MARCH 2020 | B22: SKYPAY API | C22: 3/6-8/2020 | D22: CV#318984;METRO01231 | E22: 10 | F22: =SUM(E20:E22) -> 2980.16
A23: MARCH 2020 | B23: TELEPRENEUR CORP. | C23: 43897 | D23: BPP81320633256203 | E23: 2000
A24: MARCH 2020 | B24: TELEPRENEUR CORP. | C24: 43898 | D24: BPP08860713778303 | E24: 1000
A25: MARCH 2020 | B25: TELEPRENEUR CORP. | C25: 43899 | D25: BPP20020844610903 | E25: 500
A26: MARCH 2020 | B26: TELEPRENEUR CORP. | C26: 43899 | D26: BPP07853097876701 | E26: 500
A27: MARCH 2020 | B27: TELEPRENEUR CORP. | C27: 43903 | D27: BPP54851278818803 | E27: 500
A28: MARCH 2020 | B28: TELEPRENEUR CORP. | C28: 43906 | D28: BPP22521536261303 | E28: 1000
A29: MARCH 2020 | B29: TELEPRENEUR CORP. | C29: 43913 | D29: BPP74962178135303 | E29: 1000
A30: MARCH 2020 | B30: TELEPRENEUR CORP. | C30: 43918 | D30: BPP07362777210103 | E30: 3500
A31: DECEMBER 2019 | B31: TELEPRENEURS CORP. | C31: 12/17/2019 | D31: BPP88821673971612 | F31: =SUM(E23:E31) -> 10000
A32: NOVEMBER 2017 | B32: TRAVELONLINE PHILIPPINES INC. | C32: 42805 | D32: CV#218772;BDO00051 | E32: 50 | F32: =E32 -> 50
F33: =SUM(F5:F32) -> 853969.27
A39: SUMMARY:
A40: AIR YOU GO TRAVELS PHILS. CO. | C40: =F5 -> 779675.07
A41: ASTROKIDD TRAVEL AND TOURS | C41: =F6 -> 40777
A42: CIS BAYAD CENTER | C42: =F7 -> 2000
A43: COTABATO LIGHT & POWER COMPANY | C43: =F8 -> 4613.67
A44: DAVAO LIGHTS & POWER CO., INC. | C44: =F11 -> 4527
A45: JCASS TOURS AND TRAVEL | C45: =F12 -> 100
A46: NEGROS ORIENTAL ELECTRIC COOP. (JACULBE) | C46: =F13 -> 1116.37
A47: PAYSAVED PAYMENT SOLUTIONS | C47: =F16 -> 150
A48: PESOLOAN - MASAGANANG BUHAY FINANCE PHILS CORP. | C48: =F17 -> 3500
A49: RST TELECOMS | C49: =F18 -> 3500
A50: SHOP4FUN INC. | C50: =F19 -> 980
A51: SKYBRIDGE PAYMENT INC. | C51: =F22 -> 2980.16
A52: TELEPRENEUR CORP. | C52: =F31 -> 10000
A53: TRAVELONLINE PHILIPPINES INC. | C53: =F32 -> 50
B54: TOTAL: | C54: =SUM(C40:C53) -> 853969.27

Sheet BANKS
A1: BP Receivables as of August 31, 2025
A3: BPI-RTA
A5: DATE | B5: REFERENCE NUMBER | C5: BENEFICIARY NAME | D5: REMITTER'S NAME | E5: AMOUNT | F5: BRANCH | G5: REASON
A6: 45306 | B6: BPP82521567843701 | C6: LOWIE JAY . DE LA CRUZ | D6: LOWIE JAY . DE LA CRUZ | E6: 40000 | F6: ML PIDDIG, ILOCOS NORTE | G6: DOUBLE POSTING
A7: 45306 | B7: BPP43211593369701 | C7: NOE LLORENTE LLORICO | D7: NOE L LLORICO | E7: 27610 | F7: ML CLAVER | G7: NO PAYMENT RECEIVED FROM THE CUSTOMER
E9: =SUM(E6:E8) -> 67610
A12: CHINABANK-RTA
A14: DATE | B14: REFERENCE NUMBER | C14: BENEFICIARY NAME | D14: BENEFICIARY DETAILS | E14: OPERATOR | F14: REASONS | G14: CAD REMARKS | H14: AMOUNT | I14: CHINABANK REMARKS
A15: 04/20/21 | B15: BPP45212043371604 | C15: SANCHEZ, GINA C | D15: 117600003202 | E15: ML SINDANGAN | F15: DOUBLE POSTING | G15: Emailed 05.12.21 | H15: 30300 | I15: Partner was able to contact the client last Friday and as per conversation, she can'y pat it one time.
H17: 30300
A23: SECURITY BANK - LAZADA
A24: QUERY NUMBER (Partner tracking reference number) | B24: LOCAL REFERENCE NO. | C24: TRACE NO. | D24: ACCOUNT NAME | E24: TARGET ACCOUNT | F24: TRANSACTION DATE | G24: TRANSACTION TIME | H24: TRANSACTION AMOUNT | I24: DISPUTED AMOUNT FOR REVERSAL | J24: REASON FOR REVERSAL | K24: DETAILS | L24: REPROCESSED TRANSACTION? | M24: SUPPORTING DOCUMENTS | N24: DATE SENT (Suppporting Documents) | O24: BRANCHES
A25: ML Transaction Query 32 | B25: BN-120922-56874 | C25: BPP06910925267112 | D25: SECURITY BANK LAZADA | E25: '061000128053 | F25: 44904.921 | G25: 0.92105324 | H25: 28760.95 | I25: 28760.95 | J25: WRONG ACCOUNT NUMBER | K25: Correct Account Number '0061000128053 | L25: NO | M25: YES, IR and Customer's form | N25: 44908 | O25: ML LAPU-LAPU 5
A26: ML Transaction Query 46 | B26: BN-122822-58883 | C26: BPP88722860340912 | D26: INC LAZADA | E26: '00061000128053 | F26: 44923.844 | G26: 0.84413194 | H26: 3079.65 | I26: 3079.65 | J26: WRONG ACCOUNT NUMBER | K26: Correct Account Number '0061000128053 & Correct Transaction BN-122822-58889 / BPP88722866616912 | L26: YES | M26: YES, IR and Customer's form | N26: 44924 | O26: ML IBAYO SILANGAN 2
A27: ML Transaction Query 48 | B27: BN-123022-56524 | C27: BPP05423080379712 | D27: SECURITY LAZADA | E27: '61000128053 | F27: 44925.701 | G27: 0.70111111 | H27: 7000 | I27: 7000 | J27: WRONG ACCOUNT NUMBER | K27: Correct Account Number '0061000128053 | L27: NO | M27: YES, IR and Customer's form | N27: 44930 | O27: ML SUSANO ROAD
A28: ML Transaction Query 50 | B28: BN-121622-57032 | C28: BPP57121698693812 | D28: INC LAZADA | E28: '061000128053 | F28: 44911.751 | G28: 0.75075231 | H28: 3000 | I28: 3000 | J28: WRONG ACCOUNT NUMBER | K28: Correct Account Number '0061000128053 | L28: NO | M28: YES, IR and Customer's form | N28: 44930 | O28: ML NAIC CAVITE
A29: ML Transaction Query 51 | B29: BN-122222-56790 | C29: BPP97822261481012 | D29: RANNIE CASANOVA | E29: '0061000128053 | F29: 44917.735 | G29: 0.73458333 | H29: 4935 | I29: 4500 | J29: OVERSTATED AMOUNT PHP 4,935.00 INSTEAD OF PHP 435.00 WITH THE DIFFERENCE OF PHP 4,500.00. | K29: Correct Amount should only be PHP 435.00 | L29: NO | M29: YES, IR and Customer's form | N29: 44930 | O29: ML BALLEZER
A30: ML Transaction Query 52 | B30: BN-122722-55426 | C30: BPP97822790582112 | D30: JESSICA GARCIA | E30: '0061000128053 | F30: 44922.782 | G30: 0.78179398 | H30: 10897 | I30: 5000 | J30: OVERSTATED AMOUNT PHP 10,897.00 INSTEAD OF PHP 5,897.00 WITH THE DIFFERENCE OF PHP 5,000.00. | K30: Correct Amount should only be PHP 5,897.00 | L30: NO | M30: YES, IR and Customer's form | N30: 44930 | O30: ML BALLEZER
A31: ML Transaction Query 55 | B31: BN-123022-57182 | C31: BPP09923074057212 | D31: SECURITY BANK SECURITY BANK | E31: '0061000128053 | F31: 44925.733 | G31: 0.73318287 | H31: 368.75 | I31: 368.75 | J31: NO PAYMENT RECEIVED DUE TO FLA RETURNED THE PAYMENT TO CUSTOMER | K31: Branch operator returned the payment due to error on our end. | L31: NO | M31: YES, IR and Validated Receipt | N31: 44931 | O31: ML REAL, CALAMBA
A32: ML Transaction Query 57 | B32: BN-122422-53121 | C32: BPP42722472681512 | D32: INC LAZADA | E32: '061000128053 | F32: 44919.55 | G32: 0.55018519 | H32: 40241.48 | I32: 40241.48 | J32: WRONG ACCOUNT NUMBER | K32: Correct Account Number '0061000128053 | L32: NO | M32: YES, IR and Customer's form | N32: 44932 | O32: ML AGUILAR, PANGASINAN
A33: ML Transaction Query 59 | B33: BN-010423-57062 | C33: BPP57120432420201 | D33: INC LAZADA | E33: '0061000128053 | F33: 44930.843 | G33: 0.84305556 | H33: 49711.89 | I33: 49711.89 | J33: NO PAYMENT RECEIVED DUE TO FLA RETURNED THE PAYMENT TO CUSTOMER | K33: Branch operator returned the payment due to error on our end. | L33: NO | M33: YES, IR and Validated Receipt | N33: 44933 | O33: ML NAIC CAVITE
A34: ML Transaction Query 60 | B34: BN-010623-57790 | C34: BPP58170659638701 | D34: LAZADA INC | E34: '061000128053 | F34: 44932.699 | G34: 0.69921296 | H34: 44921.26 | I34: 44921.26 | J34: WRONG ACCOUNT NUMBER | K34: Correct Account Number '0061000128053 & Correct Transaction BN-020823-55468 / BPP58170864854202 | L34: YES | M34: YES, IR and Customer's form | N34: 44933 | O34: ML SAPANG MAISAC
A35: ML Transaction Query 61 | B35: BN-120722-55923 | C35: BPP24020779981912 | D35: LAZADA INC LAZADA INC | E35: '061000128053 | F35: 44902.88 | G35: 0.88025463 | H35: 9449.02 | I35: 9449.02 | J35: WRONG ACCOUNT NUMBER | K35: Correct Account Number '0061000128053 & Correct Transaction BN-120722-55932 / BPP24020793297812 | L35: YES | M35: YES, IR and Customer's form | N35: 44935 | O35: ML DIVISORIA
A36: ML Transaction Query 62 | B36: BN-010923-54966 | C36: BPP04380970857201 | D36: LAZADA LAZADA | E36: '061000128053 | F36: 44935.684 | G36: 0.68427083 | H36: 20000 | I36: 20000 | J36: WRONG ACCOUNT NUMBER | K36: Correct Account Number '0061000128053 | L36: NO | M36: YES, IR and Customer's form | N36: 44936 | O36: ML BAGUMBAYAN TAGUIG
... A50: ML Transaction Query 102 | B50: BN-022523-51471 | C50: BPP45672594041002 | D50: LAZADA INC LAZADA INC | E50: '00061000128053 | F50: 44982.532 | G50: 0.531875 | H50: 18000 | I50: 18000 | J50: WRONG ACCOUNT NUMBER | K50: Correct Account Number '0061000128053 | L50: NO | M50: YES, IR and Customer's form | N50: 44985 | O50: ML AMAYA
A51: ML Transaction Query 104 | B51: BN-121022-54972 | C51: BPP06151018334512 | D51: BANK SECURITY | E51: '0061000128053 | F51: 44905.742 | G51: 0.74152778 | H51: 25185.74 | I51: 25185.74 | J51: REJECTED - POSTED TRANSACTION | N51: 44985 | O51: ML MANDAUE 5
A52: ML Transaction Query 105 | B52: BN-022723-54584 | C52: BPP93922782809702 | D52: LAZADA INC | E52: '0061000128053 | F52: 44984.639 | G52: 0.63884259 | H52: 2455.04 | I52: 10 | J52: OVERSTATED AMOUNT PHP 2,455.04 INSTEAD OF PHP 2,445.04 WITH THE DIFFERENCE OF PHP 10.00. | K52: Correct Amount should only be PHP 2,445.04 | L52: NO | M52: YES, IR and Customer's form | N52: 44986 | O52: ML LAOAC
A53: ML Transaction Query 107 | B53: BN-022323-50652 | C53: BPP85722393514602 | D53: LAZADA INC ALZADA INC | E53: '0061000128053 | F53: 44980.309 | G53: 0.30890046 | H53: 10895 | I53: 10895 | J53: NO PAYMENT RECEIVED DUE TO FLA RETURNED THE PAYMENT TO CUSTOMER | K53: Branch operator returned the payment due to error on our end. | L53: NO | M53: YES, IR and Validated Receipt | N53: 44987 | O53: ML PASIG 2
A54: ML Transaction Query 109 | B54: BN-030923-57795 | C54: BPP26020926509703 | D54: LAZADA INC LAZADA INC | E54: '00061000128053 | F54: 44994.807 | G54: 0.80681713 | H54: 40000 | I54: 40000 | J54: WRONG ACCOUNT NUMBER | K54: Correct Account Number '0061000128053 | L54: NO | M54: YES, IR and Customer's form | N54: 44995 | O54: ML CROSSING N.E.
A55: ML Transaction Query 110 | B55: BN-030923-57586 | C55: BPP45220920295903 | D55: LAZADA INC LAZADA INC | E55: '061000128053 | F55: 44994.778 | G55: 0.77780093 | H55: 2109.02 | I55: 2109.02 | J55: WRONG ACCOUNT NUMBER | K55: Correct Account Number '0061000128053 | L55: NO | M55: YES, IR and Customer's form | N55: 44996 | O55: ML BALUT, TONDO
A56: ML Transaction Query 111 | B56: BN-031023-57646 | C56: BPP17621041292603 | D56: SECURITY LAZADA | E56: '0061000128053 | F56: 44995.753 | G56: 0.75325231 | H56: 29244.26 | I56: 0.1 | J56: OVERSTATED AMOUNT PHP 29,244.26 INSTEAD OF PHP 29,244.16 WITH THE DIFFERENCE OF PHP 0.10. | K56: Correct Amount should only be PHP 29,244.16 | L56: NO | M56: YES, IR and Customer's form | N56: 44996 | O56: ML PAMPLONA TRES - STAR MALL LAS PIÑAS
A57: ML Transaction Query 112 | B57: BN-031223-51937 | C57: BPP93421274818203 | D57: LAZADA LAZADA | E57: '00061000128053 | F57: 44997.691 | G57: 0.69063657 | H57: 9621.97 | I57: 9621.97 | J57: WRONG ACCOUNT NUMBER | K57: Correct Account Number '0061000128053 | L57: NO | M57: YES, IR and Customer's form | N57: 44998 | O57: ML MAHARLIKA
A58: ML Transaction Query 116 | B58: BN-031323-58043 | C58: BPP85721386916003 | D58: LAZADA INC LAZADA INC | E58: '00061000128053 | F58: 44998.873 | G58: 0.87313657 | H58: 24156.07 | I58: 24156.07 | J58: WRONG ACCOUNT NUMBER | K58: Correct Account Number '0061000128053 | L58: NO | M58: YES, IR and Customer's form | N58: 45000 | O58: ML PASIG 2
A59: ML Transaction Query 117 | B59: BN-031423-59313 | C59: BPP08111436191703 | D59: BANK SECURITY | E59: '00061000128053 | F59: 44999.828 | G59: 0.82842593 | H59: 14517.46 | I59: 14517.46 | J59: WRONG ACCOUNT NUMBER | K59: Correct Account Number '0061000128053 | L59: NO | M59: YES, IR and Customer's form | N59: 45000 | O59: ML CONSOLACION 2
A60: ML Transaction Query 118 | B60: BN-031623-57681 | C60: BPP05471639376003 | D60: LAZADA INC | E60: '061000128053 | F60: 45001.677 | G60: 0.67667824 | H60: 2000 | I60: 2000 | J60: WRONG ACCOUNT NUMBER | K60: Correct Account Number '0061000128053 | L60: NO | M60: YES, IR and Customer's form | N60: 45002 | O60: ML SAN JUAN, LA UNION
A61: ML Transaction Query 120 | B61: BN-031723-57598 | C61: BPP52221784456503 | D61: LAZADA INC LAZADA INC | E61: '061000128053 | F61: 45002.683 | G61: 0.68328704 | H61: 3993.77 | I61: 3993.77 | J61: WRONG ACCOUNT NUMBER | K61: Correct Account Number '0061000128053 | L61: NO | M61: YES, IR and Customer's form | N61: 45003 | O61: ML TONDO 1
A62: ML Transaction Query 124 | B62: BN-032123-55168 | C62: BPP17972146439203 | D62: INC LAZADA INC | E62: '0061000128053 | F62: 45006.616 | G62: 0.61607639 | H62: 26739.96 | I62: 24066 | J62: OVERSTATED AMOUNT PHP 26,739.96 INSTEAD OF PHP 2,673.96 WITH THE DIFFERENCE OF PHP 24,066.00 | K62: Correct Amount should only be PHP 2,673.96 | L62: NO | M62: YES, IR and Customer's form | N62: 45006 | O62: ML MAAHAS LOS BANOS LAGUNA | P62: ?
A63: ML Transaction Query 125 | B63: BN-032123-55816 | C63: BPP56022168045403 | D63: LAZADA INC LAZADA INC | E63: '0061000128053 | F63: 45006.645 | G63: 0.64498843 | H63: 26589.15 | I63: 15979.14 | J63: OVERSTATED AMOUNT PHP 26,589.15 INSTEAD OF PHP 10,610.01 WITH THE DIFFERENCE OF PHP 15,979.14 | K63: Correct Amount should only be PHP 10,610.01 | L63: NO | M63: YES, IR and Customer's form | N63: 45006 | O63: ML AGONCILLO
A64: ML Transaction Query 127 | B64: BN-032323-57531 | C64: BPP45222332690003 | D64: LAZADA LAZADA | E64: '061000128053 | F64: 45008.757 | G64: 0.75733796 | H64: 63 | I64: 63 | J64: WRONG ACCOUNT NUMBER | K64: Correct Account Number '0061000128053 | L64: NO | M64: YES, IR and Customer's form | N64: 45009 | O64: ML BALUT, TONDO
A65: ML Transaction Query 130 | B65: BN-032123-55561 | C65: BPP25662157456003 | D65: SECURITY BANK CORP-LAZADA SECURITY BANK CORP-LAZADA | E65: '061000128053 | F65: 45006.642 | G65: 0.64173611 | H65: 42241.67 | I65: 42241.67 | J65: WRONG ACCOUNT NUMBER | K65: Correct Account Number '0061000128053 | L65: NO | M65: YES, IR and Customer's form | N65: 45010 | O65: ML AGUSAN
A66: ML Transaction Query 131 | B66: BN-020523-51833 | C66: BPP66420538932902 | D66: LAZADA LAZADA | E66: '00061000128053 | F66: 44962.601 | G66: 0.60083333 | H66: 3386 | I66: 3386 | J66: WRONG ACCOUNT NUMBER | K66: Correct Account Number '0061000128053 | L66: NO | M66: YES, IR and Customer's form | N66: 45012 | O66: ML PADRE GARCIA
A67: ML Transaction Query 139 | B67: BN-040423-56659 | C67: BPP53920470382604 | D67: LAZADA LAZADA | E67: '061000128053 | F67: 45020.684 | G67: 0.68351852 | H67: 2280.32 | I67: 2280.32 | J67: WRONG ACCOUNT NUMBER | K67: Correct Account Number '0061000128053 | L67: NO | M67: YES, IR and Customer's form | N67: 45021 | O67: ML ANGONO
A68: ML Transaction Query 142 | B68: BN-040623-51942 | C68: BPP50670624519104 | D68: LAZADA LAZADA | E68: '0061000128053 | F68: 45022.662 | G68: 0.6616088 | H68: 2956.56 | I68: 360 | J68: OVERSTATED AMOUNT PHP 2,956.56 INSTEAD OF PHP 2,596.56 WITH THE DIFFERENCE OF PHP 360 | K68: Correct Amount should only be PHP 2,596.56 | L68: NO | M68: YES, IR and Customer's form | N68: 45027 | O68: ML TIMBAO
A69: ML Transaction Query 146 | B69: BN-040423-57971 | C69: BPP85820480798804 | D69: INC LAZADA | E69: '0061000128053 | F69: 45020.729 | G69: 0.72908565 | H69: 7824.67 | I69: 6000 | J69: OVERSTATED AMOUNT PHP 7,824.67 INSTEAD OF PHP 1,824.67 WITH THE DIFFERENCE OF PHP 6,000.00 | K69: Correct Amount should only be PHP 1,824.67 | L69: NO | M69: YES, IR and Customer's form | N69: 45029 | O69: ML CAMALIG, MEYCAUAYAN
A70: ML Transaction Query 149 | B70: BN-041223-56260 | C70: BPP23571259239304 | D70: INC LAZADA | E70: '0061000128053 | F70: 45028.688 | G70: 0.68791667 | H70: 3903.5 | I70: 810 | J70: OVERSTATED AMOUNT PHP 3,903.50 INSTEAD OF PHP 3,093.50 WITH THE DIFFERENCE OF PHP 810.00 | K70: Correct Amount should only be PHP 3,093.50 | L70: NO | M70: YES, IR and Customer's form | N70: 45029 | O70: ML SAN LUIS BATANGAS
A71: ML Transaction Query 152 | B71: BN-041223-56237 | C71: BPP39821253175604 | D71: BANK SECURITY | E71: '061000128053 | F71: 45028.686 | G71: 0.68579861 | H71: 12000 | I71: 12000 | J71: WRONG ACCOUNT NUMBER | K71: Correct Account Number '0061000128053 | L71: NO | M71: YES, IR and Customer's form | N71: 45030 | O71: ML MALVAR, BATANGAS
A72: ML Transaction Query 153 | B72: BN-021723-55148 | C72: BPP78321762610402 | D72: INC LAZADA | E72: '061000128053 | F72: 44974.659 | G72: 0.65918981 | H72: 4524.51 | I72: 4524.51 | J72: WRONG ACCOUNT NUMBER | K72: Correct Account Number '0061000128053 | L72: NO | M72: YES, IR and Customer's form | N72: 45030 | O72: ML VILLASIS
A73: ML Transaction Query 154 | B73: BN-030323-55718 | C73: BPP40450375622803 | D73: BANK SECURITY | E73: '00061000128053 | F73: 44988.692 | G73: 0.69150463 | H73: 25371.77 | I73: 25371.77 | J73: WRONG ACCOUNT NUMBER | K73: Correct Account Number '0061000128053 | L73: NO | M73: YES, IR and Customer's form | N73: 45030 | O73: ML BAKILID MANDAUE
A74: ML Transaction Query 155 | B74: BN-041423-58110 | C74: BPP52721495600404 | D74: LAZADA LAZADA | E74: '00061000128053 | F74: 45030.69 | G74: 0.69005787 | H74: 2078.07 | I74: 2078.07 | J74: WRONG ACCOUNT NUMBER | K74: Correct Account Number '0061000128053 | L74: NO | M74: YES, IR and Customer's form | N74: 45031 | O74: ML TAYUMAN, MANILA
... A105: ML Transaction Query 271 | B105: BN-072923-58394 | C105: BPP85822933393507 | D105: LAZADA INC | E105: '0061000128053 | F105: 45136.677 | G105: 0.67681713 | H105: 50 | I105: 50 | J105: NO PAYMENT RECEIVED FROM THE CUSTOMER DUE TO FLA RETURNED THE PAYMENT | K105: Branch operator returned the payment due to error on our end. | L105: NO | M105: YES, IR and No Printed receipt due to error | N105: 45145 | O105: ML CAMALIG, MEYCAUAYAN
A106: ML Transaction Query 272 | B106: '202308080300006247 | C106: BPP35120811003508 | D106: LAZADA INC LAZADA INC | E106: '0061000128053 | F106: 'August 08 | G106: 2023 15:56:29 | H106: 9731.52 | I106: 3000 | J106: OVERSTATED AMOUNT PHP 9,731.52 INSTEAD OF PHP 6,731.52 WITH THE DIFFERENCE OF PHP 3,000. | K106: Correct Amount should only be PHP 6,731.52 | L106: NO | M106: YES, IR and Customer's form | N106: 45146 | O106: ML CASTILLEJOS 2
A107: ML Transaction Query 274 | B107: '202308060300001618 | C107: BPP57820677327808 | D107: LAZADA INC INC | E107: '0061000128053 | F107: August 06 | G107: 2023 14:58:13 | H107: 8717.36 | I107: 8717.36 | J107: DOUBLE POSTING | K107: Correct Transaction 202308060300001659 / BPP57820630945708 | L107: YES | M107: YES, IR and Reprocessed Receipt | N107: 45147 | O107: ML BACOOR
A108: ML Transaction Query 275 | B108: BN-080323-60720 | C108: BPP22820399469108 | D108: INC LAZADA | E108: '0061000128053 | F108: 45141.762 | G108: 0.7615625 | H108: 8750.74 | I108: 4276.52 | J108: OVERSTATED AMOUNT PHP 8,750.74 INSTEAD OF PHP 4,474.22 WITH THE DIFFERENCE OF PHP 4,276.52. | K108: Correct Amount should only be PHP 4,474.22 | L108: NO | M108: YES, IR and Customer's form | N108: 45148 | O108: ML OLONGAPO 4
A109: ML Transaction Query 276 | B109: '202308110300005395 | C109: BPP01961111782608 | D109: SECURITY BANK - LAZADA SECURITY BANK - LAZADA SECURITY BANK - LAZADA | E109: '0061000128053 | F109: 'August 11 | G109: 2023 15:47:57 | H109: 15545.38 | I109: 5000 | J109: OVERSTATED AMOUNT PHP 15,545.38 INSTEAD OF PHP 10,545.38 WITH THE DIFFERENCE OF PHP 5,000.00. | K109: Correct Amount should only be PHP 10,545.38 | L109: NO | M109: YES, IR and Customer's form | N109: 45150 | O109: ML ALAE
A110: ML Transaction Query 277 | B110: '202308090300002212 | C110: BPP94420917551108 | D110: JOSEPH CHRISTIAN L CUYUGAN | E110: '0061000128053 | F110: 'August 09 | G110: 2023 09:40:11 | H110: 1400 | I110: 1400 | J110: WRONG BILLER - INTENDED FOR PAYNAMICS EXPRESS | K110: Correct Biller should be PAYNAMICS EXPRESS due to FLA wrongly input the biller. | L110: NO | M110: YES, IR and Customer's form | N110: 45150 | O110: ML DOWNTOWN, PAMPANGA
A111: ML Transaction Query 279 | B111: '202308110300005098 | C111: BPP19271173452408 | D111: LAZADA INC LAZADA INC LAZADA INC | E111: '0061000128053 | F111: 'August 11 | G111: 2023 14:39:53 | H111: 16689.72 | I111: 16689.72 | J111: NO PAYMENT RECEIVED FROM THE CUSTOMER | K111: Branch operator returned the payment due to error on our end. | L111: NO | M111: YES, IR and No Printed receipt due to error | N111: 45152 | O111: ML LANDMASS
A112: ML Transaction Query 288 | B112: '202308110300005306 | C112: BPP16721124798608 | D112: LAZADA LAZADA LAZADA | E112: '0061000128053 | F112: 'August 11 | G112: 2023 15:28:51 | H112: 10199.55 | I112: 10199.55 | J112: NO PAYMENT RECEIVED FROM THE CUSTOMER | K112: Branch operator returned the payment due to error on our end. | L112: NO | M112: YES, IR and No Printed receipt due to error | N112: 45153 | O112: ML BAY LAGUNA
A113: ML Transaction Query 295 | B113: '202308110300006142 | C113: BPP86171111157408 | D113: LAZADA INC INC | E113: '0061000128053 | F113: 'August 11 | G113: 2023 17:13:08 | H113: 6863.04 | I113: 6863.04 | J113: MULTIPLE POSTING | K113: Branch operator returned the payment due to error on our end. | L113: NO | M113: YES, IR and No Printed receipt due to error | N113: 45155 | O113: ML PANDACAQUI 2, MEXICO BRANCH
A114: ML Transaction Query 296 | B114: '202308110300006362 | C114: BPP86171118445308 | D114: LAZADA INC INC | E114: '0061000128053 | F114: 'August 11 | G114: 2023 17:18:11 | H114: 6863.04 | I114: 6863.04 | J114: MULTIPLE POSTING | K114: Branch operator returned the payment due to error on our end. | L114: NO | M114: YES, IR and No Printed receipt due to error | N114: 45155 | O114: ML PANDACAQUI 2, MEXICO BRANCH
A115: ML Transaction Query 297 | B115: '202308110300006416 | C115: BPP86171145006008 | D115: LAZADA INC INC | E115: '0061000128053 | F115: 'August 11 | G115: 2023 17:22:01 | H115: 6863.04 | I115: 6863.04 | J115: MULTIPLE POSTING | K115: Branch operator returned the payment due to error on our end. | L115: NO | M115: YES, IR and No Printed receipt due to error | N115: 45155 | O115: ML PANDACAQUI 2, MEXICO BRANCH
A116: ML Transaction Query 298 | B116: '202308110300006040 | C116: BPP86171162197008 | D116: LAZADA INC INC | E116: '0061000128053 | F116: 'August 11 | G116: 2023 17:05:42 | H116: 6863.04 | I116: 6863.04 | J116: MULTIPLE POSTING | K116: Branch operator returned the payment due to error on our end. | L116: NO | M116: YES, IR and No Printed receipt due to error | N116: 45155 | O116: ML PANDACAQUI 2, MEXICO BRANCH
A117: ML Transaction Query 299 | B117: '202308110300006341 | C117: BPP86171177666408 | D117: LAZADA INC INC | E117: '0061000128053 | F117: 'August 11 | G117: 2023 17:16:53 | H117: 6863.04 | I117: 6863.04 | J117: MULTIPLE POSTING | K117: Branch operator returned the payment due to error on our end. | L117: NO | M117: YES, IR and No Printed receipt due to error | N117: 45155 | O117: ML PANDACAQUI 2, MEXICO BRANCH
A118: ML Transaction Query 305 | B118: '202308110300005829 | C118: BPP86171192487408 | D118: LAZADA INC INC | E118: '0061000128053 | F118: 'August 11 | G118: 2023 16:48:48 | H118: 8446.34 | I118: 8446.34 | J118: NO PAYMENT RECEIVED FROM THE CUSTOMER | K118: Branch operator returned the payment due to error on our end. | L118: NO | M118: YES, IR and No Printed receipt due to error | N118: 45155 | O118: ML PANDACAQUI 2, MEXICO BRANCH
A119: ML Transaction Query 308 | B119: '202308110300006799 | C119: BPP86451189721408 | D119: LAZADAINC LAZADA INC LAZADA INC | E119: '0061000128053 | F119: 'August 11 | G119: 2023 17:59:49 | H119: 21043.39 | I119: 21043.39 | J119: NO PAYMENT RECEIVED FROM THE CUSTOMER | K119: Branch operator returned the payment due to error on our end. | L119: NO | M119: YES, IR and No Printed receipt due to error | N119: 45157 | O119: ML CORDOVA
A120: ML Transaction Query 309 | B120: '202308190300011411 | C120: BPX00111936492608 | D120: SECURITY BANK LAZADA | E120: '0061000128053 | F120: 'August 19 | G120: 2023 17:18:52 | H120: 7581.55 | I120: 5000 | J120: OVERSTATED AMOUNT PHP 7,581.55 INSTEAD OF PHP 2,581.55 WITH THE DIFFERENCE OF PHP 5,000. | K120: Correct Amount should only be PHP 2,581.55 | L120: NO | M120: YES, IR and Customer's form | N120: 45161 | O120: CEBU HEAD OFFICE
... A130: ML Transaction Query 340 | B130: '202308110300006177 | C130: BPP15721199271308 | D130: LAZADA INC SECURITY BANK | E130: '0061000128053 | F130: 'August 11 | G130: 2023 17:14:03 | H130: 4197.72 | I130: 4197.72 | J130: NO PAYMENT RECEIVED FROM THE CUSTOMER | K130: Branch operator returned the payment due to error on our end. | L130: NO | M130: YES, IR and No Printed receipt due to error | N130: 45163 | O130: ML SHORTHORN
A131: ML Transaction Query 343 | B131: '202308260300008385 | C131: BPP78522649226708 | D131: INC LAZADA | E131: '0061000128053 | F131: 45164.723 | G131: 0.72251157 | H131: 18737.7 | I131: 364 | J131: OVERSTATED AMOUNT PHP 18,737.70 INSTEAD OF PHP 18,373.70 WITH THE DIFFERENCE OF PHP 364.00. | K131: Correct Amount should only be PHP 18,373.70 | L131: NO | M131: YES, IR and Customer's form | N131: 45167 | O131: ML ALAMINOS, PANGASINAN
A132: ML Transaction Query 350 | B132: '202309010300007736 | C132: BPP02380142215709 | D132: LAZADA LAZADA | E132: '0061000128053 | F132: 45170.642 | G132: 0.64212963 | H132: 9000 | I132: 8910 | J132: OVERSTATED AMOUNT PHP 9,000.00 INSTEAD OF PHP 90.00 WITH THE DIFFERENCE OF PHP 8,910.00. | K132: Correct Amount should only be PHP 90.00 | L132: NO | M132: YES, IR and Customer's form | N132: 45171 | O132: ML SAN MIGUEL TAGUIG
A133: ML Transaction Query 353 | B133: '202308160300007695 | C133: BPP80121627105608 | D133: JOANNE ROWENA A CORNEJO | E133: '0061000128053 | F133: 'August 16 | G133: 2023 16:04:01 | H133: 3700 | I133: 3700 | J133: WRONG BILLER - INTENDED FOR LAZADA TOP UP | K133: Correct Billler - Lazada Top Up | L133: NO | M133: YES, IR and Customer's form | N133: 45176 | O133: ML SAN JOSE CITY
A134: ML Transaction Query 355 | B134: '202309130300007992 | C134: BPP17621346409209 | D134: SECURITY LAZADA | E134: '0061000128053 | F134: 45182.756 | G134: 0.75572917 | H134: 5493.7 | I134: 900 | J134: OVERSTATED AMOUNT PHP 5,493.70 INSTEAD OF PHP 4,593.70 WITH THE DIFFERENCE OF PHP 900.00. | K134: Correct Amount should only be PHP 4,593.70 | L134: NO | M134: YES, IR and Customer's form | N134: 45183 | O134: ML PAMPLONA TRES - STAR MALL LAS PIÑAS
A135: ML Transaction Query 359 | B135: '202309130300006127 | C135: BPP30011361790109 | D135: KARL DOMINIC BAJO | E135: '0061000128053 | F135: 45182.66 | G135: 0.65990741 | H135: 17201.45 | I135: 17201.45 | J135: NO PAYMENT RECEIVED FROM THE CUSTOMER | K135: Branch operator returned the payment due to error on our end. | L135: NO | M135: YES, IR and No Printed receipt due to error | N135: 45188 | O135: ML BOULEVARD
A136: ML Transaction Query 360 | B136: '202309130300006457 | C136: BPP45621378722609 | D136: LAZADA INC LAZADA INC | E136: '0061000128053 | F136: 45182.677 | G136: 0.67716435 | H136: 276.35 | I136: 276.35 | J136: NO PAYMENT RECEIVED FROM THE CUSTOMER | K136: Branch operator returned the payment due to error on our end. | L136: NO | M136: YES, IR and No Printed receipt due to error | N136: 45188 | O136: ML LIBERTAD PASAY
A137: ML Transaction Query 364 | B137: '202309200300009367 | C137: BPP57122028263509 | D137: INC LAZADA | E137: '0061000128053 | F137: 45189.673 | G137: 0.67277778 | H137: 7600 | I137: 7600 | J137: WRONG BILLER - INTENDED FOR MICROVENTURES PHILS. FINANCING COMPANY | K137: Correct Biller should MICROVENTURES INC PHIL. FINANCING COMPANY due to FLA wrongly input the biller. | L137: NO | M137: YES, IR and Customer's form | N137: 45190 | O137: ML NAIC CAVITE
A138: ML Transaction Query 365 | B138: '202309200300013062 | C138: BPP26022080881909 | D138: LAZADA INC LAZADA INC | E138: '0061000128053 | F138: 45189.901 | G138: 0.90079861 | H138: 9072.18 | I138: 8968.06 | J138: OVERSTATED AMOUNT PHP 9,072.18 INSTEAD OF PHP 104.12 WITH THE DIFFERENCE OF PHP 8,968.06. | K138: Correct Amount should only be PHP 104.12 | L138: NO | M138: YES, IR and Customer's form | N138: 45191 | O138: ML CROSSING N.E.
A139: ML Transaction Query 366 | B139: '202308130300002951 | C139: BPP91021330161908 | D139: LAZADA INC INC | E139: '0061000128053 | F139: 'August 13 | G139: 2023 16:01:36 | H139: 10419.02 | I139: 9000 | J139: OVERSTATED AMOUNT PHP 10,419.02 INSTEAD OF PHP 1,419.02 WITH THE DIFFERENCE OF PHP 9,000.00. | K139: Correct Amount should only be PHP 1,419.02 | L139: NO | M139: YES, IR and Customer's form | N139: 45191 | O139: ML STA. ANA, PAMPANGA
A140: ML Transaction Query 369 | B140: '202309130300005034 | C140: BPP72621399703109 | D140: INC LAZADA | E140: '0061000128053 | F140: 45182.577 | G140: 0.57690972 | H140: 6426.63 | I140: 6426.63 | J140: NO PAYMENT RECEIVED FROM THE CUSTOMER | K140: Branch operator returned the payment due to error on our end. | L140: NO | M140: YES, IR and No Printed receipt due to error | N140: 45191 | O140: ML SAN MIGUEL
A141: ML Transaction Query 370 | B141: '202309220300007229 | C141: BPP47722239632209 | D141: LAZADA INC | E141: '0061000128053 | F141: 45191.657 | G141: 0.65743056 | H141: 13125.72 | I141: 3920.58 | J141: OVERSTATED AMOUNT PHP 13,125.72 INSTEAD OF PHP 9,205.14 WITH THE DIFFERENCE OF PHP 3,920.58. | K141: Correct Amount should only be PHP 9,205.14 | L141: NO | M141: YES, IR and Customer's form | N141: 45192 | O141: ML PANDACAQUI
A142: ML Transaction Query 371 | B142: '202309230300005609 | C142: BPP87522313709809 | D142: LAZADA INC | E142: '0061000128053 | F142: 45192.62 | G142: 0.61993056 | H142: 9933.33 | I142: 4000 | J142: OVERSTATED AMOUNT PHP 9,933.33 INSTEAD OF PHP 5,933.33 WITH THE DIFFERENCE OF PHP 4,000.00. | K142: Correct Amount should only be PHP 5,933.33 | L142: NO | M142: YES, IR and Customer's form | N142: 45194 | O142: ML SAN LUIS PAMPANGA
A143: ML Transaction Query 375 | B143: '202309230300005870 | C143: BPP57122336497609 | D143: INC LAZADA | E143: '0061000128053 | F143: 45192.633 | G143: 0.63267361 | H143: 17721.78 | I143: 15027.75 | J143: OVERSTATED AMOUNT PHP 17,721.78 INSTEAD OF PHP 2,694.03 WITH THE DIFFERENCE OF PHP 15,027.75. | K143: Correct Amount should only be PHP 2,694.03 | L143: NO | M143: YES, IR and Customer's form | N143: 45194 | O143: ML NAIC CAVITE
A144: ML Transaction Query 378 | B144: '202309270300010782 | C144: BPP78322781819409 | D144: INC LAZADA | E144: '0061000128053 | F144: 45196.707 | G144: 0.70668981 | H144: 17451.28 | I144: 7003.79 | J144: OVERSTATED AMOUNT PHP 17,451.28 INSTEAD OF PHP 10,447.49 WITH THE DIFFERENCE OF PHP 7,003.79. | K144: Correct Amount should only be PHP 10,447.49 | L144: NO | M144: YES, IR and Customer's form | N144: 45197 | O144: ML VILLASIS
A145: ML Transaction Query 380 | B145: '202309280300006132 | C145: BPP52722813776209 | D145: LAZADA INC LAZADA INC | E145: '0061000128053 | F145: 45197.62 | G145: 0.61982639 | H145: 364.41 | I145: 328 | J145: OVERSTATED AMOUNT PHP 364.41 INSTEAD OF PHP 36.41 WITH THE DIFFERENCE OF PHP 328.00. | K145: Correct Amount should only be PHP 36.41 | L145: NO | M145: YES, IR and Customer's form | N145: 45198 | O145: ML TAYUMAN, MANILA
A146: ML Transaction Query 381 | B146: '202310040300008118 | C146: BPP78320427748410 | D146: INC LAZADA | E146: '0061000128053 | F146: 45203.67 | G146: 0.67005787 | H146: 8653.91 | I146: 3009.83 | J146: OVERSTATED AMOUNT PHP 8,653.91 INSTEAD OF PHP 5,644.08 WITH THE DIFFERENCE OF PHP 3,009.83. | K146: Correct Amount should only be PHP 5,644.08 | L146: NO | M146: YES, IR and Customer's form | N146: 45204 | O146: ML VILLASIS
A147: ML Transaction Query 383 | B147: '202310050300008037 | C147: BPP11080517002710 | D147: LAZADA INC LAZADA INC | E147: '0061000128053 | F147: 45204.666 | G147: 0.66638889 | H147: 3161.98 | I147: 1800 | J147: OVERSTATED AMOUNT PHP 3,161.98 INSTEAD OF PHP 1,361.98 WITH THE DIFFERENCE OF PHP 1,800.00. | K147: Correct Amount should only be PHP 1,361.98 | L147: NO | M147: YES, IR and Customer's form | N147: 45205 | O147: ML TIKLING 2 RIZAL
A148: ML Transaction Query 386 | B148: '202310120300012165 | C148: BPP73221222690810 | D148: LAZADA INC | E148: '0061000128053 | F148: 45211.822 | G148: 0.82215278 | H148: 12942.64 | I148: 6228.86 | J148: OVERSTATED AMOUNT PHP 12,942.64 INSTEAD OF PHP 6,713.78 WITH THE DIFFERENCE OF PHP 6,228.86. | K148: Correct Amount should only be PHP 6,713.78 | L148: NO | M148: YES, IR and Customer's form | N148: 45212 | O148: ML BARRETTO
A149: ML Transaction Query 388 | B149: '202309130300006439 | C149: BPP30311316687609 | D149: LAZADA INC LAZADA INC | E149: '0061000128053 | F149: 45182.676 | G149: 0.67611111 | H149: 315.16 | I149: 315.16 | J149: NO PAYMENT RECEIVED FROM THE CUSTOMER | K149: Branch operator returned the payment due to error on our end. | L149: NO | M149: YES, IR and No Printed receipt due to error | N149: 10/19.2023 | O149: ML PANACAN 1
A150: ML Transaction Query 392 | B150: '202310210300010723 | C150: BPP97822110948610 | D150: LAZADA INC LAZADA INC | E150: '0061000128053 | F150: 45220.898 | G150: 0.89847222 | H150: 3565.95 | I150: 1000 | J150: OVERSTATED AMOUNT PHP 3,565.95 INSTEAD OF PHP 2,565.95 WITH THE DIFFERENCE OF PHP 1,000.00. | K150: Correct Amount should only be PHP 2,565.95 | L150: NO | M150: YES, IR and Customer's form | N150: 45223 | O150: ML BALLEZER
A151: ML Transaction Query 396 | B151: '202310110300011098 | C151: BPP57121114900310 | D151: INC LAZADA | E151: '0061000128053 | F151: 45210.652 | G151: 0.65246528 | H151: 11072.97 | I151: 9847.26 | J151: OVERSTATED AMOUNT PHP 11,072.97 INSTEAD OF PHP 1,225.71 WITH THE DIFFERENCE OF PHP 9,847.26. | K151: Correct Amount should only be PHP 1,225.71 | L151: NO | M151: YES, IR and Customer's form | N151: 45225 | O151: ML NAIC CAVITE
A152: ML Transaction Query 400 | B152: '202310270300010281 | C152: BPP47722778737510 | D152: LAZADA INC | E152: '0061000128053 | F152: 45226 | G152: 0.6694213 | H152: 16687.57 | I152: 4000 | J152: OVERSTATED AMOUNT PHP 16,687.57 INSTEAD OF PHP 12,687.57 WITH THE DIFFERENCE OF PHP 4,000.00. | K152: Correct Amount should only be PHP 12,687.57 | L152: NO | M152: YES, IR and Customer's form | N152: 45227 | O152: ML PANDACAQUI
A153: ML Transaction Query 406 | B153: '202311150300009657 | C153: BPP00521591851311 | D153: LAZADA INC | E153: '0061000128053 | F153: 45245.602 | G153: 0.60190972 | H153: 8000 | I153: 8000 | J153: DOUBLE POSTING | K153: Correct Transaction '202311150300009967 / BPP00521563765611 | L153: YES | M153: YES, IR and Reprocessed Receipt | N153: 45251 | O153: ML SAN MIGUEL 2
A154: ML Transaction Query 407 | B154: '202311070300009786 | C154: BPP58550734133011 | D154: LAZADA INC LAZADA INC | E154: '0061000128053 | F154: 45237.749 | G154: 0.7487037 | H154: 16998.32 | I154: 16998.32 | J154: NO PAYMENT RECEIVED FROM THE CUSTOMER | K154: Branch operator returned the payment due to error on our end. | L154: NO | M154: YES, IR and No Printed receipt due to error | N154: 45252 | O154: ML BASAK TOWN CENTER
A155: ML Transaction Query 408 | B155: '202311210300006458 | C155: BPP08682139957711 | D155: LAZADA INC LAZADA INC | E155: '0061000128053 | F155: 45251.603 | G155: 0.60329861 | H155: 10362.86 | I155: 10362.86 | J155: DOUBLE POSTING | K155: Correct Transaction '202311210300006884 / BPP08682141892511 | L155: YES | M155: YES, IR and Reprocessed Receipt | N155: 45253 | O155: ML ANGONO 2
A156: ML Transaction Query 409 | B156: '202311210300012344 | C156: BPP57122165490511 | D156: INC LAZADA | E156: '0061000128053 | F156: 45251.767 | G156: 0.76677083 | H156: 25970 | I156: 25710.3 | J156: OVERSTATED AMOUNT PHP 25,970.00 INSTEAD OF PHP 259.70 WITH THE DIFFERENCE OF PHP 25,710.30. | K156: Correct Amount should only be PHP 259.70 | L156: NO | M156: YES, IR, Customer's form and Receipt | N156: 45255 | O156: ML NAIC CAVITE
A157: ML Transaction Query 410 | B157: '202311280300007810 | C157: BPP18422820812811 | D157: INCI LAZADA | E157: '0061000128053 | F157: 45258.634 | G157: 0.63409722 | H157: 32028.91 | I157: 9000 | J157: OVERSTATED AMOUNT PHP 32,028.91 INSTEAD OF PHP 23,028.91 WITH THE DIFFERENCE OF PHP 9,000. | K157: Correct Amount should only be PHP 23,028.91 | L157: NO | M157: YES, IR, Customer's form and Receipt | N157: 45259 | O157: ML DR. A. SANTOS AVENUE
A158: ML Transaction Query 411 | B158: '202311170300008423 | C158: BPP89321797272911 | D158: LAZADA INC | E158: '0061000128053 | F158: 45247.687 | G158: 0.68726852 | H158: 2204.63 | I158: 2204.63 | J158: NO PAYMENT RECEIVED FROM THE CUSTOMER | K158: Branch operator returned the payment due to error on our end. | L158: NO | M158: YES, IR and No Printed receipt due to error | N158: 45260 | O158: ML PENARANDA
A159: ML Transaction Query 412 | B159: '202311240300008552 | C159: BPP98322457918811 | D159: LAZADA INC LAZADA INC | E159: '0061000128053 | F159: 45254.66 | G159: 0.66040509 | H159: 13978.07 | I159: 13978.07 | J159: DOUBLE POSTING | K159: Correct Transaction '202311240300008634 / BPP98322471131711 | L159: YES | M159: YES, IR and Reprocessed Receipt | N159: 45260 | O159: ML TUY
A160: ML Transaction Query 413 | B160: '202311290300013133 | C160: BPP58222916707011 | D160: SECURITY LAZADA | E160: '0061000128053 | F160: 45259.681 | G160: 0.68074074 | H160: 13846.5 | I160: 13846.5 | J160: DOUBLE POSTING | K160: Correct Transaction '202311290300013222 / BPP58222997760011 | L160: YES | M160: YES, IR and Reprocessed Receipt | N160: 45261 | O160: ML LAS PINAS - (REAL)
A161: ML Transaction Query 414 | B161: '202311180300005795 | C161: BPP72521865058311 | D161: LAZADA LAZADA | E161: '0061000128053 | F161: 45248.701 | G161: 0.70079861 | H161: 4282.54 | I161: 4282.54 | J161: DOUBLE POSTING | K161: Correct Transaction '202311180300005714 / BPP72521899444911 | L161: YES | M161: YES, IR and Reprocessed Receipt | N161: 45261 | O161: ML SAN ILDEFONSO
... A166: ML Transaction Query 426 | B166: '202401030300393364 | C166: BPP32020342433001 | D166: LAZADA INC | E166: '0061000128053 | F166: 45294.674 | G166: 0.67434028 | H166: 43263.58 | I166: 43263.58 | J166: NO PAYMENT RECEIVED FROM THE CUSTOMER | K166: Branch operator returned the payment due to error on our end. | L166: BANK SECURITY | M166: YES, IR and No Printed receipt due to error | N166: 45302 | O166: ML SAN JOSE, ANGELES CITY
A167: ML Transaction Query 435 | B167: '202312300300362118 | C167: BPP57523075588512 | D167: SECURITY BANK LAZADA SECURITY BANK LAZADA | E167: '0061000128053 | F167: 45290.57 | G167: 1:40:24 PM | H167: 8364.51 | I167: 8364.51 | J167: NO PAYMENT RECEIVED FROM THE CUSTOMER | K167: Branch operator returned the payment due to error on our end. | L167: NO | M167: YES, IR and No Printed receipt due to error | N167: 45310 | O167: ML ROSARIO 2
A168: ML Transaction Query 439 | B168: '202401180300532327 | C168: BPP29221828695201 | D168: BANK SECURITY | E168: '0061000128053 | F168: 45309.625 | G168: 0.62517361 | H168: 5548.04 | I168: 100 | J168: OVERSTATED AMOUNT PHP 5548.04 INSTEAD OF PHP 5448.04 WITH THE DIFFERENCE OF PHP 100. | K168: Correct Amount should only be PHP 5448.04 | L168: NO | M168: YES, IR, Customer's form and Receipt | N168: 45316 | O168: ML MENDEZ
...

Sheet OTHER PARTNERS
A1: As of July 31, 2025
A3: Transaction Date | B3: Branch | C3: Region | D3: BPP Reference Number | E3: Biller/Accnt Name/Accnt Number/Amount | F3: Correct Biller Company | G3: IR Number | H3: Correct Amount | I3: PARTNERS NAME | J3: Amount for Refund | K3: Total /BP | L3: Reason for Cancellation | M3: REMARKS | N3: OPERATOR
A4: 44012 | B4: ML Totolan | C4: BOHOL | D4: BPP48953084679406 | E4: PLDT/LISA GOMI/792743161 | F4: GLOBE INNOVE | G4: 99-489-2007-0028 | H4: 1900 | I4: PLDT | J4: 1900 | L4: WRONG BILLER | N4: MARI
A5: 44093 | B5: ML Caloocan 3 Libis | C5: NCR North | D5: bpp51721953336609 | E5: PLDT/, JOHN RUCKER L ZETA/0287449607 | G5: 68-513-2009-0004 | H5: 1399 | I5: PLDT | J5: 1399 | L5: their connection was already been cut before he inform the branch | M5: PER PARTNER- CUSTOMER STILL HAVE A BALANCE | N5: christine joy
A6: 44362 | B6: ML Tabok | C6: CebuNorth A | D6: BPP50251516799406 | E6: PLDT/LUCIA CUBAR/656788895 | F6: GLOBE INNOVE | G6: 01-063-2106-0008 | H6: 1700 | I6: PLDT | J6: 1700 | L6: WRONG BILLER/ACCOUNT #: 882893889 | N6: JO ANN
A7: 44425 | B7: BOHOL | C7: ML Ubay | D7: BPP14311799295208 | E7: PLDT/MARIA CELSA BOAQUIN/0384122728 | G7: 99-143-2108-0028 | H7: 1399 | I7: PLDT | J7: 1399 | L7: WRONG ACCOUNT #/FOR REFUND CUSTOMER ALREADY PAID FOR THE CORRECT ACCOUNT # | N7: MAY CHIEL
A8: 44643 | B8: ML Palawan 4 | C8: PALAWAN | D8: BPP36252334724203 | E8: PLDT/MADRONADO, MYLENE/0324812083 | G8: 26-362-2203-0014 | H8: 1866 | I8: PLDT | J8: 1866 | L8: DOUBLE POSTED DUE TO SYSTEM ERROR | N8: GERV20216442
A9: 44646 | B9: ML Malingao | C9: Lanao | D9: BPP78212647468303 | E9: PLDT/BOLIVER, CRISELDA T./0286899447 | G9: 22-782-2203-0007 | H9: 1399 | I9: PLDT | J9: 1399 | L9: DOUBLE POSTED / SYSTEM ERROR | N9: JASON
A10: 44648 | B10: ML Jamindan | C10: PANAY Central | D10: BPP67912860159403 | E10: PLDT/VALZADO, FRANKLIN /0246946906 | G10: 24-679-2206-0002 | H10: 1450 | I10: PLDT | J10: 1450 | L10: DOUBLE PROCESS/SYSTEM ERROR | N10: JENNIFER
A11: 44648 | B11: ML Tumauini | C11: NorthernLuzon | D11: BPP81622881262303 | E11: PLDT/MAXIMA CABASAG/0318642052 | G11: 56-816-2203-0033 | H11: 1400 | I11: PLDT | J11: 1400 | L11: UNPAID TRANSACTION DUE TO SYSTEM ERROR | N11: MARIBEL MARAYAG
A12: 44669 | B12: ML Don Carlos | C12: CagayanDeOro | D12: BPP52811843228804 | E12: PLDT/JERRY S CANOY/0264630185 | G12: 09-528-2204-0021 | H12: 3799 | I12: PLDT | J12: 3799 | L12: DOUBLE PROCESS/SYSTEM ERROR | N12: MARK KARRY
A13: 44701 | B13: ML Lipata | D13: BPP83912018601805 | E13: PLDT/OUANO, CELSO/0288484252 | G13: 03-839-2205-0021 | H13: 1800 | I13: PLDT | J13: 1800 | L13: DOUBLE PROCESS/SYSTEM ERROR | N13: SHANE
A14: 44703 | B14: ML Mandaue 1 | C14: CebuNorth A | D14: BPP05812291552305 | E14: PLDT/SOON, ROSARIO/0310306800 | G14: 02-058-2205-0043 | H14: 1699 | I14: PLDT | J14: 1699 | L14: DOUBLE PROCESS DUE TO SYSTEM ERROR | N14: JADE
A15: 44705 | B15: ML Mahayahay Iligan | D15: BPP18660759456405 | E15: PLDT/ MECHANIZED, BRIGADE/0239088945 | G15: 22-186-2205-0003 | H15: 2204 | I15: PLDT | J15: 8321 | L15: WRONG AMOUNT: 2,204.00 (SHOULD BE 5 TRANSACTIONS WITH DIFF ACC NUMBER) | N15: JANISSA
A16: 44714 | B16: ML Boulevard | D16: BPP58360290327906 | E16: PLDT/DOTILLOS, JOHN JURY S/0253785950 | G16: 08-583-2206-0001 | H16: 1310 | I16: PLDT | J16: 1310 | L16: TRIPLE PROCESS/SYSTEM ERROR | N16: JOSIE
A17: 44744 | B17: ML San Isidro 2 | C17: NortheasternLuzon | D17: BPP26920258774207 | E17: PLDT/MARITES R LAGAT/024810764 | G17: 57-269-2207-0002 | H17: 1300 | I17: PLDT | J17: 1300 | L17: DOUBLE POSTED FOR CANCELLATION/ REFUND | N17: LUZ PAJARILLO
A18: 44862 | B18: ML NLSA Lagao | C18: SARGEN | D18: BPP22662891864810 | E18: GABO JR, VICTOR/0345180109 | G18: 25-226-2210-0022 | H18: 1789 | I18: PLDT | J18: 1789 | L18: DOUBLE ENTRY | N18: NANCY
A19: 44868 | B19: ML Araneta | C19: Negros Occidental A | D19: BPP16310394056211 | E19: SALUSADA, ARLAN/0296136689 | G19: 13-175-2301-0005 | H19: 1399 | I19: PLDT | J19: 1399 | L19: DOUBLE PROCESS/SYSTEM ERROR | N19: SILV18097441
A20: 44875 | B20: ML Calumpang 1 | D20: BPP64111033694711 | E20: PARRENAS, JUVY ANN/330705035 | H20: 1472 | I20: PLDT | J20: 1472
A21: 44879 | B21: ML Sta. Catalina | C21: NEGOR/SIQ | D21: BPP15911467793711 | E21: CALDERON,MIGUELA/0289491546 | G21: 17-159-2211-0013 | H21: 1699 | I21: PLDT | J21: 1699 | L21: DOUBLE POSTED | N21: SUSEME
A22: 44880 | B22: ML Trento | C22: CARAGA Sur | D22: BPP43011586713211 | E22: BAUTISTA, GLADYS P/0328972522 | G22: 20-430-2211-0021 | H22: 1300 | I22: PLDT | J22: 1300 | L22: SYSTEM ERROR | N22: IAN JADE
A23: 44883 | B23: ML Gensan 3 | C23: SARGEN | D23: BPP37511849118411 | E23: JERMIA, ANGELICA/0290023777 | G23: 25-375-2211-0028 | H23: 1299 | I23: PLDT | J23: 11601 | L23: WRONG AMOUNT | N23: RANDY
A24: 44883 | B24: ML Cotabato 6 | C24: Cotabato-Maguindanao | D24: BPP96811852493211 | E24: TOTI, AFRAEM/0277843536 | G24: 18-968-2211-0020 | H24: 1999 | I24: PLDT | J24: 1999 | L24: DOUBLE POSTED | N24: JENELLA BABES
A25: 44894 | B25: ML Mialim | C25: ZambaSulta | D25: BPP14762923940911 | E25: ALVAREZ,RANDY/0344889171 | G25: 14-147-2212-0007 | H25: 765 | I25: PLDT | J25: 765 | L25: FOR REFUND/CUSTOMER ALREADY PAID TO PLDT HEAD OFFICE | N25: ROBERT
A26: 44922 | B26: ML Madrid | C26: CARAGA Sur | D26: BPP43412713942412 | E26: PUTONG, FLORENTINA/0348008625 | G26: 20-434-2212-0012 | H26: 650 | I26: PLDT | J26: 650 | L26: DOUBLE POST DUE TO SYSTEM ERROR | N26: LUTCHEL
A27: 44933 | B27: ML MIA Road Paranaque | C27: NCRBatanes | D27: BPP01980774861201 | E27: SALMASAN, DANTE P/0290172527 | G27: 53-019-2301-0006 | H27: 1799 | I27: PLDT | J27: 1799 | L27: WRONG AMOUNT OVERSTATED REQUEST FOR CANCELLATION | N27: JEFFREY BAUL
A28: 44942 | B28: ML Ayala | C28: ZambaSulta | D28: BPP83111692870701 | E28: HAMJA , ALHASSAN A/0329379825 | G28: 14-831-2301-0002 | H28: 1704 | I28: PLDT | J28: 1704 | L28: WRONG AMOUNT | N28: MERLY
A29: 44946 | B29: ML Sarmiento Parang | C29: Cotabato-Maguindanao | D29: BPP08562061014101 | E29: MENOR, EDUARDO/0325302607 | G29: 18-085-2301-0007 | H29: 1849 | I29: PLDT | J29: 1849 | L29: DOUBLE POSTED | N29: MARY JOY
A30: 44948 | B30: ML Pasil | C30: CebuCentral A | D30: BPP04052269523701 | E30: AGUILAR, GALILEO A/0023849569 | G30: 01-040-2301-0015 | H30: 1850 | I30: PLDT | J30: 1850 | L30: WRONG AMOUNT | N30: BANT94013885
A31: 44957 | B31: ML Hindang | C31: LEYTE A | D31: BPP63413187301701 | E31: FADRI ALICIA/0326331112 | G31: 04-634-2301-0022 | H31: 1800 | I31: PLDT | J31: 1800 | L31: WRONG AMOUNT | N31: FLORA MAE
A32: 44959 | B32: ML Bankal | C32: CebuNorth A | D32: BPP42550268695802 | E32: DELOS SANTOS, LORECIL/0250819773 | G32: 02-425-2302-0002 | H32: 1300 | I32: PLDT | J32: 1300 | L32: DOUBLE POSTED | N32: JOYLYN
... A37: 44986 | B37: ML Jaro 3 | C37: PANAY South | D37: BPP26110181641403 | E37: ALMEDA, JEHANS EMMANUELLE/0309691229 | G37: 07-261-2302-0002 | H37: 1750 | I37: PLDT | J37: 1750 | L37: DOUBLE PROCESS/SYSTEM ERROR | N37: MERRY
A38: 45028 | B38: ML Bamban | D38: BPP42621111732304 | E38: SOLEDAD CAPINDING/030114167 | G38: 62-426-2304-0003 | H38: 1399 | I38: PLDT | J38: 1399 | K38: =SUM(J4:J38) -> 74656 | L38: customer req. for refund due to disconnected
A39: 44673 | B39: ML Cabancalan | D39: BPP69952236842904 | E39: TALARA, GENARO LEGASPO | F39: 176817 | I39: MCWD | J39: 488 | L39: Double Posting (encountered an error)
